]633;E;echo '--- util bytecode ---';5e05cbc2-be75-4ebf-a560-a096caa82795]633;C--- util bytecode ---
public class com.fs.util.ooOOOOOOOOOOOOOOOOOOOOOOOOOOOOOOOOOOOOOOOOOOOOOOOOOOOOOOOOOOOOOOOOOOOOOOOOOOOOOOOOOOOOOOOOOOOOOOOOOOOOOOOOOOOOOOOOOOOOOOOOOOOOOOOOOOOOOOOOOOOOOOOOOOOOOOOOOOOOOOOOOOOOOOOOOOOOOOOOOOOOOOOOOOOOOOOOOOOOOOOOOOOOOOOOOOOOOOOOOOOOOOOOOOOOOOOOOOOOOOOOOOOOOOOOOOOOOO {
  private static com.fs.util.ooOOOOOOOOOOOOOOOOOOOOOOOOOOOOOOOOOOOOOOOOOOOOOOOOOOOOOOOOOOOOOOOOOOOOOOOOOOOOOOOOOOOOOOOOOOOOOOOOOOOOOOOOOOOOOOOOOOOOOOOOOOOOOOOOOOOOOOOOOOOOOOOOOOOOOOOOOOOOOOOOOOOOOOOOOOOOOOOOOOOOOOOOOOOOOOOOOOOOOOOOOOOOOOOOOOOOOOOOOOOOOOOOOOOOOOOOOOOOOOOOOOOOOOOOOOOOOO Object;

  private java.util.List<com.fs.util.ooOOOOOOOOOOOOOOOOOOOOOOOOOOOOOOOOOOOOOOOOOOOOOOOOOOOOOOOOOOOOOOOOOOOOOOOOOOOOOOOOOOOOOOOOOOOOOOOOOOOOOOOOOOOOOOOOOOOOOOOOOOOOOOOOOOOOOOOOOOOOOOOOOOOOOOOOOOOOOOOOOOOOOOOOOOOOOOOOOOOOOOOOOOOOOOOOOOOOOOOOOOOOOOOOOOOOOOOOOOOOOOOOOOOOOOOOOOOOOOOOOOOOOOOOOOOOOO$Oo> Ò00000;

  private java.lang.String Ô00000;

  public static boolean o00000;

  private static volatile int[] Õ00000;

  static {};
    Code:
       0: aconst_null
       1: putstatic     #20                 // Field Object:Lcom/fs/util/ooOOOOOOOOOOOOOOOOOOOOOOOOOOOOOOOOOOOOOOOOOOOOOOOOOOOOOOOOOOOOOOOOOOOOOOOOOOOOOOOOOOOOOOOOOOOOOOOOOOOOOOOOOOOOOOOOOOOOOOOOOOOOOOOOOOOOOOOOOOOOOOOOOOOOOOOOOOOOOOOOOOOOOOOOOOOOOOOOOOOOOOOOOOOOOOOOOOOOOOOOOOOOOOOOOOOOOOOOOOOOOOOOOOOOOOOOOOOOOOOOOOOOOOOOOOOOOO;
       4: iconst_0
       5: putstatic     #22                 // Field o00000:Z
       8: return

  public com.fs.util.ooOOOOOOOOOOOOOOOOOOOOOOOOOOOOOOOOOOOOOOOOOOOOOOOOOOOOOOOOOOOOOOOOOOOOOOOOOOOOOOOOOOOOOOOOOOOOOOOOOOOOOOOOOOOOOOOOOOOOOOOOOOOOOOOOOOOOOOOOOOOOOOOOOOOOOOOOOOOOOOOOOOOOOOOOOOOOOOOOOOOOOOOOOOOOOOOOOOOOOOOOOOOOOOOOOOOOOOOOOOOOOOOOOOOOOOOOOOOOOOOOOOOOOOOOOOOOOO();
    Code:
       0: aload_0
       1: invokespecial #27                 // Method java/lang/Object."<init>":()V
       4: aload_0
       5: new           #29                 // class java/util/ArrayList
       8: dup
       9: invokespecial #31                 // Method java/util/ArrayList."<init>":()V
      12: putfield      #32                 // Field Ò00000:Ljava/util/List;
      15: aload_0
      16: aconst_null
      17: putfield      #34                 // Field Ô00000:Ljava/lang/String;
      20: return

  public static synchronized com.fs.util.ooOOOOOOOOOOOOOOOOOOOOOOOOOOOOOOOOOOOOOOOOOOOOOOOOOOOOOOOOOOOOOOOOOOOOOOOOOOOOOOOOOOOOOOOOOOOOOOOOOOOOOOOOOOOOOOOOOOOOOOOOOOOOOOOOOOOOOOOOOOOOOOOOOOOOOOOOOOOOOOOOOOOOOOOOOOOOOOOOOOOOOOOOOOOOOOOOOOOOOOOOOOOOOOOOOOOOOOOOOOOOOOOOOOOOOOOOOOOOOOOOOOOOOOOOOOOOOO Ó00000();
    Code:
       0: getstatic     #20                 // Field Object:Lcom/fs/util/ooOOOOOOOOOOOOOOOOOOOOOOOOOOOOOOOOOOOOOOOOOOOOOOOOOOOOOOOOOOOOOOOOOOOOOOOOOOOOOOOOOOOOOOOOOOOOOOOOOOOOOOOOOOOOOOOOOOOOOOOOOOOOOOOOOOOOOOOOOOOOOOOOOOOOOOOOOOOOOOOOOOOOOOOOOOOOOOOOOOOOOOOOOOOOOOOOOOOOOOOOOOOOOOOOOOOOOOOOOOOOOOOOOOOOOOOOOOOOOOOOOOOOOOOOOOOOOO;
       3: ifnonnull     16
       6: new           #1                  // class com/fs/util/ooOOOOOOOOOOOOOOOOOOOOOOOOOOOOOOOOOOOOOOOOOOOOOOOOOOOOOOOOOOOOOOOOOOOOOOOOOOOOOOOOOOOOOOOOOOOOOOOOOOOOOOOOOOOOOOOOOOOOOOOOOOOOOOOOOOOOOOOOOOOOOOOOOOOOOOOOOOOOOOOOOOOOOOOOOOOOOOOOOOOOOOOOOOOOOOOOOOOOOOOOOOOOOOOOOOOOOOOOOOOOOOOOOOOOOOOOOOOOOOOOOOOOOOOOOOOOOO
       9: dup
      10: invokespecial #39                 // Method "<init>":()V
      13: putstatic     #20                 // Field Object:Lcom/fs/util/ooOOOOOOOOOOOOOOOOOOOOOOOOOOOOOOOOOOOOOOOOOOOOOOOOOOOOOOOOOOOOOOOOOOOOOOOOOOOOOOOOOOOOOOOOOOOOOOOOOOOOOOOOOOOOOOOOOOOOOOOOOOOOOOOOOOOOOOOOOOOOOOOOOOOOOOOOOOOOOOOOOOOOOOOOOOOOOOOOOOOOOOOOOOOOOOOOOOOOOOOOOOOOOOOOOOOOOOOOOOOOOOOOOOOOOOOOOOOOOOOOOOOOOOOOOOOOOO;
      16: getstatic     #20                 // Field Object:Lcom/fs/util/ooOOOOOOOOOOOOOOOOOOOOOOOOOOOOOOOOOOOOOOOOOOOOOOOOOOOOOOOOOOOOOOOOOOOOOOOOOOOOOOOOOOOOOOOOOOOOOOOOOOOOOOOOOOOOOOOOOOOOOOOOOOOOOOOOOOOOOOOOOOOOOOOOOOOOOOOOOOOOOOOOOOOOOOOOOOOOOOOOOOOOOOOOOOOOOOOOOOOOOOOOOOOOOOOOOOOOOOOOOOOOOOOOOOOOOOOOOOOOOOOOOOOOOOOOOOOOOO;
      19: areturn

  public synchronized void Õ00000(java.lang.String);
    Code:
       0: aload_0
       1: getfield      #32                 // Field Ò00000:Ljava/util/List;
       4: new           #43                 // class com/fs/util/ooOOOOOOOOOOOOOOOOOOOOOOOOOOOOOOOOOOOOOOOOOOOOOOOOOOOOOOOOOOOOOOOOOOOOOOOOOOOOOOOOOOOOOOOOOOOOOOOOOOOOOOOOOOOOOOOOOOOOOOOOOOOOOOOOOOOOOOOOOOOOOOOOOOOOOOOOOOOOOOOOOOOOOOOOOOOOOOOOOOOOOOOOOOOOOOOOOOOOOOOOOOOOOOOOOOOOOOOOOOOOOOOOOOOOOOOOOOOOOOOOOOOOOOOOOOOOOO$Oo
       7: dup
       8: getstatic     #45                 // Field com/fs/util/ooOOOOOOOOOOOOOOOOOOOOOOOOOOOOOOOOOOOOOOOOOOOOOOOOOOOOOOOOOOOOOOOOOOOOOOOOOOOOOOOOOOOOOOOOOOOOOOOOOOOOOOOOOOOOOOOOOOOOOOOOOOOOOOOOOOOOOOOOOOOOOOOOOOOOOOOOOOOOOOOOOOOOOOOOOOOOOOOOOOOOOOOOOOOOOOOOOOOOOOOOOOOOOOOOOOOOOOOOOOOOOOOOOOOOOOOOOOOOOOOOOOOOOOOOOOOOOO$o.Ô00000:Lcom/fs/util/ooOOOOOOOOOOOOOOOOOOOOOOOOOOOOOOOOOOOOOOOOOOOOOOOOOOOOOOOOOOOOOOOOOOOOOOOOOOOOOOOOOOOOOOOOOOOOOOOOOOOOOOOOOOOOOOOOOOOOOOOOOOOOOOOOOOOOOOOOOOOOOOOOOOOOOOOOOOOOOOOOOOOOOOOOOOOOOOOOOOOOOOOOOOOOOOOOOOOOOOOOOOOOOOOOOOOOOOOOOOOOOOOOOOOOOOOOOOOOOOOOOOOOOOOOOOOOOO$o;
      11: aload_1
      12: invokespecial #51                 // Method com/fs/util/ooOOOOOOOOOOOOOOOOOOOOOOOOOOOOOOOOOOOOOOOOOOOOOOOOOOOOOOOOOOOOOOOOOOOOOOOOOOOOOOOOOOOOOOOOOOOOOOOOOOOOOOOOOOOOOOOOOOOOOOOOOOOOOOOOOOOOOOOOOOOOOOOOOOOOOOOOOOOOOOOOOOOOOOOOOOOOOOOOOOOOOOOOOOOOOOOOOOOOOOOOOOOOOOOOOOOOOOOOOOOOOOOOOOOOOOOOOOOOOOOOOOOOOOOOOOOOOO$Oo."<init>":(Lcom/fs/util/ooOOOOOOOOOOOOOOOOOOOOOOOOOOOOOOOOOOOOOOOOOOOOOOOOOOOOOOOOOOOOOOOOOOOOOOOOOOOOOOOOOOOOOOOOOOOOOOOOOOOOOOOOOOOOOOOOOOOOOOOOOOOOOOOOOOOOOOOOOOOOOOOOOOOOOOOOOOOOOOOOOOOOOOOOOOOOOOOOOOOOOOOOOOOOOOOOOOOOOOOOOOOOOOOOOOOOOOOOOOOOOOOOOOOOOOOOOOOOOOOOOOOOOOOOOOOOOO$o;Ljava/lang/String;)V
      15: invokeinterface #54,  2           // InterfaceMethod java/util/List.add:(Ljava/lang/Object;)Z
      20: pop
      21: return

  public synchronized void super(java.lang.String, boolean, java.lang.Object);
    Code:
       0: aload_0
       1: getfield      #32                 // Field Ò00000:Ljava/util/List;
       4: iconst_0
       5: new           #43                 // class com/fs/util/ooOOOOOOOOOOOOOOOOOOOOOOOOOOOOOOOOOOOOOOOOOOOOOOOOOOOOOOOOOOOOOOOOOOOOOOOOOOOOOOOOOOOOOOOOOOOOOOOOOOOOOOOOOOOOOOOOOOOOOOOOOOOOOOOOOOOOOOOOOOOOOOOOOOOOOOOOOOOOOOOOOOOOOOOOOOOOOOOOOOOOOOOOOOOOOOOOOOOOOOOOOOOOOOOOOOOOOOOOOOOOOOOOOOOOOOOOOOOOOOOOOOOOOOOOOOOOOO$Oo
       8: dup
       9: getstatic     #45                 // Field com/fs/util/ooOOOOOOOOOOOOOOOOOOOOOOOOOOOOOOOOOOOOOOOOOOOOOOOOOOOOOOOOOOOOOOOOOOOOOOOOOOOOOOOOOOOOOOOOOOOOOOOOOOOOOOOOOOOOOOOOOOOOOOOOOOOOOOOOOOOOOOOOOOOOOOOOOOOOOOOOOOOOOOOOOOOOOOOOOOOOOOOOOOOOOOOOOOOOOOOOOOOOOOOOOOOOOOOOOOOOOOOOOOOOOOOOOOOOOOOOOOOOOOOOOOOOOOOOOOOOOO$o.Ô00000:Lcom/fs/util/ooOOOOOOOOOOOOOOOOOOOOOOOOOOOOOOOOOOOOOOOOOOOOOOOOOOOOOOOOOOOOOOOOOOOOOOOOOOOOOOOOOOOOOOOOOOOOOOOOOOOOOOOOOOOOOOOOOOOOOOOOOOOOOOOOOOOOOOOOOOOOOOOOOOOOOOOOOOOOOOOOOOOOOOOOOOOOOOOOOOOOOOOOOOOOOOOOOOOOOOOOOOOOOOOOOOOOOOOOOOOOOOOOOOOOOOOOOOOOOOOOOOOOOOOOOOOOOO$o;
      12: aload_1
      13: iload_2
      14: aload_3
      15: invokespecial #63                 // Method com/fs/util/ooOOOOOOOOOOOOOOOOOOOOOOOOOOOOOOOOOOOOOOOOOOOOOOOOOOOOOOOOOOOOOOOOOOOOOOOOOOOOOOOOOOOOOOOOOOOOOOOOOOOOOOOOOOOOOOOOOOOOOOOOOOOOOOOOOOOOOOOOOOOOOOOOOOOOOOOOOOOOOOOOOOOOOOOOOOOOOOOOOOOOOOOOOOOOOOOOOOOOOOOOOOOOOOOOOOOOOOOOOOOOOOOOOOOOOOOOOOOOOOOOOOOOOOOOOOOOOO$Oo."<init>":(Lcom/fs/util/ooOOOOOOOOOOOOOOOOOOOOOOOOOOOOOOOOOOOOOOOOOOOOOOOOOOOOOOOOOOOOOOOOOOOOOOOOOOOOOOOOOOOOOOOOOOOOOOOOOOOOOOOOOOOOOOOOOOOOOOOOOOOOOOOOOOOOOOOOOOOOOOOOOOOOOOOOOOOOOOOOOOOOOOOOOOOOOOOOOOOOOOOOOOOOOOOOOOOOOOOOOOOOOOOOOOOOOOOOOOOOOOOOOOOOOOOOOOOOOOOOOOOOOOOOOOOOOO$o;Ljava/lang/String;ZLjava/lang/Object;)V
      18: invokeinterface #66,  3           // InterfaceMethod java/util/List.add:(ILjava/lang/Object;)V
      23: return

  public synchronized void Ò00000();
    Code:
       0: aload_0
       1: getfield      #32                 // Field Ò00000:Ljava/util/List;
       4: new           #43                 // class com/fs/util/ooOOOOOOOOOOOOOOOOOOOOOOOOOOOOOOOOOOOOOOOOOOOOOOOOOOOOOOOOOOOOOOOOOOOOOOOOOOOOOOOOOOOOOOOOOOOOOOOOOOOOOOOOOOOOOOOOOOOOOOOOOOOOOOOOOOOOOOOOOOOOOOOOOOOOOOOOOOOOOOOOOOOOOOOOOOOOOOOOOOOOOOOOOOOOOOOOOOOOOOOOOOOOOOOOOOOOOOOOOOOOOOOOOOOOOOOOOOOOOOOOOOOOOOOOOOOOOO$Oo
       7: dup
       8: getstatic     #73                 // Field com/fs/util/ooOOOOOOOOOOOOOOOOOOOOOOOOOOOOOOOOOOOOOOOOOOOOOOOOOOOOOOOOOOOOOOOOOOOOOOOOOOOOOOOOOOOOOOOOOOOOOOOOOOOOOOOOOOOOOOOOOOOOOOOOOOOOOOOOOOOOOOOOOOOOOOOOOOOOOOOOOOOOOOOOOOOOOOOOOOOOOOOOOOOOOOOOOOOOOOOOOOOOOOOOOOOOOOOOOOOOOOOOOOOOOOOOOOOOOOOOOOOOOOOOOOOOOOOOOOOOOO$o.o00000:Lcom/fs/util/ooOOOOOOOOOOOOOOOOOOOOOOOOOOOOOOOOOOOOOOOOOOOOOOOOOOOOOOOOOOOOOOOOOOOOOOOOOOOOOOOOOOOOOOOOOOOOOOOOOOOOOOOOOOOOOOOOOOOOOOOOOOOOOOOOOOOOOOOOOOOOOOOOOOOOOOOOOOOOOOOOOOOOOOOOOOOOOOOOOOOOOOOOOOOOOOOOOOOOOOOOOOOOOOOOOOOOOOOOOOOOOOOOOOOOOOOOOOOOOOOOOOOOOOOOOOOOOO$o;
      11: aconst_null
      12: invokespecial #51                 // Method com/fs/util/ooOOOOOOOOOOOOOOOOOOOOOOOOOOOOOOOOOOOOOOOOOOOOOOOOOOOOOOOOOOOOOOOOOOOOOOOOOOOOOOOOOOOOOOOOOOOOOOOOOOOOOOOOOOOOOOOOOOOOOOOOOOOOOOOOOOOOOOOOOOOOOOOOOOOOOOOOOOOOOOOOOOOOOOOOOOOOOOOOOOOOOOOOOOOOOOOOOOOOOOOOOOOOOOOOOOOOOOOOOOOOOOOOOOOOOOOOOOOOOOOOOOOOOOOOOOOOOO$Oo."<init>":(Lcom/fs/util/ooOOOOOOOOOOOOOOOOOOOOOOOOOOOOOOOOOOOOOOOOOOOOOOOOOOOOOOOOOOOOOOOOOOOOOOOOOOOOOOOOOOOOOOOOOOOOOOOOOOOOOOOOOOOOOOOOOOOOOOOOOOOOOOOOOOOOOOOOOOOOOOOOOOOOOOOOOOOOOOOOOOOOOOOOOOOOOOOOOOOOOOOOOOOOOOOOOOOOOOOOOOOOOOOOOOOOOOOOOOOOOOOOOOOOOOOOOOOOOOOOOOOOOOOOOOOOOO$o;Ljava/lang/String;)V
      15: invokeinterface #54,  2           // InterfaceMethod java/util/List.add:(Ljava/lang/Object;)Z
      20: pop
      21: return

  public synchronized void Õ00000();
    Code:
       0: aload_0
       1: getfield      #32                 // Field Ò00000:Ljava/util/List;
       4: new           #43                 // class com/fs/util/ooOOOOOOOOOOOOOOOOOOOOOOOOOOOOOOOOOOOOOOOOOOOOOOOOOOOOOOOOOOOOOOOOOOOOOOOOOOOOOOOOOOOOOOOOOOOOOOOOOOOOOOOOOOOOOOOOOOOOOOOOOOOOOOOOOOOOOOOOOOOOOOOOOOOOOOOOOOOOOOOOOOOOOOOOOOOOOOOOOOOOOOOOOOOOOOOOOOOOOOOOOOOOOOOOOOOOOOOOOOOOOOOOOOOOOOOOOOOOOOOOOOOOOOOOOOOOOO$Oo
       7: dup
       8: getstatic     #77                 // Field com/fs/util/ooOOOOOOOOOOOOOOOOOOOOOOOOOOOOOOOOOOOOOOOOOOOOOOOOOOOOOOOOOOOOOOOOOOOOOOOOOOOOOOOOOOOOOOOOOOOOOOOOOOOOOOOOOOOOOOOOOOOOOOOOOOOOOOOOOOOOOOOOOOOOOOOOOOOOOOOOOOOOOOOOOOOOOOOOOOOOOOOOOOOOOOOOOOOOOOOOOOOOOOOOOOOOOOOOOOOOOOOOOOOOOOOOOOOOOOOOOOOOOOOOOOOOOOOOOOOOOO$o.Object:Lcom/fs/util/ooOOOOOOOOOOOOOOOOOOOOOOOOOOOOOOOOOOOOOOOOOOOOOOOOOOOOOOOOOOOOOOOOOOOOOOOOOOOOOOOOOOOOOOOOOOOOOOOOOOOOOOOOOOOOOOOOOOOOOOOOOOOOOOOOOOOOOOOOOOOOOOOOOOOOOOOOOOOOOOOOOOOOOOOOOOOOOOOOOOOOOOOOOOOOOOOOOOOOOOOOOOOOOOOOOOOOOOOOOOOOOOOOOOOOOOOOOOOOOOOOOOOOOOOOOOOOOO$o;
      11: aconst_null
      12: invokespecial #51                 // Method com/fs/util/ooOOOOOOOOOOOOOOOOOOOOOOOOOOOOOOOOOOOOOOOOOOOOOOOOOOOOOOOOOOOOOOOOOOOOOOOOOOOOOOOOOOOOOOOOOOOOOOOOOOOOOOOOOOOOOOOOOOOOOOOOOOOOOOOOOOOOOOOOOOOOOOOOOOOOOOOOOOOOOOOOOOOOOOOOOOOOOOOOOOOOOOOOOOOOOOOOOOOOOOOOOOOOOOOOOOOOOOOOOOOOOOOOOOOOOOOOOOOOOOOOOOOOOOOOOOOOOO$Oo."<init>":(Lcom/fs/util/ooOOOOOOOOOOOOOOOOOOOOOOOOOOOOOOOOOOOOOOOOOOOOOOOOOOOOOOOOOOOOOOOOOOOOOOOOOOOOOOOOOOOOOOOOOOOOOOOOOOOOOOOOOOOOOOOOOOOOOOOOOOOOOOOOOOOOOOOOOOOOOOOOOOOOOOOOOOOOOOOOOOOOOOOOOOOOOOOOOOOOOOOOOOOOOOOOOOOOOOOOOOOOOOOOOOOOOOOOOOOOOOOOOOOOOOOOOOOOOOOOOOOOOOOOOOOOOO$o;Ljava/lang/String;)V
      15: invokeinterface #54,  2           // InterfaceMethod java/util/List.add:(Ljava/lang/Object;)Z
      20: pop
      21: return

  public synchronized java.util.List<com.fs.util.ooOOOOOOOOOOOOOOOOOOOOOOOOOOOOOOOOOOOOOOOOOOOOOOOOOOOOOOOOOOOOOOOOOOOOOOOOOOOOOOOOOOOOOOOOOOOOOOOOOOOOOOOOOOOOOOOOOOOOOOOOOOOOOOOOOOOOOOOOOOOOOOOOOOOOOOOOOOOOOOOOOOOOOOOOOOOOOOOOOOOOOOOOOOOOOOOOOOOOOOOOOOOOOOOOOOOOOOOOOOOOOOOOOOOOOOOOOOOOOOOOOOOOOOOOOOOOOO$Oo> String();
    Code:
       0: aload_0
       1: getfield      #32                 // Field Ò00000:Ljava/util/List;
       4: areturn

  public synchronized java.io.InputStream String(java.lang.String) throws java.io.IOException;
    Code:
       0: aload_0
       1: aload_1
       2: iconst_1
       3: invokevirtual #88                 // Method Ó00000:(Ljava/lang/String;Z)Ljava/io/InputStream;
       6: areturn

  public synchronized void Ö00000(java.lang.String);
    Code:
       0: aload_0
       1: aload_1
       2: putfield      #34                 // Field Ô00000:Ljava/lang/String;
       5: return

  public synchronized java.io.InputStream Ó00000(java.lang.String, boolean) throws java.io.IOException;
    Code:
       0: aload_0
       1: getfield      #34                 // Field Ô00000:Ljava/lang/String;
       4: astore_3
       5: aload_0
       6: aconst_null
       7: putfield      #34                 // Field Ô00000:Ljava/lang/String;
      10: getstatic     #22                 // Field o00000:Z
      13: ifeq          22
      16: iconst_0
      17: istore_2
      18: iconst_0
      19: putstatic     #22                 // Field o00000:Z
      22: ldc           #94                 // String
      24: astore        4
      26: aload_0
      27: getfield      #32                 // Field Ò00000:Ljava/util/List;
      30: invokeinterface #96,  1           // InterfaceMethod java/util/List.iterator:()Ljava/util/Iterator;
      35: astore        6
      37: goto          209
      40: aload         6
      42: invokeinterface #100,  1          // InterfaceMethod java/util/Iterator.next:()Ljava/lang/Object;
      47: checkcast     #43                 // class com/fs/util/ooOOOOOOOOOOOOOOOOOOOOOOOOOOOOOOOOOOOOOOOOOOOOOOOOOOOOOOOOOOOOOOOOOOOOOOOOOOOOOOOOOOOOOOOOOOOOOOOOOOOOOOOOOOOOOOOOOOOOOOOOOOOOOOOOOOOOOOOOOOOOOOOOOOOOOOOOOOOOOOOOOOOOOOOOOOOOOOOOOOOOOOOOOOOOOOOOOOOOOOOOOOOOOOOOOOOOOOOOOOOOOOOOOOOOOOOOOOOOOOOOOOOOOOOOOOOOOO$Oo
      50: astore        5
      52: iload_2
      53: ifne          67
      56: aload         5
      58: getfield      #106                // Field com/fs/util/ooOOOOOOOOOOOOOOOOOOOOOOOOOOOOOOOOOOOOOOOOOOOOOOOOOOOOOOOOOOOOOOOOOOOOOOOOOOOOOOOOOOOOOOOOOOOOOOOOOOOOOOOOOOOOOOOOOOOOOOOOOOOOOOOOOOOOOOOOOOOOOOOOOOOOOOOOOOOOOOOOOOOOOOOOOOOOOOOOOOOOOOOOOOOOOOOOOOOOOOOOOOOOOOOOOOOOOOOOOOOOOOOOOOOOOOOOOOOOOOOOOOOOOOOOOOOOOO$Oo.String:Z
      61: ifeq          67
      64: goto          209
      67: invokestatic  #108                // Method super:()[I
      70: aload         5
      72: getfield      #111                // Field com/fs/util/ooOOOOOOOOOOOOOOOOOOOOOOOOOOOOOOOOOOOOOOOOOOOOOOOOOOOOOOOOOOOOOOOOOOOOOOOOOOOOOOOOOOOOOOOOOOOOOOOOOOOOOOOOOOOOOOOOOOOOOOOOOOOOOOOOOOOOOOOOOOOOOOOOOOOOOOOOOOOOOOOOOOOOOOOOOOOOOOOOOOOOOOOOOOOOOOOOOOOOOOOOOOOOOOOOOOOOOOOOOOOOOOOOOOOOOOOOOOOOOOOOOOOOOOOOOOOOOO$Oo.super:Lcom/fs/util/ooOOOOOOOOOOOOOOOOOOOOOOOOOOOOOOOOOOOOOOOOOOOOOOOOOOOOOOOOOOOOOOOOOOOOOOOOOOOOOOOOOOOOOOOOOOOOOOOOOOOOOOOOOOOOOOOOOOOOOOOOOOOOOOOOOOOOOOOOOOOOOOOOOOOOOOOOOOOOOOOOOOOOOOOOOOOOOOOOOOOOOOOOOOOOOOOOOOOOOOOOOOOOOOOOOOOOOOOOOOOOOOOOOOOOOOOOOOOOOOOOOOOOOOOOOOOOOO$o;
      75: invokevirtual #114                // Method com/fs/util/ooOOOOOOOOOOOOOOOOOOOOOOOOOOOOOOOOOOOOOOOOOOOOOOOOOOOOOOOOOOOOOOOOOOOOOOOOOOOOOOOOOOOOOOOOOOOOOOOOOOOOOOOOOOOOOOOOOOOOOOOOOOOOOOOOOOOOOOOOOOOOOOOOOOOOOOOOOOOOOOOOOOOOOOOOOOOOOOOOOOOOOOOOOOOOOOOOOOOOOOOOOOOOOOOOOOOOOOOOOOOOOOOOOOOOOOOOOOOOOOOOOOOOOOOOOOOOOO$o.ordinal:()I
      78: iaload
      79: tableswitch   { // 1 to 3
                     1: 132
                     2: 104
                     3: 107
               default: 162
          }
     104: goto          162
     107: new           #118                // class java/lang/StringBuilder
     110: dup
     111: aload         4
     113: invokestatic  #120                // Method java/lang/String.valueOf:(Ljava/lang/Object;)Ljava/lang/String;
     116: invokespecial #126                // Method java/lang/StringBuilder."<init>":(Ljava/lang/String;)V
     119: ldc           #128                // String CLASSPATH,
     121: invokevirtual #130                // Method java/lang/StringBuilder.append:(Ljava/lang/String;)Ljava/lang/StringBuilder;
     124: invokevirtual #134                // Method java/lang/StringBuilder.toString:()Ljava/lang/String;
     127: astore        4
     129: goto          162
     132: new           #118                // class java/lang/StringBuilder
     135: dup
     136: aload         4
     138: invokestatic  #120                // Method java/lang/String.valueOf:(Ljava/lang/Object;)Ljava/lang/String;
     141: invokespecial #126                // Method java/lang/StringBuilder."<init>":(Ljava/lang/String;)V
     144: aload         5
     146: getfield      #138                // Field com/fs/util/ooOOOOOOOOOOOOOOOOOOOOOOOOOOOOOOOOOOOOOOOOOOOOOOOOOOOOOOOOOOOOOOOOOOOOOOOOOOOOOOOOOOOOOOOOOOOOOOOOOOOOOOOOOOOOOOOOOOOOOOOOOOOOOOOOOOOOOOOOOOOOOOOOOOOOOOOOOOOOOOOOOOOOOOOOOOOOOOOOOOOOOOOOOOOOOOOOOOOOOOOOOOOOOOOOOOOOOOOOOOOOOOOOOOOOOOOOOOOOOOOOOOOOOOOOOOOOOO$Oo.Ó00000:Ljava/lang/String;
     149: invokevirtual #130                // Method java/lang/StringBuilder.append:(Ljava/lang/String;)Ljava/lang/StringBuilder;
     152: ldc           #140                // String ,
     154: invokevirtual #130                // Method java/lang/StringBuilder.append:(Ljava/lang/String;)Ljava/lang/StringBuilder;
     157: invokevirtual #134                // Method java/lang/StringBuilder.toString:()Ljava/lang/String;
     160: astore        4
     162: aload_3
     163: ifnull        192
     166: aload         5
     168: getfield      #111                // Field com/fs/util/ooOOOOOOOOOOOOOOOOOOOOOOOOOOOOOOOOOOOOOOOOOOOOOOOOOOOOOOOOOOOOOOOOOOOOOOOOOOOOOOOOOOOOOOOOOOOOOOOOOOOOOOOOOOOOOOOOOOOOOOOOOOOOOOOOOOOOOOOOOOOOOOOOOOOOOOOOOOOOOOOOOOOOOOOOOOOOOOOOOOOOOOOOOOOOOOOOOOOOOOOOOOOOOOOOOOOOOOOOOOOOOOOOOOOOOOOOOOOOOOOOOOOOOOOOOOOOOO$Oo.super:Lcom/fs/util/ooOOOOOOOOOOOOOOOOOOOOOOOOOOOOOOOOOOOOOOOOOOOOOOOOOOOOOOOOOOOOOOOOOOOOOOOOOOOOOOOOOOOOOOOOOOOOOOOOOOOOOOOOOOOOOOOOOOOOOOOOOOOOOOOOOOOOOOOOOOOOOOOOOOOOOOOOOOOOOOOOOOOOOOOOOOOOOOOOOOOOOOOOOOOOOOOOOOOOOOOOOOOOOOOOOOOOOOOOOOOOOOOOOOOOOOOOOOOOOOOOOOOOOOOOOOOOOO$o;
     171: getstatic     #45                 // Field com/fs/util/ooOOOOOOOOOOOOOOOOOOOOOOOOOOOOOOOOOOOOOOOOOOOOOOOOOOOOOOOOOOOOOOOOOOOOOOOOOOOOOOOOOOOOOOOOOOOOOOOOOOOOOOOOOOOOOOOOOOOOOOOOOOOOOOOOOOOOOOOOOOOOOOOOOOOOOOOOOOOOOOOOOOOOOOOOOOOOOOOOOOOOOOOOOOOOOOOOOOOOOOOOOOOOOOOOOOOOOOOOOOOOOOOOOOOOOOOOOOOOOOOOOOOOOOOOOOOOOO$o.Ô00000:Lcom/fs/util/ooOOOOOOOOOOOOOOOOOOOOOOOOOOOOOOOOOOOOOOOOOOOOOOOOOOOOOOOOOOOOOOOOOOOOOOOOOOOOOOOOOOOOOOOOOOOOOOOOOOOOOOOOOOOOOOOOOOOOOOOOOOOOOOOOOOOOOOOOOOOOOOOOOOOOOOOOOOOOOOOOOOOOOOOOOOOOOOOOOOOOOOOOOOOOOOOOOOOOOOOOOOOOOOOOOOOOOOOOOOOOOOOOOOOOOOOOOOOOOOOOOOOOOOOOOOOOOO$o;
     174: if_acmpne     209
     177: aload         5
     179: getfield      #138                // Field com/fs/util/ooOOOOOOOOOOOOOOOOOOOOOOOOOOOOOOOOOOOOOOOOOOOOOOOOOOOOOOOOOOOOOOOOOOOOOOOOOOOOOOOOOOOOOOOOOOOOOOOOOOOOOOOOOOOOOOOOOOOOOOOOOOOOOOOOOOOOOOOOOOOOOOOOOOOOOOOOOOOOOOOOOOOOOOOOOOOOOOOOOOOOOOOOOOOOOOOOOOOOOOOOOOOOOOOOOOOOOOOOOOOOOOOOOOOOOOOOOOOOOOOOOOOOOOOOOOOOOO$Oo.Ó00000:Ljava/lang/String;
     182: aload_3
     183: invokevirtual #142                // Method java/lang/String.endsWith:(Ljava/lang/String;)Z
     186: ifne          192
     189: goto          209
     192: aload_0
     193: aload_1
     194: aload         5
     196: invokevirtual #146                // Method String:(Ljava/lang/String;Lcom/fs/util/ooOOOOOOOOOOOOOOOOOOOOOOOOOOOOOOOOOOOOOOOOOOOOOOOOOOOOOOOOOOOOOOOOOOOOOOOOOOOOOOOOOOOOOOOOOOOOOOOOOOOOOOOOOOOOOOOOOOOOOOOOOOOOOOOOOOOOOOOOOOOOOOOOOOOOOOOOOOOOOOOOOOOOOOOOOOOOOOOOOOOOOOOOOOOOOOOOOOOOOOOOOOOOOOOOOOOOOOOOOOOOOOOOOOOOOOOOOOOOOOOOOOOOOOOOOOOOOO$Oo;)Ljava/io/InputStream;
     199: astore        7
     201: aload         7
     203: ifnull        209
     206: aload         7
     208: areturn
     209: aload         6
     211: invokeinterface #150,  1          // InterfaceMethod java/util/Iterator.hasNext:()Z
     216: ifne          40
     219: aload         4
     221: iconst_0
     222: aload         4
     224: invokevirtual #154                // Method java/lang/String.length:()I
     227: iconst_1
     228: isub
     229: invokevirtual #157                // Method java/lang/String.substring:(II)Ljava/lang/String;
     232: astore        4
     234: new           #161                // class java/lang/RuntimeException
     237: dup
     238: new           #118                // class java/lang/StringBuilder
     241: dup
     242: ldc           #163                // String Error loading [
     244: invokespecial #126                // Method java/lang/StringBuilder."<init>":(Ljava/lang/String;)V
     247: aload_1
     248: invokevirtual #130                // Method java/lang/StringBuilder.append:(Ljava/lang/String;)Ljava/lang/StringBuilder;
     251: ldc           #165                // String ] resource, not found in [
     253: invokevirtual #130                // Method java/lang/StringBuilder.append:(Ljava/lang/String;)Ljava/lang/StringBuilder;
     256: aload         4
     258: invokevirtual #130                // Method java/lang/StringBuilder.append:(Ljava/lang/String;)Ljava/lang/StringBuilder;
     261: ldc           #167                // String ]
     263: invokevirtual #130                // Method java/lang/StringBuilder.append:(Ljava/lang/String;)Ljava/lang/StringBuilder;
     266: invokevirtual #134                // Method java/lang/StringBuilder.toString:()Ljava/lang/String;
     269: invokespecial #169                // Method java/lang/RuntimeException."<init>":(Ljava/lang/String;)V
     272: athrow

  public synchronized long Ò00000(java.lang.String, boolean) throws java.io.IOException;
    Code:
       0: aload_0
       1: getfield      #32                 // Field Ò00000:Ljava/util/List;
       4: invokeinterface #96,  1           // InterfaceMethod java/util/List.iterator:()Ljava/util/Iterator;
       9: astore        4
      11: goto          57
      14: aload         4
      16: invokeinterface #100,  1          // InterfaceMethod java/util/Iterator.next:()Ljava/lang/Object;
      21: checkcast     #43                 // class com/fs/util/ooOOOOOOOOOOOOOOOOOOOOOOOOOOOOOOOOOOOOOOOOOOOOOOOOOOOOOOOOOOOOOOOOOOOOOOOOOOOOOOOOOOOOOOOOOOOOOOOOOOOOOOOOOOOOOOOOOOOOOOOOOOOOOOOOOOOOOOOOOOOOOOOOOOOOOOOOOOOOOOOOOOOOOOOOOOOOOOOOOOOOOOOOOOOOOOOOOOOOOOOOOOOOOOOOOOOOOOOOOOOOOOOOOOOOOOOOOOOOOOOOOOOOOOOOOOOOOO$Oo
      24: astore_3
      25: iload_2
      26: ifne          39
      29: aload_3
      30: getfield      #106                // Field com/fs/util/ooOOOOOOOOOOOOOOOOOOOOOOOOOOOOOOOOOOOOOOOOOOOOOOOOOOOOOOOOOOOOOOOOOOOOOOOOOOOOOOOOOOOOOOOOOOOOOOOOOOOOOOOOOOOOOOOOOOOOOOOOOOOOOOOOOOOOOOOOOOOOOOOOOOOOOOOOOOOOOOOOOOOOOOOOOOOOOOOOOOOOOOOOOOOOOOOOOOOOOOOOOOOOOOOOOOOOOOOOOOOOOOOOOOOOOOOOOOOOOOOOOOOOOOOOOOOOOO$Oo.String:Z
      33: ifeq          39
      36: goto          57
      39: aload_0
      40: aload_1
      41: aload_3
      42: invokevirtual #178                // Method Ò00000:(Ljava/lang/String;Lcom/fs/util/ooOOOOOOOOOOOOOOOOOOOOOOOOOOOOOOOOOOOOOOOOOOOOOOOOOOOOOOOOOOOOOOOOOOOOOOOOOOOOOOOOOOOOOOOOOOOOOOOOOOOOOOOOOOOOOOOOOOOOOOOOOOOOOOOOOOOOOOOOOOOOOOOOOOOOOOOOOOOOOOOOOOOOOOOOOOOOOOOOOOOOOOOOOOOOOOOOOOOOOOOOOOOOOOOOOOOOOOOOOOOOOOOOOOOOOOOOOOOOOOOOOOOOOOOOOOOOOO$Oo;)J
      45: lstore        5
      47: lload         5
      49: lconst_0
      50: lcmp
      51: ifeq          57
      54: lload         5
      56: lreturn
      57: aload         4
      59: invokeinterface #150,  1          // InterfaceMethod java/util/Iterator.hasNext:()Z
      64: ifne          14
      67: lconst_0
      68: lreturn

  public synchronized long Ò00000(java.lang.String, com.fs.util.ooOOOOOOOOOOOOOOOOOOOOOOOOOOOOOOOOOOOOOOOOOOOOOOOOOOOOOOOOOOOOOOOOOOOOOOOOOOOOOOOOOOOOOOOOOOOOOOOOOOOOOOOOOOOOOOOOOOOOOOOOOOOOOOOOOOOOOOOOOOOOOOOOOOOOOOOOOOOOOOOOOOOOOOOOOOOOOOOOOOOOOOOOOOOOOOOOOOOOOOOOOOOOOOOOOOOOOOOOOOOOOOOOOOOOOOOOOOOOOOOOOOOOOOOOOOOOOO$Oo) throws java.io.FileNotFoundException;
    Code:
       0: invokestatic  #108                // Method super:()[I
       3: aload_2
       4: getfield      #111                // Field com/fs/util/ooOOOOOOOOOOOOOOOOOOOOOOOOOOOOOOOOOOOOOOOOOOOOOOOOOOOOOOOOOOOOOOOOOOOOOOOOOOOOOOOOOOOOOOOOOOOOOOOOOOOOOOOOOOOOOOOOOOOOOOOOOOOOOOOOOOOOOOOOOOOOOOOOOOOOOOOOOOOOOOOOOOOOOOOOOOOOOOOOOOOOOOOOOOOOOOOOOOOOOOOOOOOOOOOOOOOOOOOOOOOOOOOOOOOOOOOOOOOOOOOOOOOOOOOOOOOOOO$Oo.super:Lcom/fs/util/ooOOOOOOOOOOOOOOOOOOOOOOOOOOOOOOOOOOOOOOOOOOOOOOOOOOOOOOOOOOOOOOOOOOOOOOOOOOOOOOOOOOOOOOOOOOOOOOOOOOOOOOOOOOOOOOOOOOOOOOOOOOOOOOOOOOOOOOOOOOOOOOOOOOOOOOOOOOOOOOOOOOOOOOOOOOOOOOOOOOOOOOOOOOOOOOOOOOOOOOOOOOOOOOOOOOOOOOOOOOOOOOOOOOOOOOOOOOOOOOOOOOOOOOOOOOOOOO$o;
       7: invokevirtual #114                // Method com/fs/util/ooOOOOOOOOOOOOOOOOOOOOOOOOOOOOOOOOOOOOOOOOOOOOOOOOOOOOOOOOOOOOOOOOOOOOOOOOOOOOOOOOOOOOOOOOOOOOOOOOOOOOOOOOOOOOOOOOOOOOOOOOOOOOOOOOOOOOOOOOOOOOOOOOOOOOOOOOOOOOOOOOOOOOOOOOOOOOOOOOOOOOOOOOOOOOOOOOOOOOOOOOOOOOOOOOOOOOOOOOOOOOOOOOOOOOOOOOOOOOOOOOOOOOOOOOOOOOOO$o.ordinal:()I
      10: iaload
      11: tableswitch   { // 1 to 3
                     1: 59
                     2: 36
                     3: 57
               default: 105
          }
      36: new           #185                // class java/io/File
      39: dup
      40: aload_1
      41: invokespecial #187                // Method java/io/File."<init>":(Ljava/lang/String;)V
      44: astore_3
      45: aload_3
      46: invokevirtual #188                // Method java/io/File.exists:()Z
      49: ifeq          105
      52: aload_3
      53: invokevirtual #191                // Method java/io/File.lastModified:()J
      56: lreturn
      57: lconst_0
      58: lreturn
      59: new           #185                // class java/io/File
      62: dup
      63: new           #118                // class java/lang/StringBuilder
      66: dup
      67: aload_2
      68: getfield      #138                // Field com/fs/util/ooOOOOOOOOOOOOOOOOOOOOOOOOOOOOOOOOOOOOOOOOOOOOOOOOOOOOOOOOOOOOOOOOOOOOOOOOOOOOOOOOOOOOOOOOOOOOOOOOOOOOOOOOOOOOOOOOOOOOOOOOOOOOOOOOOOOOOOOOOOOOOOOOOOOOOOOOOOOOOOOOOOOOOOOOOOOOOOOOOOOOOOOOOOOOOOOOOOOOOOOOOOOOOOOOOOOOOOOOOOOOOOOOOOOOOOOOOOOOOOOOOOOOOOOOOOOOOO$Oo.Ó00000:Ljava/lang/String;
      71: invokestatic  #120                // Method java/lang/String.valueOf:(Ljava/lang/Object;)Ljava/lang/String;
      74: invokespecial #126                // Method java/lang/StringBuilder."<init>":(Ljava/lang/String;)V
      77: ldc           #194                // String /
      79: invokevirtual #130                // Method java/lang/StringBuilder.append:(Ljava/lang/String;)Ljava/lang/StringBuilder;
      82: aload_1
      83: invokevirtual #130                // Method java/lang/StringBuilder.append:(Ljava/lang/String;)Ljava/lang/StringBuilder;
      86: invokevirtual #134                // Method java/lang/StringBuilder.toString:()Ljava/lang/String;
      89: invokespecial #187                // Method java/io/File."<init>":(Ljava/lang/String;)V
      92: astore_3
      93: aload_3
      94: invokevirtual #188                // Method java/io/File.exists:()Z
      97: ifeq          105
     100: aload_3
     101: invokevirtual #191                // Method java/io/File.lastModified:()J
     104: lreturn
     105: lconst_0
     106: lreturn

  public synchronized java.util.List<com.fs.util.container.Pair<com.fs.util.ooOOOOOOOOOOOOOOOOOOOOOOOOOOOOOOOOOOOOOOOOOOOOOOOOOOOOOOOOOOOOOOOOOOOOOOOOOOOOOOOOOOOOOOOOOOOOOOOOOOOOOOOOOOOOOOOOOOOOOOOOOOOOOOOOOOOOOOOOOOOOOOOOOOOOOOOOOOOOOOOOOOOOOOOOOOOOOOOOOOOOOOOOOOOOOOOOOOOOOOOOOOOOOOOOOOOOOOOOOOOOOOOOOOOOOOOOOOOOOOOOOOOOOOOOOOOOOO$Oo, java.io.InputStream>> Ò00000(java.lang.String) throws java.io.IOException;
    Code:
       0: new           #29                 // class java/util/ArrayList
       3: dup
       4: invokespecial #31                 // Method java/util/ArrayList."<init>":()V
       7: astore_2
       8: ldc           #94                 // String
      10: astore_3
      11: iconst_0
      12: istore        4
      14: aload_0
      15: getfield      #32                 // Field Ò00000:Ljava/util/List;
      18: invokeinterface #96,  1           // InterfaceMethod java/util/List.iterator:()Ljava/util/Iterator;
      23: astore        6
      25: goto          235
      28: aload         6
      30: invokeinterface #100,  1          // InterfaceMethod java/util/Iterator.next:()Ljava/lang/Object;
      35: checkcast     #43                 // class com/fs/util/ooOOOOOOOOOOOOOOOOOOOOOOOOOOOOOOOOOOOOOOOOOOOOOOOOOOOOOOOOOOOOOOOOOOOOOOOOOOOOOOOOOOOOOOOOOOOOOOOOOOOOOOOOOOOOOOOOOOOOOOOOOOOOOOOOOOOOOOOOOOOOOOOOOOOOOOOOOOOOOOOOOOOOOOOOOOOOOOOOOOOOOOOOOOOOOOOOOOOOOOOOOOOOOOOOOOOOOOOOOOOOOOOOOOOOOOOOOOOOOOOOOOOOOOOOOOOOOO$Oo
      38: astore        5
      40: iconst_0
      41: istore        7
      43: invokestatic  #108                // Method super:()[I
      46: aload         5
      48: getfield      #111                // Field com/fs/util/ooOOOOOOOOOOOOOOOOOOOOOOOOOOOOOOOOOOOOOOOOOOOOOOOOOOOOOOOOOOOOOOOOOOOOOOOOOOOOOOOOOOOOOOOOOOOOOOOOOOOOOOOOOOOOOOOOOOOOOOOOOOOOOOOOOOOOOOOOOOOOOOOOOOOOOOOOOOOOOOOOOOOOOOOOOOOOOOOOOOOOOOOOOOOOOOOOOOOOOOOOOOOOOOOOOOOOOOOOOOOOOOOOOOOOOOOOOOOOOOOOOOOOOOOOOOOOOO$Oo.super:Lcom/fs/util/ooOOOOOOOOOOOOOOOOOOOOOOOOOOOOOOOOOOOOOOOOOOOOOOOOOOOOOOOOOOOOOOOOOOOOOOOOOOOOOOOOOOOOOOOOOOOOOOOOOOOOOOOOOOOOOOOOOOOOOOOOOOOOOOOOOOOOOOOOOOOOOOOOOOOOOOOOOOOOOOOOOOOOOOOOOOOOOOOOOOOOOOOOOOOOOOOOOOOOOOOOOOOOOOOOOOOOOOOOOOOOOOOOOOOOOOOOOOOOOOOOOOOOOOOOOOOOOO$o;
      51: invokevirtual #114                // Method com/fs/util/ooOOOOOOOOOOOOOOOOOOOOOOOOOOOOOOOOOOOOOOOOOOOOOOOOOOOOOOOOOOOOOOOOOOOOOOOOOOOOOOOOOOOOOOOOOOOOOOOOOOOOOOOOOOOOOOOOOOOOOOOOOOOOOOOOOOOOOOOOOOOOOOOOOOOOOOOOOOOOOOOOOOOOOOOOOOOOOOOOOOOOOOOOOOOOOOOOOOOOOOOOOOOOOOOOOOOOOOOOOOOOOOOOOOOOOOOOOOOOOOOOOOOOOOOOOOOOOO$o.ordinal:()I
      54: iaload
      55: tableswitch   { // 1 to 3
                     1: 112
                     2: 80
                     3: 86
               default: 140
          }
      80: iconst_1
      81: istore        7
      83: goto          140
      86: iconst_1
      87: istore        7
      89: new           #118                // class java/lang/StringBuilder
      92: dup
      93: aload_3
      94: invokestatic  #120                // Method java/lang/String.valueOf:(Ljava/lang/Object;)Ljava/lang/String;
      97: invokespecial #126                // Method java/lang/StringBuilder."<init>":(Ljava/lang/String;)V
     100: ldc           #128                // String CLASSPATH,
     102: invokevirtual #130                // Method java/lang/StringBuilder.append:(Ljava/lang/String;)Ljava/lang/StringBuilder;
     105: invokevirtual #134                // Method java/lang/StringBuilder.toString:()Ljava/lang/String;
     108: astore_3
     109: goto          140
     112: new           #118                // class java/lang/StringBuilder
     115: dup
     116: aload_3
     117: invokestatic  #120                // Method java/lang/String.valueOf:(Ljava/lang/Object;)Ljava/lang/String;
     120: invokespecial #126                // Method java/lang/StringBuilder."<init>":(Ljava/lang/String;)V
     123: aload         5
     125: getfield      #138                // Field com/fs/util/ooOOOOOOOOOOOOOOOOOOOOOOOOOOOOOOOOOOOOOOOOOOOOOOOOOOOOOOOOOOOOOOOOOOOOOOOOOOOOOOOOOOOOOOOOOOOOOOOOOOOOOOOOOOOOOOOOOOOOOOOOOOOOOOOOOOOOOOOOOOOOOOOOOOOOOOOOOOOOOOOOOOOOOOOOOOOOOOOOOOOOOOOOOOOOOOOOOOOOOOOOOOOOOOOOOOOOOOOOOOOOOOOOOOOOOOOOOOOOOOOOOOOOOOOOOOOOOO$Oo.Ó00000:Ljava/lang/String;
     128: invokevirtual #130                // Method java/lang/StringBuilder.append:(Ljava/lang/String;)Ljava/lang/StringBuilder;
     131: ldc           #140                // String ,
     133: invokevirtual #130                // Method java/lang/StringBuilder.append:(Ljava/lang/String;)Ljava/lang/StringBuilder;
     136: invokevirtual #134                // Method java/lang/StringBuilder.toString:()Ljava/lang/String;
     139: astore_3
     140: aload_0
     141: aload_1
     142: aload         5
     144: invokevirtual #146                // Method String:(Ljava/lang/String;Lcom/fs/util/ooOOOOOOOOOOOOOOOOOOOOOOOOOOOOOOOOOOOOOOOOOOOOOOOOOOOOOOOOOOOOOOOOOOOOOOOOOOOOOOOOOOOOOOOOOOOOOOOOOOOOOOOOOOOOOOOOOOOOOOOOOOOOOOOOOOOOOOOOOOOOOOOOOOOOOOOOOOOOOOOOOOOOOOOOOOOOOOOOOOOOOOOOOOOOOOOOOOOOOOOOOOOOOOOOOOOOOOOOOOOOOOOOOOOOOOOOOOOOOOOOOOOOOOOOOOOOOO$Oo;)Ljava/io/InputStream;
     147: astore        8
     149: aload         8
     151: ifnull        235
     154: iload         7
     156: ifeq          164
     159: iload         4
     161: ifne          235
     164: iload         7
     166: ifeq          172
     169: iconst_1
     170: istore        4
     172: aload_1
     173: astore        9
     175: aload         5
     177: getfield      #138                // Field com/fs/util/ooOOOOOOOOOOOOOOOOOOOOOOOOOOOOOOOOOOOOOOOOOOOOOOOOOOOOOOOOOOOOOOOOOOOOOOOOOOOOOOOOOOOOOOOOOOOOOOOOOOOOOOOOOOOOOOOOOOOOOOOOOOOOOOOOOOOOOOOOOOOOOOOOOOOOOOOOOOOOOOOOOOOOOOOOOOOOOOOOOOOOOOOOOOOOOOOOOOOOOOOOOOOOOOOOOOOOOOOOOOOOOOOOOOOOOOOOOOOOOOOOOOOOOOOOOOOOOO$Oo.Ó00000:Ljava/lang/String;
     180: ifnull        212
     183: new           #118                // class java/lang/StringBuilder
     186: dup
     187: aload         5
     189: getfield      #138                // Field com/fs/util/ooOOOOOOOOOOOOOOOOOOOOOOOOOOOOOOOOOOOOOOOOOOOOOOOOOOOOOOOOOOOOOOOOOOOOOOOOOOOOOOOOOOOOOOOOOOOOOOOOOOOOOOOOOOOOOOOOOOOOOOOOOOOOOOOOOOOOOOOOOOOOOOOOOOOOOOOOOOOOOOOOOOOOOOOOOOOOOOOOOOOOOOOOOOOOOOOOOOOOOOOOOOOOOOOOOOOOOOOOOOOOOOOOOOOOOOOOOOOOOOOOOOOOOOOOOOOOOO$Oo.Ó00000:Ljava/lang/String;
     192: invokestatic  #120                // Method java/lang/String.valueOf:(Ljava/lang/Object;)Ljava/lang/String;
     195: invokespecial #126                // Method java/lang/StringBuilder."<init>":(Ljava/lang/String;)V
     198: ldc           #194                // String /
     200: invokevirtual #130                // Method java/lang/StringBuilder.append:(Ljava/lang/String;)Ljava/lang/StringBuilder;
     203: aload_1
     204: invokevirtual #130                // Method java/lang/StringBuilder.append:(Ljava/lang/String;)Ljava/lang/StringBuilder;
     207: invokevirtual #134                // Method java/lang/StringBuilder.toString:()Ljava/lang/String;
     210: astore        9
     212: aload         8
     214: ifnull        235
     217: aload_2
     218: new           #201                // class com/fs/util/container/Pair
     221: dup
     222: aload         5
     224: aload         8
     226: invokespecial #203                // Method com/fs/util/container/Pair."<init>":(Ljava/lang/Object;Ljava/lang/Object;)V
     229: invokeinterface #54,  2           // InterfaceMethod java/util/List.add:(Ljava/lang/Object;)Z
     234: pop
     235: aload         6
     237: invokeinterface #150,  1          // InterfaceMethod java/util/Iterator.hasNext:()Z
     242: ifne          28
     245: aload_2
     246: invokeinterface #206,  1          // InterfaceMethod java/util/List.isEmpty:()Z
     251: ifne          256
     254: aload_2
     255: areturn
     256: aload_3
     257: iconst_0
     258: aload_3
     259: invokevirtual #154                // Method java/lang/String.length:()I
     262: iconst_1
     263: isub
     264: invokevirtual #157                // Method java/lang/String.substring:(II)Ljava/lang/String;
     267: astore_3
     268: new           #161                // class java/lang/RuntimeException
     271: dup
     272: new           #118                // class java/lang/StringBuilder
     275: dup
     276: ldc           #163                // String Error loading [
     278: invokespecial #126                // Method java/lang/StringBuilder."<init>":(Ljava/lang/String;)V
     281: aload_1
     282: invokevirtual #130                // Method java/lang/StringBuilder.append:(Ljava/lang/String;)Ljava/lang/StringBuilder;
     285: ldc           #165                // String ] resource, not found in [
     287: invokevirtual #130                // Method java/lang/StringBuilder.append:(Ljava/lang/String;)Ljava/lang/StringBuilder;
     290: aload_3
     291: invokevirtual #130                // Method java/lang/StringBuilder.append:(Ljava/lang/String;)Ljava/lang/StringBuilder;
     294: ldc           #167                // String ]
     296: invokevirtual #130                // Method java/lang/StringBuilder.append:(Ljava/lang/String;)Ljava/lang/StringBuilder;
     299: invokevirtual #134                // Method java/lang/StringBuilder.toString:()Ljava/lang/String;
     302: invokespecial #169                // Method java/lang/RuntimeException."<init>":(Ljava/lang/String;)V
     305: athrow

  public synchronized java.util.List<java.lang.String> super(java.lang.String, java.lang.String, boolean) throws java.io.IOException;
    Code:
       0: iload_3
       1: ifeq          11
       4: aload_0
       5: aload_1
       6: aload_2
       7: invokevirtual #219                // Method super:(Ljava/lang/String;Ljava/lang/String;)Ljava/util/List;
      10: areturn
      11: new           #29                 // class java/util/ArrayList
      14: dup
      15: invokespecial #31                 // Method java/util/ArrayList."<init>":()V
      18: astore        4
      20: aload_0
      21: getfield      #32                 // Field Ò00000:Ljava/util/List;
      24: invokeinterface #96,  1           // InterfaceMethod java/util/List.iterator:()Ljava/util/Iterator;
      29: astore        6
      31: goto          224
      34: aload         6
      36: invokeinterface #100,  1          // InterfaceMethod java/util/Iterator.next:()Ljava/lang/Object;
      41: checkcast     #43                 // class com/fs/util/ooOOOOOOOOOOOOOOOOOOOOOOOOOOOOOOOOOOOOOOOOOOOOOOOOOOOOOOOOOOOOOOOOOOOOOOOOOOOOOOOOOOOOOOOOOOOOOOOOOOOOOOOOOOOOOOOOOOOOOOOOOOOOOOOOOOOOOOOOOOOOOOOOOOOOOOOOOOOOOOOOOOOOOOOOOOOOOOOOOOOOOOOOOOOOOOOOOOOOOOOOOOOOOOOOOOOOOOOOOOOOOOOOOOOOOOOOOOOOOOOOOOOOOOOOOOOOOO$Oo
      44: astore        5
      46: aconst_null
      47: astore        7
      49: invokestatic  #108                // Method super:()[I
      52: aload         5
      54: getfield      #111                // Field com/fs/util/ooOOOOOOOOOOOOOOOOOOOOOOOOOOOOOOOOOOOOOOOOOOOOOOOOOOOOOOOOOOOOOOOOOOOOOOOOOOOOOOOOOOOOOOOOOOOOOOOOOOOOOOOOOOOOOOOOOOOOOOOOOOOOOOOOOOOOOOOOOOOOOOOOOOOOOOOOOOOOOOOOOOOOOOOOOOOOOOOOOOOOOOOOOOOOOOOOOOOOOOOOOOOOOOOOOOOOOOOOOOOOOOOOOOOOOOOOOOOOOOOOOOOOOOOOOOOOOO$Oo.super:Lcom/fs/util/ooOOOOOOOOOOOOOOOOOOOOOOOOOOOOOOOOOOOOOOOOOOOOOOOOOOOOOOOOOOOOOOOOOOOOOOOOOOOOOOOOOOOOOOOOOOOOOOOOOOOOOOOOOOOOOOOOOOOOOOOOOOOOOOOOOOOOOOOOOOOOOOOOOOOOOOOOOOOOOOOOOOOOOOOOOOOOOOOOOOOOOOOOOOOOOOOOOOOOOOOOOOOOOOOOOOOOOOOOOOOOOOOOOOOOOOOOOOOOOOOOOOOOOOOOOOOOOO$o;
      57: invokevirtual #114                // Method com/fs/util/ooOOOOOOOOOOOOOOOOOOOOOOOOOOOOOOOOOOOOOOOOOOOOOOOOOOOOOOOOOOOOOOOOOOOOOOOOOOOOOOOOOOOOOOOOOOOOOOOOOOOOOOOOOOOOOOOOOOOOOOOOOOOOOOOOOOOOOOOOOOOOOOOOOOOOOOOOOOOOOOOOOOOOOOOOOOOOOOOOOOOOOOOOOOOOOOOOOOOOOOOOOOOOOOOOOOOOOOOOOOOOOOOOOOOOOOOOOOOOOOOOOOOOOOOOOOOOOO$o.ordinal:()I
      60: iaload
      61: tableswitch   { // 1 to 3
                     1: 104
                     2: 88
                     3: 101
               default: 140
          }
      88: new           #185                // class java/io/File
      91: dup
      92: aload_1
      93: invokespecial #187                // Method java/io/File."<init>":(Ljava/lang/String;)V
      96: astore        7
      98: goto          140
     101: goto          140
     104: new           #185                // class java/io/File
     107: dup
     108: new           #118                // class java/lang/StringBuilder
     111: dup
     112: aload         5
     114: getfield      #138                // Field com/fs/util/ooOOOOOOOOOOOOOOOOOOOOOOOOOOOOOOOOOOOOOOOOOOOOOOOOOOOOOOOOOOOOOOOOOOOOOOOOOOOOOOOOOOOOOOOOOOOOOOOOOOOOOOOOOOOOOOOOOOOOOOOOOOOOOOOOOOOOOOOOOOOOOOOOOOOOOOOOOOOOOOOOOOOOOOOOOOOOOOOOOOOOOOOOOOOOOOOOOOOOOOOOOOOOOOOOOOOOOOOOOOOOOOOOOOOOOOOOOOOOOOOOOOOOOOOOOOOOOO$Oo.Ó00000:Ljava/lang/String;
     117: invokestatic  #120                // Method java/lang/String.valueOf:(Ljava/lang/Object;)Ljava/lang/String;
     120: invokespecial #126                // Method java/lang/StringBuilder."<init>":(Ljava/lang/String;)V
     123: ldc           #194                // String /
     125: invokevirtual #130                // Method java/lang/StringBuilder.append:(Ljava/lang/String;)Ljava/lang/StringBuilder;
     128: aload_1
     129: invokevirtual #130                // Method java/lang/StringBuilder.append:(Ljava/lang/String;)Ljava/lang/StringBuilder;
     132: invokevirtual #134                // Method java/lang/StringBuilder.toString:()Ljava/lang/String;
     135: invokespecial #187                // Method java/io/File."<init>":(Ljava/lang/String;)V
     138: astore        7
     140: aload         7
     142: ifnull        224
     145: aload         7
     147: invokevirtual #188                // Method java/io/File.exists:()Z
     150: ifeq          224
     153: aload         7
     155: invokevirtual #223                // Method java/io/File.isDirectory:()Z
     158: ifne          164
     161: goto          224
     164: aload         7
     166: new           #226                // class com/fs/util/ooOOOOOOOOOOOOOOOOOOOOOOOOOOOOOOOOOOOOOOOOOOOOOOOOOOOOOOOOOOOOOOOOOOOOOOOOOOOOOOOOOOOOOOOOOOOOOOOOOOOOOOOOOOOOOOOOOOOOOOOOOOOOOOOOOOOOOOOOOOOOOOOOOOOOOOOOOOOOOOOOOOOOOOOOOOOOOOOOOOOOOOOOOOOOOOOOOOOOOOOOOOOOOOOOOOOOOOOOOOOOOOOOOOOOOOOOOOOOOOOOOOOOOOOOOOOOOO$1
     169: dup
     170: aload_0
     171: aload_2
     172: invokespecial #228                // Method com/fs/util/ooOOOOOOOOOOOOOOOOOOOOOOOOOOOOOOOOOOOOOOOOOOOOOOOOOOOOOOOOOOOOOOOOOOOOOOOOOOOOOOOOOOOOOOOOOOOOOOOOOOOOOOOOOOOOOOOOOOOOOOOOOOOOOOOOOOOOOOOOOOOOOOOOOOOOOOOOOOOOOOOOOOOOOOOOOOOOOOOOOOOOOOOOOOOOOOOOOOOOOOOOOOOOOOOOOOOOOOOOOOOOOOOOOOOOOOOOOOOOOOOOOOOOOOOOOOOOOO$1."<init>":(Lcom/fs/util/ooOOOOOOOOOOOOOOOOOOOOOOOOOOOOOOOOOOOOOOOOOOOOOOOOOOOOOOOOOOOOOOOOOOOOOOOOOOOOOOOOOOOOOOOOOOOOOOOOOOOOOOOOOOOOOOOOOOOOOOOOOOOOOOOOOOOOOOOOOOOOOOOOOOOOOOOOOOOOOOOOOOOOOOOOOOOOOOOOOOOOOOOOOOOOOOOOOOOOOOOOOOOOOOOOOOOOOOOOOOOOOOOOOOOOOOOOOOOOOOOOOOOOOOOOOOOOOO;Ljava/lang/String;)V
     175: invokevirtual #231                // Method java/io/File.listFiles:(Ljava/io/FilenameFilter;)[Ljava/io/File;
     178: astore        8
     180: aload         8
     182: dup
     183: astore        12
     185: arraylength
     186: istore        11
     188: iconst_0
     189: istore        10
     191: goto          217
     194: aload         12
     196: iload         10
     198: aaload
     199: astore        9
     201: aload         4
     203: aload         9
     205: invokevirtual #235                // Method java/io/File.getAbsolutePath:()Ljava/lang/String;
     208: invokeinterface #54,  2           // InterfaceMethod java/util/List.add:(Ljava/lang/Object;)Z
     213: pop
     214: iinc          10, 1
     217: iload         10
     219: iload         11
     221: if_icmplt     194
     224: aload         6
     226: invokeinterface #150,  1          // InterfaceMethod java/util/Iterator.hasNext:()Z
     231: ifne          34
     234: aload         4
     236: areturn

  public synchronized java.util.List<java.lang.String> super(java.lang.String, java.lang.String) throws java.io.IOException;
    Code:
       0: new           #248                // class java/util/LinkedHashSet
       3: dup
       4: invokespecial #250                // Method java/util/LinkedHashSet."<init>":()V
       7: astore_3
       8: new           #248                // class java/util/LinkedHashSet
      11: dup
      12: invokespecial #250                // Method java/util/LinkedHashSet."<init>":()V
      15: astore        4
      17: aload_0
      18: getfield      #32                 // Field Ò00000:Ljava/util/List;
      21: invokeinterface #96,  1           // InterfaceMethod java/util/List.iterator:()Ljava/util/Iterator;
      26: astore        6
      28: goto          377
      31: aload         6
      33: invokeinterface #100,  1          // InterfaceMethod java/util/Iterator.next:()Ljava/lang/Object;
      38: checkcast     #43                 // class com/fs/util/ooOOOOOOOOOOOOOOOOOOOOOOOOOOOOOOOOOOOOOOOOOOOOOOOOOOOOOOOOOOOOOOOOOOOOOOOOOOOOOOOOOOOOOOOOOOOOOOOOOOOOOOOOOOOOOOOOOOOOOOOOOOOOOOOOOOOOOOOOOOOOOOOOOOOOOOOOOOOOOOOOOOOOOOOOOOOOOOOOOOOOOOOOOOOOOOOOOOOOOOOOOOOOOOOOOOOOOOOOOOOOOOOOOOOOOOOOOOOOOOOOOOOOOOOOOOOOOO$Oo
      41: astore        5
      43: aconst_null
      44: astore        7
      46: aconst_null
      47: astore        8
      49: invokestatic  #108                // Method super:()[I
      52: aload         5
      54: getfield      #111                // Field com/fs/util/ooOOOOOOOOOOOOOOOOOOOOOOOOOOOOOOOOOOOOOOOOOOOOOOOOOOOOOOOOOOOOOOOOOOOOOOOOOOOOOOOOOOOOOOOOOOOOOOOOOOOOOOOOOOOOOOOOOOOOOOOOOOOOOOOOOOOOOOOOOOOOOOOOOOOOOOOOOOOOOOOOOOOOOOOOOOOOOOOOOOOOOOOOOOOOOOOOOOOOOOOOOOOOOOOOOOOOOOOOOOOOOOOOOOOOOOOOOOOOOOOOOOOOOOOOOOOOOO$Oo.super:Lcom/fs/util/ooOOOOOOOOOOOOOOOOOOOOOOOOOOOOOOOOOOOOOOOOOOOOOOOOOOOOOOOOOOOOOOOOOOOOOOOOOOOOOOOOOOOOOOOOOOOOOOOOOOOOOOOOOOOOOOOOOOOOOOOOOOOOOOOOOOOOOOOOOOOOOOOOOOOOOOOOOOOOOOOOOOOOOOOOOOOOOOOOOOOOOOOOOOOOOOOOOOOOOOOOOOOOOOOOOOOOOOOOOOOOOOOOOOOOOOOOOOOOOOOOOOOOOOOOOOOOOO$o;
      57: invokevirtual #114                // Method com/fs/util/ooOOOOOOOOOOOOOOOOOOOOOOOOOOOOOOOOOOOOOOOOOOOOOOOOOOOOOOOOOOOOOOOOOOOOOOOOOOOOOOOOOOOOOOOOOOOOOOOOOOOOOOOOOOOOOOOOOOOOOOOOOOOOOOOOOOOOOOOOOOOOOOOOOOOOOOOOOOOOOOOOOOOOOOOOOOOOOOOOOOOOOOOOOOOOOOOOOOOOOOOOOOOOOOOOOOOOOOOOOOOOOOOOOOOOOOOOOOOOOOOOOOOOOOOOOOOOOO$o.ordinal:()I
      60: iaload
      61: tableswitch   { // 1 to 3
                     1: 104
                     2: 88
                     3: 101
               default: 147
          }
      88: new           #185                // class java/io/File
      91: dup
      92: aload_1
      93: invokespecial #187                // Method java/io/File."<init>":(Ljava/lang/String;)V
      96: astore        7
      98: goto          147
     101: goto          147
     104: new           #185                // class java/io/File
     107: dup
     108: new           #118                // class java/lang/StringBuilder
     111: dup
     112: aload         5
     114: getfield      #138                // Field com/fs/util/ooOOOOOOOOOOOOOOOOOOOOOOOOOOOOOOOOOOOOOOOOOOOOOOOOOOOOOOOOOOOOOOOOOOOOOOOOOOOOOOOOOOOOOOOOOOOOOOOOOOOOOOOOOOOOOOOOOOOOOOOOOOOOOOOOOOOOOOOOOOOOOOOOOOOOOOOOOOOOOOOOOOOOOOOOOOOOOOOOOOOOOOOOOOOOOOOOOOOOOOOOOOOOOOOOOOOOOOOOOOOOOOOOOOOOOOOOOOOOOOOOOOOOOOOOOOOOOO$Oo.Ó00000:Ljava/lang/String;
     117: invokestatic  #120                // Method java/lang/String.valueOf:(Ljava/lang/Object;)Ljava/lang/String;
     120: invokespecial #126                // Method java/lang/StringBuilder."<init>":(Ljava/lang/String;)V
     123: ldc           #194                // String /
     125: invokevirtual #130                // Method java/lang/StringBuilder.append:(Ljava/lang/String;)Ljava/lang/StringBuilder;
     128: aload_1
     129: invokevirtual #130                // Method java/lang/StringBuilder.append:(Ljava/lang/String;)Ljava/lang/StringBuilder;
     132: invokevirtual #134                // Method java/lang/StringBuilder.toString:()Ljava/lang/String;
     135: invokespecial #187                // Method java/io/File."<init>":(Ljava/lang/String;)V
     138: astore        7
     140: aload         5
     142: getfield      #138                // Field com/fs/util/ooOOOOOOOOOOOOOOOOOOOOOOOOOOOOOOOOOOOOOOOOOOOOOOOOOOOOOOOOOOOOOOOOOOOOOOOOOOOOOOOOOOOOOOOOOOOOOOOOOOOOOOOOOOOOOOOOOOOOOOOOOOOOOOOOOOOOOOOOOOOOOOOOOOOOOOOOOOOOOOOOOOOOOOOOOOOOOOOOOOOOOOOOOOOOOOOOOOOOOOOOOOOOOOOOOOOOOOOOOOOOOOOOOOOOOOOOOOOOOOOOOOOOOOOOOOOOOO$Oo.Ó00000:Ljava/lang/String;
     145: astore        8
     147: aload         7
     149: ifnull        377
     152: aload         7
     154: invokevirtual #188                // Method java/io/File.exists:()Z
     157: ifeq          377
     160: aload         7
     162: invokevirtual #223                // Method java/io/File.isDirectory:()Z
     165: ifne          171
     168: goto          377
     171: aload         7
     173: new           #251                // class com/fs/util/ooOOOOOOOOOOOOOOOOOOOOOOOOOOOOOOOOOOOOOOOOOOOOOOOOOOOOOOOOOOOOOOOOOOOOOOOOOOOOOOOOOOOOOOOOOOOOOOOOOOOOOOOOOOOOOOOOOOOOOOOOOOOOOOOOOOOOOOOOOOOOOOOOOOOOOOOOOOOOOOOOOOOOOOOOOOOOOOOOOOOOOOOOOOOOOOOOOOOOOOOOOOOOOOOOOOOOOOOOOOOOOOOOOOOOOOOOOOOOOOOOOOOOOOOOOOOOOO$2
     176: dup
     177: aload_0
     178: aload_2
     179: invokespecial #253                // Method com/fs/util/ooOOOOOOOOOOOOOOOOOOOOOOOOOOOOOOOOOOOOOOOOOOOOOOOOOOOOOOOOOOOOOOOOOOOOOOOOOOOOOOOOOOOOOOOOOOOOOOOOOOOOOOOOOOOOOOOOOOOOOOOOOOOOOOOOOOOOOOOOOOOOOOOOOOOOOOOOOOOOOOOOOOOOOOOOOOOOOOOOOOOOOOOOOOOOOOOOOOOOOOOOOOOOOOOOOOOOOOOOOOOOOOOOOOOOOOOOOOOOOOOOOOOOOOOOOOOOOO$2."<init>":(Lcom/fs/util/ooOOOOOOOOOOOOOOOOOOOOOOOOOOOOOOOOOOOOOOOOOOOOOOOOOOOOOOOOOOOOOOOOOOOOOOOOOOOOOOOOOOOOOOOOOOOOOOOOOOOOOOOOOOOOOOOOOOOOOOOOOOOOOOOOOOOOOOOOOOOOOOOOOOOOOOOOOOOOOOOOOOOOOOOOOOOOOOOOOOOOOOOOOOOOOOOOOOOOOOOOOOOOOOOOOOOOOOOOOOOOOOOOOOOOOOOOOOOOOOOOOOOOOOOOOOOOOO;Ljava/lang/String;)V
     182: invokevirtual #231                // Method java/io/File.listFiles:(Ljava/io/FilenameFilter;)[Ljava/io/File;
     185: astore        9
     187: aconst_null
     188: astore        10
     190: aload         8
     192: ifnull        209
     195: new           #185                // class java/io/File
     198: dup
     199: aload         8
     201: invokespecial #187                // Method java/io/File."<init>":(Ljava/lang/String;)V
     204: invokevirtual #235                // Method java/io/File.getAbsolutePath:()Ljava/lang/String;
     207: astore        10
     209: aload         9
     211: dup
     212: astore        14
     214: arraylength
     215: istore        13
     217: iconst_0
     218: istore        12
     220: goto          370
     223: aload         14
     225: iload         12
     227: aaload
     228: astore        11
     230: new           #118                // class java/lang/StringBuilder
     233: dup
     234: aload_1
     235: invokestatic  #120                // Method java/lang/String.valueOf:(Ljava/lang/Object;)Ljava/lang/String;
     238: invokespecial #126                // Method java/lang/StringBuilder."<init>":(Ljava/lang/String;)V
     241: ldc           #194                // String /
     243: invokevirtual #130                // Method java/lang/StringBuilder.append:(Ljava/lang/String;)Ljava/lang/StringBuilder;
     246: aload         11
     248: invokevirtual #254                // Method java/io/File.getName:()Ljava/lang/String;
     251: invokevirtual #130                // Method java/lang/StringBuilder.append:(Ljava/lang/String;)Ljava/lang/StringBuilder;
     254: invokevirtual #134                // Method java/lang/StringBuilder.toString:()Ljava/lang/String;
     257: astore        15
     259: aload         4
     261: aload         15
     263: invokeinterface #257,  2          // InterfaceMethod java/util/Set.contains:(Ljava/lang/Object;)Z
     268: ifeq          274
     271: goto          367
     274: aload         4
     276: aload         15
     278: invokeinterface #262,  2          // InterfaceMethod java/util/Set.add:(Ljava/lang/Object;)Z
     283: pop
     284: aload         11
     286: invokevirtual #235                // Method java/io/File.getAbsolutePath:()Ljava/lang/String;
     289: astore        16
     291: aload         10
     293: ifnull        358
     296: aload         16
     298: invokevirtual #154                // Method java/lang/String.length:()I
     301: aload         10
     303: invokevirtual #154                // Method java/lang/String.length:()I
     306: if_icmple     358
     309: aload         16
     311: aload         10
     313: invokevirtual #154                // Method java/lang/String.length:()I
     316: invokevirtual #263                // Method java/lang/String.substring:(I)Ljava/lang/String;
     319: astore        16
     321: aload         16
     323: ldc_w         #266                // String \\
     326: invokevirtual #268                // Method java/lang/String.startsWith:(Ljava/lang/String;)Z
     329: ifeq          340
     332: aload         16
     334: iconst_1
     335: invokevirtual #263                // Method java/lang/String.substring:(I)Ljava/lang/String;
     338: astore        16
     340: aload         16
     342: ldc           #194                // String /
     344: invokevirtual #268                // Method java/lang/String.startsWith:(Ljava/lang/String;)Z
     347: ifeq          358
     350: aload         16
     352: iconst_1
     353: invokevirtual #263                // Method java/lang/String.substring:(I)Ljava/lang/String;
     356: astore        16
     358: aload_3
     359: aload         16
     361: invokeinterface #262,  2          // InterfaceMethod java/util/Set.add:(Ljava/lang/Object;)Z
     366: pop
     367: iinc          12, 1
     370: iload         12
     372: iload         13
     374: if_icmplt     223
     377: aload         6
     379: invokeinterface #150,  1          // InterfaceMethod java/util/Iterator.hasNext:()Z
     384: ifne          31
     387: new           #29                 // class java/util/ArrayList
     390: dup
     391: aload_3
     392: invokespecial #271                // Method java/util/ArrayList."<init>":(Ljava/util/Collection;)V
     395: areturn

  public synchronized java.util.List<java.lang.String> Ó00000(java.lang.String);
    Code:
       0: new           #248                // class java/util/LinkedHashSet
       3: dup
       4: invokespecial #250                // Method java/util/LinkedHashSet."<init>":()V
       7: astore_2
       8: aload_0
       9: getfield      #32                 // Field Ò00000:Ljava/util/List;
      12: invokeinterface #96,  1           // InterfaceMethod java/util/List.iterator:()Ljava/util/Iterator;
      17: astore        4
      19: goto          251
      22: aload         4
      24: invokeinterface #100,  1          // InterfaceMethod java/util/Iterator.next:()Ljava/lang/Object;
      29: checkcast     #43                 // class com/fs/util/ooOOOOOOOOOOOOOOOOOOOOOOOOOOOOOOOOOOOOOOOOOOOOOOOOOOOOOOOOOOOOOOOOOOOOOOOOOOOOOOOOOOOOOOOOOOOOOOOOOOOOOOOOOOOOOOOOOOOOOOOOOOOOOOOOOOOOOOOOOOOOOOOOOOOOOOOOOOOOOOOOOOOOOOOOOOOOOOOOOOOOOOOOOOOOOOOOOOOOOOOOOOOOOOOOOOOOOOOOOOOOOOOOOOOOOOOOOOOOOOOOOOOOOOOOOOOOOO$Oo
      32: astore_3
      33: aconst_null
      34: astore        5
      36: invokestatic  #108                // Method super:()[I
      39: aload_3
      40: getfield      #111                // Field com/fs/util/ooOOOOOOOOOOOOOOOOOOOOOOOOOOOOOOOOOOOOOOOOOOOOOOOOOOOOOOOOOOOOOOOOOOOOOOOOOOOOOOOOOOOOOOOOOOOOOOOOOOOOOOOOOOOOOOOOOOOOOOOOOOOOOOOOOOOOOOOOOOOOOOOOOOOOOOOOOOOOOOOOOOOOOOOOOOOOOOOOOOOOOOOOOOOOOOOOOOOOOOOOOOOOOOOOOOOOOOOOOOOOOOOOOOOOOOOOOOOOOOOOOOOOOOOOOOOOOO$Oo.super:Lcom/fs/util/ooOOOOOOOOOOOOOOOOOOOOOOOOOOOOOOOOOOOOOOOOOOOOOOOOOOOOOOOOOOOOOOOOOOOOOOOOOOOOOOOOOOOOOOOOOOOOOOOOOOOOOOOOOOOOOOOOOOOOOOOOOOOOOOOOOOOOOOOOOOOOOOOOOOOOOOOOOOOOOOOOOOOOOOOOOOOOOOOOOOOOOOOOOOOOOOOOOOOOOOOOOOOOOOOOOOOOOOOOOOOOOOOOOOOOOOOOOOOOOOOOOOOOOOOOOOOOOO$o;
      43: invokevirtual #114                // Method com/fs/util/ooOOOOOOOOOOOOOOOOOOOOOOOOOOOOOOOOOOOOOOOOOOOOOOOOOOOOOOOOOOOOOOOOOOOOOOOOOOOOOOOOOOOOOOOOOOOOOOOOOOOOOOOOOOOOOOOOOOOOOOOOOOOOOOOOOOOOOOOOOOOOOOOOOOOOOOOOOOOOOOOOOOOOOOOOOOOOOOOOOOOOOOOOOOOOOOOOOOOOOOOOOOOOOOOOOOOOOOOOOOOOOOOOOOOOOOOOOOOOOOOOOOOOOOOOOOOOOO$o.ordinal:()I
      46: iaload
      47: tableswitch   { // 1 to 3
                     1: 88
                     2: 72
                     3: 85
               default: 123
          }
      72: new           #185                // class java/io/File
      75: dup
      76: aload_1
      77: invokespecial #187                // Method java/io/File."<init>":(Ljava/lang/String;)V
      80: astore        5
      82: goto          123
      85: goto          123
      88: new           #185                // class java/io/File
      91: dup
      92: new           #118                // class java/lang/StringBuilder
      95: dup
      96: aload_3
      97: getfield      #138                // Field com/fs/util/ooOOOOOOOOOOOOOOOOOOOOOOOOOOOOOOOOOOOOOOOOOOOOOOOOOOOOOOOOOOOOOOOOOOOOOOOOOOOOOOOOOOOOOOOOOOOOOOOOOOOOOOOOOOOOOOOOOOOOOOOOOOOOOOOOOOOOOOOOOOOOOOOOOOOOOOOOOOOOOOOOOOOOOOOOOOOOOOOOOOOOOOOOOOOOOOOOOOOOOOOOOOOOOOOOOOOOOOOOOOOOOOOOOOOOOOOOOOOOOOOOOOOOOOOOOOOOOO$Oo.Ó00000:Ljava/lang/String;
     100: invokestatic  #120                // Method java/lang/String.valueOf:(Ljava/lang/Object;)Ljava/lang/String;
     103: invokespecial #126                // Method java/lang/StringBuilder."<init>":(Ljava/lang/String;)V
     106: ldc           #194                // String /
     108: invokevirtual #130                // Method java/lang/StringBuilder.append:(Ljava/lang/String;)Ljava/lang/StringBuilder;
     111: aload_1
     112: invokevirtual #130                // Method java/lang/StringBuilder.append:(Ljava/lang/String;)Ljava/lang/StringBuilder;
     115: invokevirtual #134                // Method java/lang/StringBuilder.toString:()Ljava/lang/String;
     118: invokespecial #187                // Method java/io/File."<init>":(Ljava/lang/String;)V
     121: astore        5
     123: aload         5
     125: ifnull        251
     128: aload         5
     130: invokevirtual #188                // Method java/io/File.exists:()Z
     133: ifeq          251
     136: aload         5
     138: invokevirtual #223                // Method java/io/File.isDirectory:()Z
     141: ifne          147
     144: goto          251
     147: aload         5
     149: invokevirtual #282                // Method java/io/File.listFiles:()[Ljava/io/File;
     152: dup
     153: astore        9
     155: arraylength
     156: istore        8
     158: iconst_0
     159: istore        7
     161: goto          244
     164: aload         9
     166: iload         7
     168: aaload
     169: astore        6
     171: aload         6
     173: invokevirtual #223                // Method java/io/File.isDirectory:()Z
     176: ifeq          241
     179: aload         6
     181: invokevirtual #285                // Method java/io/File.isHidden:()Z
     184: ifeq          190
     187: goto          241
     190: aload         6
     192: invokevirtual #254                // Method java/io/File.getName:()Ljava/lang/String;
     195: ldc_w         #288                // String .
     198: invokevirtual #268                // Method java/lang/String.startsWith:(Ljava/lang/String;)Z
     201: ifeq          207
     204: goto          241
     207: aload_2
     208: new           #118                // class java/lang/StringBuilder
     211: dup
     212: aload_1
     213: invokestatic  #120                // Method java/lang/String.valueOf:(Ljava/lang/Object;)Ljava/lang/String;
     216: invokespecial #126                // Method java/lang/StringBuilder."<init>":(Ljava/lang/String;)V
     219: ldc           #194                // String /
     221: invokevirtual #130                // Method java/lang/StringBuilder.append:(Ljava/lang/String;)Ljava/lang/StringBuilder;
     224: aload         6
     226: invokevirtual #254                // Method java/io/File.getName:()Ljava/lang/String;
     229: invokevirtual #130                // Method java/lang/StringBuilder.append:(Ljava/lang/String;)Ljava/lang/StringBuilder;
     232: invokevirtual #134                // Method java/lang/StringBuilder.toString:()Ljava/lang/String;
     235: invokeinterface #262,  2          // InterfaceMethod java/util/Set.add:(Ljava/lang/Object;)Z
     240: pop
     241: iinc          7, 1
     244: iload         7
     246: iload         8
     248: if_icmplt     164
     251: aload         4
     253: invokeinterface #150,  1          // InterfaceMethod java/util/Iterator.hasNext:()Z
     258: ifne          22
     261: new           #29                 // class java/util/ArrayList
     264: dup
     265: aload_2
     266: invokespecial #271                // Method java/util/ArrayList."<init>":(Ljava/util/Collection;)V
     269: areturn

  public synchronized java.io.InputStream String(java.lang.String, com.fs.util.ooOOOOOOOOOOOOOOOOOOOOOOOOOOOOOOOOOOOOOOOOOOOOOOOOOOOOOOOOOOOOOOOOOOOOOOOOOOOOOOOOOOOOOOOOOOOOOOOOOOOOOOOOOOOOOOOOOOOOOOOOOOOOOOOOOOOOOOOOOOOOOOOOOOOOOOOOOOOOOOOOOOOOOOOOOOOOOOOOOOOOOOOOOOOOOOOOOOOOOOOOOOOOOOOOOOOOOOOOOOOOOOOOOOOOOOOOOOOOOOOOOOOOOOOOOOOOOO$Oo) throws java.io.FileNotFoundException;
    Code:
       0: aconst_null
       1: astore_3
       2: invokestatic  #108                // Method super:()[I
       5: aload_2
       6: getfield      #111                // Field com/fs/util/ooOOOOOOOOOOOOOOOOOOOOOOOOOOOOOOOOOOOOOOOOOOOOOOOOOOOOOOOOOOOOOOOOOOOOOOOOOOOOOOOOOOOOOOOOOOOOOOOOOOOOOOOOOOOOOOOOOOOOOOOOOOOOOOOOOOOOOOOOOOOOOOOOOOOOOOOOOOOOOOOOOOOOOOOOOOOOOOOOOOOOOOOOOOOOOOOOOOOOOOOOOOOOOOOOOOOOOOOOOOOOOOOOOOOOOOOOOOOOOOOOOOOOOOOOOOOOOO$Oo.super:Lcom/fs/util/ooOOOOOOOOOOOOOOOOOOOOOOOOOOOOOOOOOOOOOOOOOOOOOOOOOOOOOOOOOOOOOOOOOOOOOOOOOOOOOOOOOOOOOOOOOOOOOOOOOOOOOOOOOOOOOOOOOOOOOOOOOOOOOOOOOOOOOOOOOOOOOOOOOOOOOOOOOOOOOOOOOOOOOOOOOOOOOOOOOOOOOOOOOOOOOOOOOOOOOOOOOOOOOOOOOOOOOOOOOOOOOOOOOOOOOOOOOOOOOOOOOOOOOOOOOOOOOO$o;
       9: invokevirtual #114                // Method com/fs/util/ooOOOOOOOOOOOOOOOOOOOOOOOOOOOOOOOOOOOOOOOOOOOOOOOOOOOOOOOOOOOOOOOOOOOOOOOOOOOOOOOOOOOOOOOOOOOOOOOOOOOOOOOOOOOOOOOOOOOOOOOOOOOOOOOOOOOOOOOOOOOOOOOOOOOOOOOOOOOOOOOOOOOOOOOOOOOOOOOOOOOOOOOOOOOOOOOOOOOOOOOOOOOOOOOOOOOOOOOOOOOOOOOOOOOOOOOOOOOOOOOOOOOOOOOOOOOOOO$o.ordinal:()I
      12: iaload
      13: tableswitch   { // 1 to 3
                     1: 98
                     2: 40
                     3: 75
               default: 158
          }
      40: new           #185                // class java/io/File
      43: dup
      44: aload_1
      45: invokespecial #187                // Method java/io/File."<init>":(Ljava/lang/String;)V
      48: astore        4
      50: aload         4
      52: invokevirtual #188                // Method java/io/File.exists:()Z
      55: ifeq          158
      58: new           #292                // class java/io/BufferedInputStream
      61: dup
      62: new           #294                // class java/io/FileInputStream
      65: dup
      66: aload         4
      68: invokespecial #296                // Method java/io/FileInputStream."<init>":(Ljava/io/File;)V
      71: invokespecial #299                // Method java/io/BufferedInputStream."<init>":(Ljava/io/InputStream;)V
      74: areturn
      75: ldc           #1                  // class com/fs/util/ooOOOOOOOOOOOOOOOOOOOOOOOOOOOOOOOOOOOOOOOOOOOOOOOOOOOOOOOOOOOOOOOOOOOOOOOOOOOOOOOOOOOOOOOOOOOOOOOOOOOOOOOOOOOOOOOOOOOOOOOOOOOOOOOOOOOOOOOOOOOOOOOOOOOOOOOOOOOOOOOOOOOOOOOOOOOOOOOOOOOOOOOOOOOOOOOOOOOOOOOOOOOOOOOOOOOOOOOOOOOOOOOOOOOOOOOOOOOOOOOOOOOOOOOOOOOOOO
      77: invokevirtual #302                // Method java/lang/Class.getClassLoader:()Ljava/lang/ClassLoader;
      80: aload_1
      81: invokevirtual #308                // Method java/lang/ClassLoader.getResourceAsStream:(Ljava/lang/String;)Ljava/io/InputStream;
      84: astore_3
      85: aload_3
      86: ifnull        158
      89: new           #292                // class java/io/BufferedInputStream
      92: dup
      93: aload_3
      94: invokespecial #299                // Method java/io/BufferedInputStream."<init>":(Ljava/io/InputStream;)V
      97: areturn
      98: new           #185                // class java/io/File
     101: dup
     102: new           #118                // class java/lang/StringBuilder
     105: dup
     106: aload_2
     107: getfield      #138                // Field com/fs/util/ooOOOOOOOOOOOOOOOOOOOOOOOOOOOOOOOOOOOOOOOOOOOOOOOOOOOOOOOOOOOOOOOOOOOOOOOOOOOOOOOOOOOOOOOOOOOOOOOOOOOOOOOOOOOOOOOOOOOOOOOOOOOOOOOOOOOOOOOOOOOOOOOOOOOOOOOOOOOOOOOOOOOOOOOOOOOOOOOOOOOOOOOOOOOOOOOOOOOOOOOOOOOOOOOOOOOOOOOOOOOOOOOOOOOOOOOOOOOOOOOOOOOOOOOOOOOOOO$Oo.Ó00000:Ljava/lang/String;
     110: invokestatic  #120                // Method java/lang/String.valueOf:(Ljava/lang/Object;)Ljava/lang/String;
     113: invokespecial #126                // Method java/lang/StringBuilder."<init>":(Ljava/lang/String;)V
     116: ldc           #194                // String /
     118: invokevirtual #130                // Method java/lang/StringBuilder.append:(Ljava/lang/String;)Ljava/lang/StringBuilder;
     121: aload_1
     122: invokevirtual #130                // Method java/lang/StringBuilder.append:(Ljava/lang/String;)Ljava/lang/StringBuilder;
     125: invokevirtual #134                // Method java/lang/StringBuilder.toString:()Ljava/lang/String;
     128: invokespecial #187                // Method java/io/File."<init>":(Ljava/lang/String;)V
     131: astore        4
     133: aload         4
     135: invokevirtual #188                // Method java/io/File.exists:()Z
     138: ifeq          158
     141: new           #292                // class java/io/BufferedInputStream
     144: dup
     145: new           #294                // class java/io/FileInputStream
     148: dup
     149: aload         4
     151: invokespecial #296                // Method java/io/FileInputStream."<init>":(Ljava/io/File;)V
     154: invokespecial #299                // Method java/io/BufferedInputStream."<init>":(Ljava/io/InputStream;)V
     157: areturn
     158: aconst_null
     159: areturn

  public synchronized java.io.File super(java.lang.String, boolean) throws java.io.IOException;
    Code:
       0: ldc           #94                 // String
       2: astore_3
       3: aload_0
       4: getfield      #32                 // Field Ò00000:Ljava/util/List;
       7: invokeinterface #96,  1           // InterfaceMethod java/util/List.iterator:()Ljava/util/Iterator;
      12: astore        5
      14: goto          142
      17: aload         5
      19: invokeinterface #100,  1          // InterfaceMethod java/util/Iterator.next:()Ljava/lang/Object;
      24: checkcast     #43                 // class com/fs/util/ooOOOOOOOOOOOOOOOOOOOOOOOOOOOOOOOOOOOOOOOOOOOOOOOOOOOOOOOOOOOOOOOOOOOOOOOOOOOOOOOOOOOOOOOOOOOOOOOOOOOOOOOOOOOOOOOOOOOOOOOOOOOOOOOOOOOOOOOOOOOOOOOOOOOOOOOOOOOOOOOOOOOOOOOOOOOOOOOOOOOOOOOOOOOOOOOOOOOOOOOOOOOOOOOOOOOOOOOOOOOOOOOOOOOOOOOOOOOOOOOOOOOOOOOOOOOOOO$Oo
      27: astore        4
      29: iload_2
      30: ifne          44
      33: aload         4
      35: getfield      #106                // Field com/fs/util/ooOOOOOOOOOOOOOOOOOOOOOOOOOOOOOOOOOOOOOOOOOOOOOOOOOOOOOOOOOOOOOOOOOOOOOOOOOOOOOOOOOOOOOOOOOOOOOOOOOOOOOOOOOOOOOOOOOOOOOOOOOOOOOOOOOOOOOOOOOOOOOOOOOOOOOOOOOOOOOOOOOOOOOOOOOOOOOOOOOOOOOOOOOOOOOOOOOOOOOOOOOOOOOOOOOOOOOOOOOOOOOOOOOOOOOOOOOOOOOOOOOOOOOOOOOOOOOO$Oo.String:Z
      38: ifeq          44
      41: goto          142
      44: invokestatic  #108                // Method super:()[I
      47: aload         4
      49: getfield      #111                // Field com/fs/util/ooOOOOOOOOOOOOOOOOOOOOOOOOOOOOOOOOOOOOOOOOOOOOOOOOOOOOOOOOOOOOOOOOOOOOOOOOOOOOOOOOOOOOOOOOOOOOOOOOOOOOOOOOOOOOOOOOOOOOOOOOOOOOOOOOOOOOOOOOOOOOOOOOOOOOOOOOOOOOOOOOOOOOOOOOOOOOOOOOOOOOOOOOOOOOOOOOOOOOOOOOOOOOOOOOOOOOOOOOOOOOOOOOOOOOOOOOOOOOOOOOOOOOOOOOOOOOOO$Oo.super:Lcom/fs/util/ooOOOOOOOOOOOOOOOOOOOOOOOOOOOOOOOOOOOOOOOOOOOOOOOOOOOOOOOOOOOOOOOOOOOOOOOOOOOOOOOOOOOOOOOOOOOOOOOOOOOOOOOOOOOOOOOOOOOOOOOOOOOOOOOOOOOOOOOOOOOOOOOOOOOOOOOOOOOOOOOOOOOOOOOOOOOOOOOOOOOOOOOOOOOOOOOOOOOOOOOOOOOOOOOOOOOOOOOOOOOOOOOOOOOOOOOOOOOOOOOOOOOOOOOOOOOOOO$o;
      52: invokevirtual #114                // Method com/fs/util/ooOOOOOOOOOOOOOOOOOOOOOOOOOOOOOOOOOOOOOOOOOOOOOOOOOOOOOOOOOOOOOOOOOOOOOOOOOOOOOOOOOOOOOOOOOOOOOOOOOOOOOOOOOOOOOOOOOOOOOOOOOOOOOOOOOOOOOOOOOOOOOOOOOOOOOOOOOOOOOOOOOOOOOOOOOOOOOOOOOOOOOOOOOOOOOOOOOOOOOOOOOOOOOOOOOOOOOOOOOOOOOOOOOOOOOOOOOOOOOOOOOOOOOOOOOOOOOO$o.ordinal:()I
      55: iaload
      56: tableswitch   { // 1 to 2
                     1: 83
                     2: 80
               default: 111
          }
      80: goto          111
      83: new           #118                // class java/lang/StringBuilder
      86: dup
      87: aload_3
      88: invokestatic  #120                // Method java/lang/String.valueOf:(Ljava/lang/Object;)Ljava/lang/String;
      91: invokespecial #126                // Method java/lang/StringBuilder."<init>":(Ljava/lang/String;)V
      94: aload         4
      96: getfield      #138                // Field com/fs/util/ooOOOOOOOOOOOOOOOOOOOOOOOOOOOOOOOOOOOOOOOOOOOOOOOOOOOOOOOOOOOOOOOOOOOOOOOOOOOOOOOOOOOOOOOOOOOOOOOOOOOOOOOOOOOOOOOOOOOOOOOOOOOOOOOOOOOOOOOOOOOOOOOOOOOOOOOOOOOOOOOOOOOOOOOOOOOOOOOOOOOOOOOOOOOOOOOOOOOOOOOOOOOOOOOOOOOOOOOOOOOOOOOOOOOOOOOOOOOOOOOOOOOOOOOOOOOOOO$Oo.Ó00000:Ljava/lang/String;
      99: invokevirtual #130                // Method java/lang/StringBuilder.append:(Ljava/lang/String;)Ljava/lang/StringBuilder;
     102: ldc           #140                // String ,
     104: invokevirtual #130                // Method java/lang/StringBuilder.append:(Ljava/lang/String;)Ljava/lang/StringBuilder;
     107: invokevirtual #134                // Method java/lang/StringBuilder.toString:()Ljava/lang/String;
     110: astore_3
     111: aload         4
     113: getfield      #111                // Field com/fs/util/ooOOOOOOOOOOOOOOOOOOOOOOOOOOOOOOOOOOOOOOOOOOOOOOOOOOOOOOOOOOOOOOOOOOOOOOOOOOOOOOOOOOOOOOOOOOOOOOOOOOOOOOOOOOOOOOOOOOOOOOOOOOOOOOOOOOOOOOOOOOOOOOOOOOOOOOOOOOOOOOOOOOOOOOOOOOOOOOOOOOOOOOOOOOOOOOOOOOOOOOOOOOOOOOOOOOOOOOOOOOOOOOOOOOOOOOOOOOOOOOOOOOOOOOOOOOOOOO$Oo.super:Lcom/fs/util/ooOOOOOOOOOOOOOOOOOOOOOOOOOOOOOOOOOOOOOOOOOOOOOOOOOOOOOOOOOOOOOOOOOOOOOOOOOOOOOOOOOOOOOOOOOOOOOOOOOOOOOOOOOOOOOOOOOOOOOOOOOOOOOOOOOOOOOOOOOOOOOOOOOOOOOOOOOOOOOOOOOOOOOOOOOOOOOOOOOOOOOOOOOOOOOOOOOOOOOOOOOOOOOOOOOOOOOOOOOOOOOOOOOOOOOOOOOOOOOOOOOOOOOOOOOOOOOO$o;
     116: getstatic     #73                 // Field com/fs/util/ooOOOOOOOOOOOOOOOOOOOOOOOOOOOOOOOOOOOOOOOOOOOOOOOOOOOOOOOOOOOOOOOOOOOOOOOOOOOOOOOOOOOOOOOOOOOOOOOOOOOOOOOOOOOOOOOOOOOOOOOOOOOOOOOOOOOOOOOOOOOOOOOOOOOOOOOOOOOOOOOOOOOOOOOOOOOOOOOOOOOOOOOOOOOOOOOOOOOOOOOOOOOOOOOOOOOOOOOOOOOOOOOOOOOOOOOOOOOOOOOOOOOOOOOOOOOOOO$o.o00000:Lcom/fs/util/ooOOOOOOOOOOOOOOOOOOOOOOOOOOOOOOOOOOOOOOOOOOOOOOOOOOOOOOOOOOOOOOOOOOOOOOOOOOOOOOOOOOOOOOOOOOOOOOOOOOOOOOOOOOOOOOOOOOOOOOOOOOOOOOOOOOOOOOOOOOOOOOOOOOOOOOOOOOOOOOOOOOOOOOOOOOOOOOOOOOOOOOOOOOOOOOOOOOOOOOOOOOOOOOOOOOOOOOOOOOOOOOOOOOOOOOOOOOOOOOOOOOOOOOOOOOOOOO$o;
     119: if_acmpne     125
     122: goto          142
     125: aload_0
     126: aload_1
     127: aload         4
     129: invokevirtual #315                // Method Ó00000:(Ljava/lang/String;Lcom/fs/util/ooOOOOOOOOOOOOOOOOOOOOOOOOOOOOOOOOOOOOOOOOOOOOOOOOOOOOOOOOOOOOOOOOOOOOOOOOOOOOOOOOOOOOOOOOOOOOOOOOOOOOOOOOOOOOOOOOOOOOOOOOOOOOOOOOOOOOOOOOOOOOOOOOOOOOOOOOOOOOOOOOOOOOOOOOOOOOOOOOOOOOOOOOOOOOOOOOOOOOOOOOOOOOOOOOOOOOOOOOOOOOOOOOOOOOOOOOOOOOOOOOOOOOOOOOOOOOOO$Oo;)Ljava/io/File;
     132: astore        6
     134: aload         6
     136: ifnull        142
     139: aload         6
     141: areturn
     142: aload         5
     144: invokeinterface #150,  1          // InterfaceMethod java/util/Iterator.hasNext:()Z
     149: ifne          17
     152: aload_3
     153: iconst_0
     154: aload_3
     155: invokevirtual #154                // Method java/lang/String.length:()I
     158: iconst_1
     159: isub
     160: invokevirtual #157                // Method java/lang/String.substring:(II)Ljava/lang/String;
     163: astore_3
     164: new           #161                // class java/lang/RuntimeException
     167: dup
     168: new           #118                // class java/lang/StringBuilder
     171: dup
     172: ldc           #163                // String Error loading [
     174: invokespecial #126                // Method java/lang/StringBuilder."<init>":(Ljava/lang/String;)V
     177: aload_1
     178: invokevirtual #130                // Method java/lang/StringBuilder.append:(Ljava/lang/String;)Ljava/lang/StringBuilder;
     181: ldc           #165                // String ] resource, not found in [
     183: invokevirtual #130                // Method java/lang/StringBuilder.append:(Ljava/lang/String;)Ljava/lang/StringBuilder;
     186: aload_3
     187: invokevirtual #130                // Method java/lang/StringBuilder.append:(Ljava/lang/String;)Ljava/lang/StringBuilder;
     190: ldc           #167                // String ]
     192: invokevirtual #130                // Method java/lang/StringBuilder.append:(Ljava/lang/String;)Ljava/lang/StringBuilder;
     195: invokevirtual #134                // Method java/lang/StringBuilder.toString:()Ljava/lang/String;
     198: invokespecial #169                // Method java/lang/RuntimeException."<init>":(Ljava/lang/String;)V
     201: athrow

  public synchronized java.io.File Ó00000(java.lang.String, com.fs.util.ooOOOOOOOOOOOOOOOOOOOOOOOOOOOOOOOOOOOOOOOOOOOOOOOOOOOOOOOOOOOOOOOOOOOOOOOOOOOOOOOOOOOOOOOOOOOOOOOOOOOOOOOOOOOOOOOOOOOOOOOOOOOOOOOOOOOOOOOOOOOOOOOOOOOOOOOOOOOOOOOOOOOOOOOOOOOOOOOOOOOOOOOOOOOOOOOOOOOOOOOOOOOOOOOOOOOOOOOOOOOOOOOOOOOOOOOOOOOOOOOOOOOOOOOOOOOOOO$Oo) throws java.io.FileNotFoundException;
    Code:
       0: aconst_null
       1: astore_3
       2: invokestatic  #108                // Method super:()[I
       5: aload_2
       6: getfield      #111                // Field com/fs/util/ooOOOOOOOOOOOOOOOOOOOOOOOOOOOOOOOOOOOOOOOOOOOOOOOOOOOOOOOOOOOOOOOOOOOOOOOOOOOOOOOOOOOOOOOOOOOOOOOOOOOOOOOOOOOOOOOOOOOOOOOOOOOOOOOOOOOOOOOOOOOOOOOOOOOOOOOOOOOOOOOOOOOOOOOOOOOOOOOOOOOOOOOOOOOOOOOOOOOOOOOOOOOOOOOOOOOOOOOOOOOOOOOOOOOOOOOOOOOOOOOOOOOOOOOOOOOOOO$Oo.super:Lcom/fs/util/ooOOOOOOOOOOOOOOOOOOOOOOOOOOOOOOOOOOOOOOOOOOOOOOOOOOOOOOOOOOOOOOOOOOOOOOOOOOOOOOOOOOOOOOOOOOOOOOOOOOOOOOOOOOOOOOOOOOOOOOOOOOOOOOOOOOOOOOOOOOOOOOOOOOOOOOOOOOOOOOOOOOOOOOOOOOOOOOOOOOOOOOOOOOOOOOOOOOOOOOOOOOOOOOOOOOOOOOOOOOOOOOOOOOOOOOOOOOOOOOOOOOOOOOOOOOOOOO$o;
       9: invokevirtual #114                // Method com/fs/util/ooOOOOOOOOOOOOOOOOOOOOOOOOOOOOOOOOOOOOOOOOOOOOOOOOOOOOOOOOOOOOOOOOOOOOOOOOOOOOOOOOOOOOOOOOOOOOOOOOOOOOOOOOOOOOOOOOOOOOOOOOOOOOOOOOOOOOOOOOOOOOOOOOOOOOOOOOOOOOOOOOOOOOOOOOOOOOOOOOOOOOOOOOOOOOOOOOOOOOOOOOOOOOOOOOOOOOOOOOOOOOOOOOOOOOOOOOOOOOOOOOOOOOOOOOOOOOOO$o.ordinal:()I
      12: iaload
      13: tableswitch   { // 1 to 3
                     1: 69
                     2: 40
                     3: 58
               default: 112
          }
      40: new           #185                // class java/io/File
      43: dup
      44: aload_1
      45: invokespecial #187                // Method java/io/File."<init>":(Ljava/lang/String;)V
      48: astore_3
      49: aload_3
      50: invokevirtual #188                // Method java/io/File.exists:()Z
      53: ifeq          112
      56: aload_3
      57: areturn
      58: new           #161                // class java/lang/RuntimeException
      61: dup
      62: ldc_w         #319                // String Can\'t find a file on the classpath - use openResource() instead.
      65: invokespecial #169                // Method java/lang/RuntimeException."<init>":(Ljava/lang/String;)V
      68: athrow
      69: new           #185                // class java/io/File
      72: dup
      73: new           #118                // class java/lang/StringBuilder
      76: dup
      77: aload_2
      78: getfield      #138                // Field com/fs/util/ooOOOOOOOOOOOOOOOOOOOOOOOOOOOOOOOOOOOOOOOOOOOOOOOOOOOOOOOOOOOOOOOOOOOOOOOOOOOOOOOOOOOOOOOOOOOOOOOOOOOOOOOOOOOOOOOOOOOOOOOOOOOOOOOOOOOOOOOOOOOOOOOOOOOOOOOOOOOOOOOOOOOOOOOOOOOOOOOOOOOOOOOOOOOOOOOOOOOOOOOOOOOOOOOOOOOOOOOOOOOOOOOOOOOOOOOOOOOOOOOOOOOOOOOOOOOOOO$Oo.Ó00000:Ljava/lang/String;
      81: invokestatic  #120                // Method java/lang/String.valueOf:(Ljava/lang/Object;)Ljava/lang/String;
      84: invokespecial #126                // Method java/lang/StringBuilder."<init>":(Ljava/lang/String;)V
      87: ldc           #194                // String /
      89: invokevirtual #130                // Method java/lang/StringBuilder.append:(Ljava/lang/String;)Ljava/lang/StringBuilder;
      92: aload_1
      93: invokevirtual #130                // Method java/lang/StringBuilder.append:(Ljava/lang/String;)Ljava/lang/StringBuilder;
      96: invokevirtual #134                // Method java/lang/StringBuilder.toString:()Ljava/lang/String;
      99: invokespecial #187                // Method java/io/File."<init>":(Ljava/lang/String;)V
     102: astore_3
     103: aload_3
     104: invokevirtual #188                // Method java/io/File.exists:()Z
     107: ifeq          112
     110: aload_3
     111: areturn
     112: aconst_null
     113: areturn

  public synchronized java.lang.String super(java.lang.String) throws java.io.IOException;
    Code:
       0: aload_0
       1: getfield      #32                 // Field Ò00000:Ljava/util/List;
       4: invokeinterface #96,  1           // InterfaceMethod java/util/List.iterator:()Ljava/util/Iterator;
       9: astore_3
      10: goto          104
      13: aload_3
      14: invokeinterface #100,  1          // InterfaceMethod java/util/Iterator.next:()Ljava/lang/Object;
      19: checkcast     #43                 // class com/fs/util/ooOOOOOOOOOOOOOOOOOOOOOOOOOOOOOOOOOOOOOOOOOOOOOOOOOOOOOOOOOOOOOOOOOOOOOOOOOOOOOOOOOOOOOOOOOOOOOOOOOOOOOOOOOOOOOOOOOOOOOOOOOOOOOOOOOOOOOOOOOOOOOOOOOOOOOOOOOOOOOOOOOOOOOOOOOOOOOOOOOOOOOOOOOOOOOOOOOOOOOOOOOOOOOOOOOOOOOOOOOOOOOOOOOOOOOOOOOOOOOOOOOOOOOOOOOOOOOO$Oo
      22: astore_2
      23: aload_2
      24: getfield      #111                // Field com/fs/util/ooOOOOOOOOOOOOOOOOOOOOOOOOOOOOOOOOOOOOOOOOOOOOOOOOOOOOOOOOOOOOOOOOOOOOOOOOOOOOOOOOOOOOOOOOOOOOOOOOOOOOOOOOOOOOOOOOOOOOOOOOOOOOOOOOOOOOOOOOOOOOOOOOOOOOOOOOOOOOOOOOOOOOOOOOOOOOOOOOOOOOOOOOOOOOOOOOOOOOOOOOOOOOOOOOOOOOOOOOOOOOOOOOOOOOOOOOOOOOOOOOOOOOOOOOOOOOOO$Oo.super:Lcom/fs/util/ooOOOOOOOOOOOOOOOOOOOOOOOOOOOOOOOOOOOOOOOOOOOOOOOOOOOOOOOOOOOOOOOOOOOOOOOOOOOOOOOOOOOOOOOOOOOOOOOOOOOOOOOOOOOOOOOOOOOOOOOOOOOOOOOOOOOOOOOOOOOOOOOOOOOOOOOOOOOOOOOOOOOOOOOOOOOOOOOOOOOOOOOOOOOOOOOOOOOOOOOOOOOOOOOOOOOOOOOOOOOOOOOOOOOOOOOOOOOOOOOOOOOOOOOOOOOOOO$o;
      27: getstatic     #73                 // Field com/fs/util/ooOOOOOOOOOOOOOOOOOOOOOOOOOOOOOOOOOOOOOOOOOOOOOOOOOOOOOOOOOOOOOOOOOOOOOOOOOOOOOOOOOOOOOOOOOOOOOOOOOOOOOOOOOOOOOOOOOOOOOOOOOOOOOOOOOOOOOOOOOOOOOOOOOOOOOOOOOOOOOOOOOOOOOOOOOOOOOOOOOOOOOOOOOOOOOOOOOOOOOOOOOOOOOOOOOOOOOOOOOOOOOOOOOOOOOOOOOOOOOOOOOOOOOOOOOOOOOO$o.o00000:Lcom/fs/util/ooOOOOOOOOOOOOOOOOOOOOOOOOOOOOOOOOOOOOOOOOOOOOOOOOOOOOOOOOOOOOOOOOOOOOOOOOOOOOOOOOOOOOOOOOOOOOOOOOOOOOOOOOOOOOOOOOOOOOOOOOOOOOOOOOOOOOOOOOOOOOOOOOOOOOOOOOOOOOOOOOOOOOOOOOOOOOOOOOOOOOOOOOOOOOOOOOOOOOOOOOOOOOOOOOOOOOOOOOOOOOOOOOOOOOOOOOOOOOOOOOOOOOOOOOOOOOOO$o;
      30: if_acmpne     36
      33: goto          104
      36: aload_2
      37: getfield      #111                // Field com/fs/util/ooOOOOOOOOOOOOOOOOOOOOOOOOOOOOOOOOOOOOOOOOOOOOOOOOOOOOOOOOOOOOOOOOOOOOOOOOOOOOOOOOOOOOOOOOOOOOOOOOOOOOOOOOOOOOOOOOOOOOOOOOOOOOOOOOOOOOOOOOOOOOOOOOOOOOOOOOOOOOOOOOOOOOOOOOOOOOOOOOOOOOOOOOOOOOOOOOOOOOOOOOOOOOOOOOOOOOOOOOOOOOOOOOOOOOOOOOOOOOOOOOOOOOOOOOOOOOOO$Oo.super:Lcom/fs/util/ooOOOOOOOOOOOOOOOOOOOOOOOOOOOOOOOOOOOOOOOOOOOOOOOOOOOOOOOOOOOOOOOOOOOOOOOOOOOOOOOOOOOOOOOOOOOOOOOOOOOOOOOOOOOOOOOOOOOOOOOOOOOOOOOOOOOOOOOOOOOOOOOOOOOOOOOOOOOOOOOOOOOOOOOOOOOOOOOOOOOOOOOOOOOOOOOOOOOOOOOOOOOOOOOOOOOOOOOOOOOOOOOOOOOOOOOOOOOOOOOOOOOOOOOOOOOOOO$o;
      40: getstatic     #77                 // Field com/fs/util/ooOOOOOOOOOOOOOOOOOOOOOOOOOOOOOOOOOOOOOOOOOOOOOOOOOOOOOOOOOOOOOOOOOOOOOOOOOOOOOOOOOOOOOOOOOOOOOOOOOOOOOOOOOOOOOOOOOOOOOOOOOOOOOOOOOOOOOOOOOOOOOOOOOOOOOOOOOOOOOOOOOOOOOOOOOOOOOOOOOOOOOOOOOOOOOOOOOOOOOOOOOOOOOOOOOOOOOOOOOOOOOOOOOOOOOOOOOOOOOOOOOOOOOOOOOOOOOO$o.Object:Lcom/fs/util/ooOOOOOOOOOOOOOOOOOOOOOOOOOOOOOOOOOOOOOOOOOOOOOOOOOOOOOOOOOOOOOOOOOOOOOOOOOOOOOOOOOOOOOOOOOOOOOOOOOOOOOOOOOOOOOOOOOOOOOOOOOOOOOOOOOOOOOOOOOOOOOOOOOOOOOOOOOOOOOOOOOOOOOOOOOOOOOOOOOOOOOOOOOOOOOOOOOOOOOOOOOOOOOOOOOOOOOOOOOOOOOOOOOOOOOOOOOOOOOOOOOOOOOOOOOOOOOO$o;
      43: if_acmpne     49
      46: goto          104
      49: aload_2
      50: getfield      #138                // Field com/fs/util/ooOOOOOOOOOOOOOOOOOOOOOOOOOOOOOOOOOOOOOOOOOOOOOOOOOOOOOOOOOOOOOOOOOOOOOOOOOOOOOOOOOOOOOOOOOOOOOOOOOOOOOOOOOOOOOOOOOOOOOOOOOOOOOOOOOOOOOOOOOOOOOOOOOOOOOOOOOOOOOOOOOOOOOOOOOOOOOOOOOOOOOOOOOOOOOOOOOOOOOOOOOOOOOOOOOOOOOOOOOOOOOOOOOOOOOOOOOOOOOOOOOOOOOOOOOOOOOO$Oo.Ó00000:Ljava/lang/String;
      53: ifnull        72
      56: aload_2
      57: getfield      #138                // Field com/fs/util/ooOOOOOOOOOOOOOOOOOOOOOOOOOOOOOOOOOOOOOOOOOOOOOOOOOOOOOOOOOOOOOOOOOOOOOOOOOOOOOOOOOOOOOOOOOOOOOOOOOOOOOOOOOOOOOOOOOOOOOOOOOOOOOOOOOOOOOOOOOOOOOOOOOOOOOOOOOOOOOOOOOOOOOOOOOOOOOOOOOOOOOOOOOOOOOOOOOOOOOOOOOOOOOOOOOOOOOOOOOOOOOOOOOOOOOOOOOOOOOOOOOOOOOOOOOOOOOO$Oo.Ó00000:Ljava/lang/String;
      60: ldc_w         #323                // String /res
      63: invokevirtual #142                // Method java/lang/String.endsWith:(Ljava/lang/String;)Z
      66: ifeq          72
      69: goto          104
      72: aload_0
      73: aload_1
      74: aload_2
      75: invokevirtual #325                // Method super:(Ljava/lang/String;Lcom/fs/util/ooOOOOOOOOOOOOOOOOOOOOOOOOOOOOOOOOOOOOOOOOOOOOOOOOOOOOOOOOOOOOOOOOOOOOOOOOOOOOOOOOOOOOOOOOOOOOOOOOOOOOOOOOOOOOOOOOOOOOOOOOOOOOOOOOOOOOOOOOOOOOOOOOOOOOOOOOOOOOOOOOOOOOOOOOOOOOOOOOOOOOOOOOOOOOOOOOOOOOOOOOOOOOOOOOOOOOOOOOOOOOOOOOOOOOOOOOOOOOOOOOOOOOOOOOOOOOOO$Oo;)Z
      78: istore        4
      80: iload         4
      82: ifeq          104
      85: new           #185                // class java/io/File
      88: dup
      89: aload_2
      90: getfield      #138                // Field com/fs/util/ooOOOOOOOOOOOOOOOOOOOOOOOOOOOOOOOOOOOOOOOOOOOOOOOOOOOOOOOOOOOOOOOOOOOOOOOOOOOOOOOOOOOOOOOOOOOOOOOOOOOOOOOOOOOOOOOOOOOOOOOOOOOOOOOOOOOOOOOOOOOOOOOOOOOOOOOOOOOOOOOOOOOOOOOOOOOOOOOOOOOOOOOOOOOOOOOOOOOOOOOOOOOOOOOOOOOOOOOOOOOOOOOOOOOOOOOOOOOOOOOOOOOOOOOOOOOOOO$Oo.Ó00000:Ljava/lang/String;
      93: invokespecial #187                // Method java/io/File."<init>":(Ljava/lang/String;)V
      96: astore        5
      98: aload         5
     100: invokevirtual #254                // Method java/io/File.getName:()Ljava/lang/String;
     103: areturn
     104: aload_3
     105: invokeinterface #150,  1          // InterfaceMethod java/util/Iterator.hasNext:()Z
     110: ifne          13
     113: aconst_null
     114: areturn

  public synchronized boolean super(java.lang.String, com.fs.util.ooOOOOOOOOOOOOOOOOOOOOOOOOOOOOOOOOOOOOOOOOOOOOOOOOOOOOOOOOOOOOOOOOOOOOOOOOOOOOOOOOOOOOOOOOOOOOOOOOOOOOOOOOOOOOOOOOOOOOOOOOOOOOOOOOOOOOOOOOOOOOOOOOOOOOOOOOOOOOOOOOOOOOOOOOOOOOOOOOOOOOOOOOOOOOOOOOOOOOOOOOOOOOOOOOOOOOOOOOOOOOOOOOOOOOOOOOOOOOOOOOOOOOOOOOOOOOOO$Oo) throws java.io.FileNotFoundException;
    Code:
       0: aconst_null
       1: astore_3
       2: invokestatic  #108                // Method super:()[I
       5: aload_2
       6: getfield      #111                // Field com/fs/util/ooOOOOOOOOOOOOOOOOOOOOOOOOOOOOOOOOOOOOOOOOOOOOOOOOOOOOOOOOOOOOOOOOOOOOOOOOOOOOOOOOOOOOOOOOOOOOOOOOOOOOOOOOOOOOOOOOOOOOOOOOOOOOOOOOOOOOOOOOOOOOOOOOOOOOOOOOOOOOOOOOOOOOOOOOOOOOOOOOOOOOOOOOOOOOOOOOOOOOOOOOOOOOOOOOOOOOOOOOOOOOOOOOOOOOOOOOOOOOOOOOOOOOOOOOOOOOOO$Oo.super:Lcom/fs/util/ooOOOOOOOOOOOOOOOOOOOOOOOOOOOOOOOOOOOOOOOOOOOOOOOOOOOOOOOOOOOOOOOOOOOOOOOOOOOOOOOOOOOOOOOOOOOOOOOOOOOOOOOOOOOOOOOOOOOOOOOOOOOOOOOOOOOOOOOOOOOOOOOOOOOOOOOOOOOOOOOOOOOOOOOOOOOOOOOOOOOOOOOOOOOOOOOOOOOOOOOOOOOOOOOOOOOOOOOOOOOOOOOOOOOOOOOOOOOOOOOOOOOOOOOOOOOOOO$o;
       9: invokevirtual #114                // Method com/fs/util/ooOOOOOOOOOOOOOOOOOOOOOOOOOOOOOOOOOOOOOOOOOOOOOOOOOOOOOOOOOOOOOOOOOOOOOOOOOOOOOOOOOOOOOOOOOOOOOOOOOOOOOOOOOOOOOOOOOOOOOOOOOOOOOOOOOOOOOOOOOOOOOOOOOOOOOOOOOOOOOOOOOOOOOOOOOOOOOOOOOOOOOOOOOOOOOOOOOOOOOOOOOOOOOOOOOOOOOOOOOOOOOOOOOOOOOOOOOOOOOOOOOOOOOOOOOOOOOO$o.ordinal:()I
      12: iaload
      13: tableswitch   { // 1 to 3
                     1: 91
                     2: 40
                     3: 56
               default: 132
          }
      40: new           #185                // class java/io/File
      43: dup
      44: aload_1
      45: invokespecial #187                // Method java/io/File."<init>":(Ljava/lang/String;)V
      48: astore        4
      50: aload         4
      52: invokevirtual #188                // Method java/io/File.exists:()Z
      55: ireturn
      56: ldc           #1                  // class com/fs/util/ooOOOOOOOOOOOOOOOOOOOOOOOOOOOOOOOOOOOOOOOOOOOOOOOOOOOOOOOOOOOOOOOOOOOOOOOOOOOOOOOOOOOOOOOOOOOOOOOOOOOOOOOOOOOOOOOOOOOOOOOOOOOOOOOOOOOOOOOOOOOOOOOOOOOOOOOOOOOOOOOOOOOOOOOOOOOOOOOOOOOOOOOOOOOOOOOOOOOOOOOOOOOOOOOOOOOOOOOOOOOOOOOOOOOOOOOOOOOOOOOOOOOOOOOOOOOOOO
      58: invokevirtual #302                // Method java/lang/Class.getClassLoader:()Ljava/lang/ClassLoader;
      61: aload_1
      62: invokevirtual #308                // Method java/lang/ClassLoader.getResourceAsStream:(Ljava/lang/String;)Ljava/io/InputStream;
      65: astore_3
      66: aload_3
      67: ifnull        132
      70: aload_3
      71: invokevirtual #330                // Method java/io/InputStream.close:()V
      74: goto          89
      77: astore        5
      79: new           #161                // class java/lang/RuntimeException
      82: dup
      83: aload         5
      85: invokespecial #333                // Method java/lang/RuntimeException."<init>":(Ljava/lang/Throwable;)V
      88: athrow
      89: iconst_1
      90: ireturn
      91: new           #185                // class java/io/File
      94: dup
      95: new           #118                // class java/lang/StringBuilder
      98: dup
      99: aload_2
     100: getfield      #138                // Field com/fs/util/ooOOOOOOOOOOOOOOOOOOOOOOOOOOOOOOOOOOOOOOOOOOOOOOOOOOOOOOOOOOOOOOOOOOOOOOOOOOOOOOOOOOOOOOOOOOOOOOOOOOOOOOOOOOOOOOOOOOOOOOOOOOOOOOOOOOOOOOOOOOOOOOOOOOOOOOOOOOOOOOOOOOOOOOOOOOOOOOOOOOOOOOOOOOOOOOOOOOOOOOOOOOOOOOOOOOOOOOOOOOOOOOOOOOOOOOOOOOOOOOOOOOOOOOOOOOOOOO$Oo.Ó00000:Ljava/lang/String;
     103: invokestatic  #120                // Method java/lang/String.valueOf:(Ljava/lang/Object;)Ljava/lang/String;
     106: invokespecial #126                // Method java/lang/StringBuilder."<init>":(Ljava/lang/String;)V
     109: ldc           #194                // String /
     111: invokevirtual #130                // Method java/lang/StringBuilder.append:(Ljava/lang/String;)Ljava/lang/StringBuilder;
     114: aload_1
     115: invokevirtual #130                // Method java/lang/StringBuilder.append:(Ljava/lang/String;)Ljava/lang/StringBuilder;
     118: invokevirtual #134                // Method java/lang/StringBuilder.toString:()Ljava/lang/String;
     121: invokespecial #187                // Method java/io/File."<init>":(Ljava/lang/String;)V
     124: astore        4
     126: aload         4
     128: invokevirtual #188                // Method java/io/File.exists:()Z
     131: ireturn
     132: iconst_0
     133: ireturn
    Exception table:
       from    to  target type
          70    74    77   Class java/io/IOException

  static int[] super();
    Code:
       0: getstatic     #338                // Field Õ00000:[I
       3: dup
       4: ifnull        8
       7: areturn
       8: pop
       9: invokestatic  #340                // Method com/fs/util/ooOOOOOOOOOOOOOOOOOOOOOOOOOOOOOOOOOOOOOOOOOOOOOOOOOOOOOOOOOOOOOOOOOOOOOOOOOOOOOOOOOOOOOOOOOOOOOOOOOOOOOOOOOOOOOOOOOOOOOOOOOOOOOOOOOOOOOOOOOOOOOOOOOOOOOOOOOOOOOOOOOOOOOOOOOOOOOOOOOOOOOOOOOOOOOOOOOOOOOOOOOOOOOOOOOOOOOOOOOOOOOOOOOOOOOOOOOOOOOOOOOOOOOOOOOOOOOO$o.values:()[Lcom/fs/util/ooOOOOOOOOOOOOOOOOOOOOOOOOOOOOOOOOOOOOOOOOOOOOOOOOOOOOOOOOOOOOOOOOOOOOOOOOOOOOOOOOOOOOOOOOOOOOOOOOOOOOOOOOOOOOOOOOOOOOOOOOOOOOOOOOOOOOOOOOOOOOOOOOOOOOOOOOOOOOOOOOOOOOOOOOOOOOOOOOOOOOOOOOOOOOOOOOOOOOOOOOOOOOOOOOOOOOOOOOOOOOOOOOOOOOOOOOOOOOOOOOOOOOOOOOOOOOOO$o;
      12: arraylength
      13: newarray       int
      15: astore_0
      16: aload_0
      17: getstatic     #77                 // Field com/fs/util/ooOOOOOOOOOOOOOOOOOOOOOOOOOOOOOOOOOOOOOOOOOOOOOOOOOOOOOOOOOOOOOOOOOOOOOOOOOOOOOOOOOOOOOOOOOOOOOOOOOOOOOOOOOOOOOOOOOOOOOOOOOOOOOOOOOOOOOOOOOOOOOOOOOOOOOOOOOOOOOOOOOOOOOOOOOOOOOOOOOOOOOOOOOOOOOOOOOOOOOOOOOOOOOOOOOOOOOOOOOOOOOOOOOOOOOOOOOOOOOOOOOOOOOOOOOOOOOO$o.Object:Lcom/fs/util/ooOOOOOOOOOOOOOOOOOOOOOOOOOOOOOOOOOOOOOOOOOOOOOOOOOOOOOOOOOOOOOOOOOOOOOOOOOOOOOOOOOOOOOOOOOOOOOOOOOOOOOOOOOOOOOOOOOOOOOOOOOOOOOOOOOOOOOOOOOOOOOOOOOOOOOOOOOOOOOOOOOOOOOOOOOOOOOOOOOOOOOOOOOOOOOOOOOOOOOOOOOOOOOOOOOOOOOOOOOOOOOOOOOOOOOOOOOOOOOOOOOOOOOOOOOOOOOO$o;
      20: invokevirtual #114                // Method com/fs/util/ooOOOOOOOOOOOOOOOOOOOOOOOOOOOOOOOOOOOOOOOOOOOOOOOOOOOOOOOOOOOOOOOOOOOOOOOOOOOOOOOOOOOOOOOOOOOOOOOOOOOOOOOOOOOOOOOOOOOOOOOOOOOOOOOOOOOOOOOOOOOOOOOOOOOOOOOOOOOOOOOOOOOOOOOOOOOOOOOOOOOOOOOOOOOOOOOOOOOOOOOOOOOOOOOOOOOOOOOOOOOOOOOOOOOOOOOOOOOOOOOOOOOOOOOOOOOOOO$o.ordinal:()I
      23: iconst_2
      24: iastore
      25: goto          29
      28: pop
      29: aload_0
      30: getstatic     #73                 // Field com/fs/util/ooOOOOOOOOOOOOOOOOOOOOOOOOOOOOOOOOOOOOOOOOOOOOOOOOOOOOOOOOOOOOOOOOOOOOOOOOOOOOOOOOOOOOOOOOOOOOOOOOOOOOOOOOOOOOOOOOOOOOOOOOOOOOOOOOOOOOOOOOOOOOOOOOOOOOOOOOOOOOOOOOOOOOOOOOOOOOOOOOOOOOOOOOOOOOOOOOOOOOOOOOOOOOOOOOOOOOOOOOOOOOOOOOOOOOOOOOOOOOOOOOOOOOOOOOOOOOOO$o.o00000:Lcom/fs/util/ooOOOOOOOOOOOOOOOOOOOOOOOOOOOOOOOOOOOOOOOOOOOOOOOOOOOOOOOOOOOOOOOOOOOOOOOOOOOOOOOOOOOOOOOOOOOOOOOOOOOOOOOOOOOOOOOOOOOOOOOOOOOOOOOOOOOOOOOOOOOOOOOOOOOOOOOOOOOOOOOOOOOOOOOOOOOOOOOOOOOOOOOOOOOOOOOOOOOOOOOOOOOOOOOOOOOOOOOOOOOOOOOOOOOOOOOOOOOOOOOOOOOOOOOOOOOOOO$o;
      33: invokevirtual #114                // Method com/fs/util/ooOOOOOOOOOOOOOOOOOOOOOOOOOOOOOOOOOOOOOOOOOOOOOOOOOOOOOOOOOOOOOOOOOOOOOOOOOOOOOOOOOOOOOOOOOOOOOOOOOOOOOOOOOOOOOOOOOOOOOOOOOOOOOOOOOOOOOOOOOOOOOOOOOOOOOOOOOOOOOOOOOOOOOOOOOOOOOOOOOOOOOOOOOOOOOOOOOOOOOOOOOOOOOOOOOOOOOOOOOOOOOOOOOOOOOOOOOOOOOOOOOOOOOOOOOOOOOO$o.ordinal:()I
      36: iconst_3
      37: iastore
      38: goto          42
      41: pop
      42: aload_0
      43: getstatic     #45                 // Field com/fs/util/ooOOOOOOOOOOOOOOOOOOOOOOOOOOOOOOOOOOOOOOOOOOOOOOOOOOOOOOOOOOOOOOOOOOOOOOOOOOOOOOOOOOOOOOOOOOOOOOOOOOOOOOOOOOOOOOOOOOOOOOOOOOOOOOOOOOOOOOOOOOOOOOOOOOOOOOOOOOOOOOOOOOOOOOOOOOOOOOOOOOOOOOOOOOOOOOOOOOOOOOOOOOOOOOOOOOOOOOOOOOOOOOOOOOOOOOOOOOOOOOOOOOOOOOOOOOOOOO$o.Ô00000:Lcom/fs/util/ooOOOOOOOOOOOOOOOOOOOOOOOOOOOOOOOOOOOOOOOOOOOOOOOOOOOOOOOOOOOOOOOOOOOOOOOOOOOOOOOOOOOOOOOOOOOOOOOOOOOOOOOOOOOOOOOOOOOOOOOOOOOOOOOOOOOOOOOOOOOOOOOOOOOOOOOOOOOOOOOOOOOOOOOOOOOOOOOOOOOOOOOOOOOOOOOOOOOOOOOOOOOOOOOOOOOOOOOOOOOOOOOOOOOOOOOOOOOOOOOOOOOOOOOOOOOOOO$o;
      46: invokevirtual #114                // Method com/fs/util/ooOOOOOOOOOOOOOOOOOOOOOOOOOOOOOOOOOOOOOOOOOOOOOOOOOOOOOOOOOOOOOOOOOOOOOOOOOOOOOOOOOOOOOOOOOOOOOOOOOOOOOOOOOOOOOOOOOOOOOOOOOOOOOOOOOOOOOOOOOOOOOOOOOOOOOOOOOOOOOOOOOOOOOOOOOOOOOOOOOOOOOOOOOOOOOOOOOOOOOOOOOOOOOOOOOOOOOOOOOOOOOOOOOOOOOOOOOOOOOOOOOOOOOOOOOOOOOO$o.ordinal:()I
      49: iconst_1
      50: iastore
      51: goto          55
      54: pop
      55: aload_0
      56: dup
      57: putstatic     #338                // Field Õ00000:[I
      60: areturn
    Exception table:
       from    to  target type
          16    25    28   Class java/lang/NoSuchFieldError
          29    38    41   Class java/lang/NoSuchFieldError
          42    51    54   Class java/lang/NoSuchFieldError
}

--- L bytecode ---
public class com.fs.graphics.L {
  private static byte[] Ö00000;

  private static org.apache.log4j.Logger Ó00000;

  private static final int null;

  private static java.util.List<java.lang.String> class;

  private static java.util.Map<java.lang.String, java.awt.image.BufferedImage> Ø00000;

  private static java.util.List<java.lang.String> õ00000;

  private static java.util.Map<java.lang.String, byte[]> new;

  private static java.awt.image.BufferedImage Ô00000;

  private static java.lang.Thread o00000;

  static {};
    Code:
       0: iconst_0
       1: newarray       byte
       3: putstatic     #30                 // Field Ö00000:[B
       6: ldc           #1                  // class com/fs/graphics/L
       8: invokestatic  #32                 // Method org/apache/log4j/Logger.getLogger:(Ljava/lang/Class;)Lorg/apache/log4j/Logger;
      11: putstatic     #38                 // Field Ó00000:Lorg/apache/log4j/Logger;
      14: new           #40                 // class java/util/LinkedList
      17: dup
      18: invokespecial #42                 // Method java/util/LinkedList."<init>":()V
      21: invokestatic  #45                 // Method java/util/Collections.synchronizedList:(Ljava/util/List;)Ljava/util/List;
      24: putstatic     #51                 // Field class:Ljava/util/List;
      27: new           #53                 // class java/util/concurrent/ConcurrentHashMap
      30: dup
      31: invokespecial #55                 // Method java/util/concurrent/ConcurrentHashMap."<init>":()V
      34: putstatic     #56                 // Field Ø00000:Ljava/util/Map;
      37: new           #40                 // class java/util/LinkedList
      40: dup
      41: invokespecial #42                 // Method java/util/LinkedList."<init>":()V
      44: invokestatic  #45                 // Method java/util/Collections.synchronizedList:(Ljava/util/List;)Ljava/util/List;
      47: putstatic     #58                 // Field õ00000:Ljava/util/List;
      50: new           #53                 // class java/util/concurrent/ConcurrentHashMap
      53: dup
      54: invokespecial #55                 // Method java/util/concurrent/ConcurrentHashMap."<init>":()V
      57: putstatic     #60                 // Field new:Ljava/util/Map;
      60: new           #62                 // class java/awt/image/BufferedImage
      63: dup
      64: iconst_1
      65: iconst_1
      66: iconst_5
      67: invokespecial #64                 // Method java/awt/image/BufferedImage."<init>":(III)V
      70: putstatic     #67                 // Field Ô00000:Ljava/awt/image/BufferedImage;
      73: return

  public com.fs.graphics.L();
    Code:
       0: aload_0
       1: invokespecial #71                 // Method java/lang/Object."<init>":()V
       4: return

  public static void Ö00000(java.lang.String);
    Code:
       0: getstatic     #51                 // Field class:Ljava/util/List;
       3: aload_0
       4: invokeinterface #76,  2           // InterfaceMethod java/util/List.add:(Ljava/lang/Object;)Z
       9: pop
      10: return

  public static void Ó00000(java.lang.String);
    Code:
       0: getstatic     #58                 // Field õ00000:Ljava/util/List;
       3: aload_0
       4: invokeinterface #76,  2           // InterfaceMethod java/util/List.add:(Ljava/lang/Object;)Z
       9: pop
      10: return

  public static byte[] new(java.lang.String);
    Code:
       0: getstatic     #58                 // Field õ00000:Ljava/util/List;
       3: aload_0
       4: invokeinterface #87,  2           // InterfaceMethod java/util/List.contains:(Ljava/lang/Object;)Z
       9: ifne          26
      12: getstatic     #60                 // Field new:Ljava/util/Map;
      15: aload_0
      16: invokeinterface #90,  2           // InterfaceMethod java/util/Map.containsKey:(Ljava/lang/Object;)Z
      21: ifne          26
      24: aconst_null
      25: areturn
      26: getstatic     #60                 // Field new:Ljava/util/Map;
      29: aload_0
      30: invokeinterface #95,  2           // InterfaceMethod java/util/Map.get:(Ljava/lang/Object;)Ljava/lang/Object;
      35: checkcast     #99                 // class "[B"
      38: astore_1
      39: aload_1
      40: ifnull        62
      43: aload_1
      44: getstatic     #30                 // Field Ö00000:[B
      47: if_acmpeq     62
      50: getstatic     #60                 // Field new:Ljava/util/Map;
      53: aload_0
      54: invokeinterface #100,  2          // InterfaceMethod java/util/Map.remove:(Ljava/lang/Object;)Ljava/lang/Object;
      59: pop
      60: aload_1
      61: areturn
      62: ldc2_w        #103                // long 10l
      65: invokestatic  #105                // Method java/lang/Thread.sleep:(J)V
      68: goto          0
      71: astore_2
      72: aconst_null
      73: areturn
    Exception table:
       from    to  target type
          62    68    71   Class java/lang/InterruptedException

  public static java.awt.image.BufferedImage class(java.lang.String);
    Code:
       0: getstatic     #51                 // Field class:Ljava/util/List;
       3: aload_0
       4: invokeinterface #87,  2           // InterfaceMethod java/util/List.contains:(Ljava/lang/Object;)Z
       9: ifne          26
      12: getstatic     #56                 // Field Ø00000:Ljava/util/Map;
      15: aload_0
      16: invokeinterface #90,  2           // InterfaceMethod java/util/Map.containsKey:(Ljava/lang/Object;)Z
      21: ifne          26
      24: aconst_null
      25: areturn
      26: getstatic     #56                 // Field Ø00000:Ljava/util/Map;
      29: aload_0
      30: invokeinterface #95,  2           // InterfaceMethod java/util/Map.get:(Ljava/lang/Object;)Ljava/lang/Object;
      35: checkcast     #62                 // class java/awt/image/BufferedImage
      38: astore_1
      39: aload_1
      40: ifnull        62
      43: aload_1
      44: getstatic     #67                 // Field Ô00000:Ljava/awt/image/BufferedImage;
      47: if_acmpeq     62
      50: getstatic     #56                 // Field Ø00000:Ljava/util/Map;
      53: aload_0
      54: invokeinterface #100,  2          // InterfaceMethod java/util/Map.remove:(Ljava/lang/Object;)Ljava/lang/Object;
      59: pop
      60: aload_1
      61: areturn
      62: ldc2_w        #103                // long 10l
      65: invokestatic  #105                // Method java/lang/Thread.sleep:(J)V
      68: goto          0
      71: astore_2
      72: aconst_null
      73: areturn
    Exception table:
       from    to  target type
          62    68    71   Class java/lang/InterruptedException

  public static void o00000();
    Code:
       0: new           #106                // class java/lang/Thread
       3: dup
       4: new           #121                // class com/fs/graphics/L$1
       7: dup
       8: invokespecial #123                // Method com/fs/graphics/L$1."<init>":()V
      11: invokespecial #124                // Method java/lang/Thread."<init>":(Ljava/lang/Runnable;)V
      14: putstatic     #127                // Field o00000:Ljava/lang/Thread;
      17: getstatic     #127                // Field o00000:Ljava/lang/Thread;
      20: invokevirtual #129                // Method java/lang/Thread.start:()V
      23: return

  public static void new();
    Code:
       0: getstatic     #127                // Field o00000:Ljava/lang/Thread;
       3: invokevirtual #133                // Method java/lang/Thread.interrupt:()V
       6: getstatic     #56                 // Field Ø00000:Ljava/util/Map;
       9: invokeinterface #136,  1          // InterfaceMethod java/util/Map.clear:()V
      14: getstatic     #60                 // Field new:Ljava/util/Map;
      17: invokeinterface #136,  1          // InterfaceMethod java/util/Map.clear:()V
      22: return

  private static java.awt.image.BufferedImage o00000(java.lang.String) throws java.io.IOException;
    Code:
       0: new           #143                // class java/io/BufferedInputStream
       3: dup
       4: invokestatic  #145                // Method com/fs/util/ooOOOOOOOOOOOOOOOOOOOOOOOOOOOOOOOOOOOOOOOOOOOOOOOOOOOOOOOOOOOOOOOOOOOOOOOOOOOOOOOOOOOOOOOOOOOOOOOOOOOOOOOOOOOOOOOOOOOOOOOOOOOOOOOOOOOOOOOOOOOOOOOOOOOOOOOOOOOOOOOOOOOOOOOOOOOOOOOOOOOOOOOOOOOOOOOOOOOOOOOOOOOOOOOOOOOOOOOOOOOOOOOOOOOOOOOOOOOOOOOOOOOOOOOOOOOOOO.Ó00000:()Lcom/fs/util/ooOOOOOOOOOOOOOOOOOOOOOOOOOOOOOOOOOOOOOOOOOOOOOOOOOOOOOOOOOOOOOOOOOOOOOOOOOOOOOOOOOOOOOOOOOOOOOOOOOOOOOOOOOOOOOOOOOOOOOOOOOOOOOOOOOOOOOOOOOOOOOOOOOOOOOOOOOOOOOOOOOOOOOOOOOOOOOOOOOOOOOOOOOOOOOOOOOOOOOOOOOOOOOOOOOOOOOOOOOOOOOOOOOOOOOOOOOOOOOOOOOOOOOOOOOOOOOO;
       7: aload_0
       8: invokevirtual #151                // Method com/fs/util/ooOOOOOOOOOOOOOOOOOOOOOOOOOOOOOOOOOOOOOOOOOOOOOOOOOOOOOOOOOOOOOOOOOOOOOOOOOOOOOOOOOOOOOOOOOOOOOOOOOOOOOOOOOOOOOOOOOOOOOOOOOOOOOOOOOOOOOOOOOOOOOOOOOOOOOOOOOOOOOOOOOOOOOOOOOOOOOOOOOOOOOOOOOOOOOOOOOOOOOOOOOOOOOOOOOOOOOOOOOOOOOOOOOOOOOOOOOOOOOOOOOOOOOOOOOOOOOO.String:(Ljava/lang/String;)Ljava/io/InputStream;
      11: invokespecial #155                // Method java/io/BufferedInputStream."<init>":(Ljava/io/InputStream;)V
      14: astore_1
      15: aload_1
      16: invokestatic  #158                // Method javax/imageio/ImageIO.read:(Ljava/io/InputStream;)Ljava/awt/image/BufferedImage;
      19: astore_2
      20: aload_1
      21: invokevirtual #164                // Method java/io/BufferedInputStream.close:()V
      24: aload_2
      25: areturn

  private static byte[] Ô00000(java.lang.String) throws java.io.IOException;
    Code:
       0: new           #143                // class java/io/BufferedInputStream
       3: dup
       4: invokestatic  #145                // Method com/fs/util/ooOOOOOOOOOOOOOOOOOOOOOOOOOOOOOOOOOOOOOOOOOOOOOOOOOOOOOOOOOOOOOOOOOOOOOOOOOOOOOOOOOOOOOOOOOOOOOOOOOOOOOOOOOOOOOOOOOOOOOOOOOOOOOOOOOOOOOOOOOOOOOOOOOOOOOOOOOOOOOOOOOOOOOOOOOOOOOOOOOOOOOOOOOOOOOOOOOOOOOOOOOOOOOOOOOOOOOOOOOOOOOOOOOOOOOOOOOOOOOOOOOOOOOOOOOOOOOO.Ó00000:()Lcom/fs/util/ooOOOOOOOOOOOOOOOOOOOOOOOOOOOOOOOOOOOOOOOOOOOOOOOOOOOOOOOOOOOOOOOOOOOOOOOOOOOOOOOOOOOOOOOOOOOOOOOOOOOOOOOOOOOOOOOOOOOOOOOOOOOOOOOOOOOOOOOOOOOOOOOOOOOOOOOOOOOOOOOOOOOOOOOOOOOOOOOOOOOOOOOOOOOOOOOOOOOOOOOOOOOOOOOOOOOOOOOOOOOOOOOOOOOOOOOOOOOOOOOOOOOOOOOOOOOOOO;
       7: aload_0
       8: invokevirtual #151                // Method com/fs/util/ooOOOOOOOOOOOOOOOOOOOOOOOOOOOOOOOOOOOOOOOOOOOOOOOOOOOOOOOOOOOOOOOOOOOOOOOOOOOOOOOOOOOOOOOOOOOOOOOOOOOOOOOOOOOOOOOOOOOOOOOOOOOOOOOOOOOOOOOOOOOOOOOOOOOOOOOOOOOOOOOOOOOOOOOOOOOOOOOOOOOOOOOOOOOOOOOOOOOOOOOOOOOOOOOOOOOOOOOOOOOOOOOOOOOOOOOOOOOOOOOOOOOOOOOOOOOOOO.String:(Ljava/lang/String;)Ljava/io/InputStream;
      11: invokespecial #155                // Method java/io/BufferedInputStream."<init>":(Ljava/io/InputStream;)V
      14: astore_1
      15: new           #171                // class java/io/ByteArrayOutputStream
      18: dup
      19: invokespecial #173                // Method java/io/ByteArrayOutputStream."<init>":()V
      22: astore_2
      23: iconst_0
      24: istore_3
      25: sipush        16384
      28: newarray       byte
      30: astore        4
      32: goto          43
      35: aload_2
      36: aload         4
      38: iconst_0
      39: iload_3
      40: invokevirtual #174                // Method java/io/ByteArrayOutputStream.write:([BII)V
      43: aload_1
      44: aload         4
      46: iconst_0
      47: aload         4
      49: arraylength
      50: invokevirtual #178                // Method java/io/BufferedInputStream.read:([BII)I
      53: dup
      54: istore_3
      55: iconst_m1
      56: if_icmpne     35
      59: aload_2
      60: invokevirtual #181                // Method java/io/ByteArrayOutputStream.flush:()V
      63: aload_2
      64: invokevirtual #184                // Method java/io/ByteArrayOutputStream.toByteArray:()[B
      67: areturn
}
