]633;E;echo '--- TextureLoader signatures ---';1f025ecb-b97e-48b6-b386-7953ca383313]633;C--- TextureLoader signatures ---
public class com.fs.graphics.TextureLoader {
  private java.util.HashMap ÔO0000;
  private java.awt.image.ColorModel OO0000;
  private java.awt.image.ColorModel Ø00000;
  private java.nio.IntBuffer Ô00000;
  private static org.apache.log4j.Logger ÓO0000;
  com.fs.graphics.I new;
  private static long ö00000;
  public static java.util.Set<java.lang.String> null;
  private int o00000;
  private int while;
  public static java.util.Map<java.lang.Class, java.lang.reflect.Method> float;
  public static java.util.Map<java.lang.Class, java.lang.reflect.Method> Ö00000;
  private java.awt.Color Ó00000;
  private java.awt.Color õ00000;
  private java.awt.Color interface;
  private static java.nio.ByteBuffer oO0000;
  private org.apache.log4j.Logger class;
  static {};
  public com.fs.graphics.TextureLoader();
  public void super(java.lang.String, java.lang.String) throws java.io.IOException;
  public void super(java.lang.String, java.awt.image.BufferedImage) throws java.io.IOException;
  private int Ò00000();
  public com.fs.graphics.Object super(java.lang.String) throws java.io.IOException;
  public com.fs.graphics.Object Ò00000(java.lang.String, java.awt.image.BufferedImage) throws java.io.IOException;
  public void super(com.fs.graphics.Object, java.lang.String) throws java.io.IOException;
  public void super(com.fs.graphics.Object) throws java.io.IOException;
  public com.fs.graphics.Object super(java.awt.image.BufferedImage, int, int, int, int) throws java.io.IOException;
  public com.fs.graphics.Object super(com.fs.graphics.Object, java.lang.String, int, int, int, int, boolean) throws java.io.IOException;
  public static void super(java.nio.ByteBuffer, java.lang.String);
  private java.nio.ByteBuffer Ò00000(java.lang.String) throws java.io.IOException;
  private int super(int);
  private java.nio.ByteBuffer super(java.awt.image.BufferedImage, com.fs.graphics.Object);
  private float super(float[], float);
  private float Ò00000(float[], float);
  private java.awt.image.BufferedImage String(java.lang.String) throws java.io.IOException;
  public void super(com.fs.graphics.I);
  public void Ó00000(java.lang.String);
  public java.util.HashMap super();
}

--- TextureLoader bytecode ---
public class com.fs.graphics.TextureLoader {
  private java.util.HashMap ÔO0000;

  private java.awt.image.ColorModel OO0000;

  private java.awt.image.ColorModel Ø00000;

  private java.nio.IntBuffer Ô00000;

  private static org.apache.log4j.Logger ÓO0000;

  com.fs.graphics.I new;

  private static long ö00000;

  public static java.util.Set<java.lang.String> null;

  private int o00000;

  private int while;

  public static java.util.Map<java.lang.Class, java.lang.reflect.Method> float;

  public static java.util.Map<java.lang.Class, java.lang.reflect.Method> Ö00000;

  private java.awt.Color Ó00000;

  private java.awt.Color õ00000;

  private java.awt.Color interface;

  private static java.nio.ByteBuffer oO0000;

  private org.apache.log4j.Logger class;

  static {};
    Code:
       0: ldc           #1                  // class com/fs/graphics/TextureLoader
       2: invokestatic  #39                 // Method org/apache/log4j/Logger.getLogger:(Ljava/lang/Class;)Lorg/apache/log4j/Logger;
       5: putstatic     #45                 // Field ÓO0000:Lorg/apache/log4j/Logger;
       8: lconst_0
       9: putstatic     #47                 // Field ö00000:J
      12: new           #49                 // class java/util/LinkedHashSet
      15: dup
      16: invokespecial #51                 // Method java/util/LinkedHashSet."<init>":()V
      19: putstatic     #54                 // Field null:Ljava/util/Set;
      22: new           #56                 // class java/util/LinkedHashMap
      25: dup
      26: invokespecial #58                 // Method java/util/LinkedHashMap."<init>":()V
      29: putstatic     #59                 // Field float:Ljava/util/Map;
      32: new           #56                 // class java/util/LinkedHashMap
      35: dup
      36: invokespecial #58                 // Method java/util/LinkedHashMap."<init>":()V
      39: putstatic     #61                 // Field Ö00000:Ljava/util/Map;
      42: aconst_null
      43: putstatic     #63                 // Field oO0000:Ljava/nio/ByteBuffer;
      46: return

  public com.fs.graphics.TextureLoader();
    Code:
       0: aload_0
       1: invokespecial #67                 // Method java/lang/Object."<init>":()V
       4: aload_0
       5: new           #68                 // class java/util/HashMap
       8: dup
       9: invokespecial #70                 // Method java/util/HashMap."<init>":()V
      12: putfield      #71                 // Field ÔO0000:Ljava/util/HashMap;
      15: aload_0
      16: iconst_1
      17: invokestatic  #73                 // Method org/lwjgl/BufferUtils.createIntBuffer:(I)Ljava/nio/IntBuffer;
      20: putfield      #79                 // Field Ô00000:Ljava/nio/IntBuffer;
      23: aload_0
      24: getstatic     #81                 // Field java/awt/Color.white:Ljava/awt/Color;
      27: putfield      #86                 // Field Ó00000:Ljava/awt/Color;
      30: aload_0
      31: getstatic     #81                 // Field java/awt/Color.white:Ljava/awt/Color;
      34: putfield      #88                 // Field õ00000:Ljava/awt/Color;
      37: aload_0
      38: getstatic     #81                 // Field java/awt/Color.white:Ljava/awt/Color;
      41: putfield      #90                 // Field interface:Ljava/awt/Color;
      44: aload_0
      45: aload_0
      46: invokevirtual #92                 // Method java/lang/Object.getClass:()Ljava/lang/Class;
      49: invokestatic  #39                 // Method org/apache/log4j/Logger.getLogger:(Ljava/lang/Class;)Lorg/apache/log4j/Logger;
      52: putfield      #96                 // Field class:Lorg/apache/log4j/Logger;
      55: aload_0
      56: new           #98                 // class java/awt/image/ComponentColorModel
      59: dup
      60: sipush        1000
      63: invokestatic  #100                // Method java/awt/color/ColorSpace.getInstance:(I)Ljava/awt/color/ColorSpace;
      66: iconst_4
      67: newarray       int
      69: dup
      70: iconst_0
      71: bipush        8
      73: iastore
      74: dup
      75: iconst_1
      76: bipush        8
      78: iastore
      79: dup
      80: iconst_2
      81: bipush        8
      83: iastore
      84: dup
      85: iconst_3
      86: bipush        8
      88: iastore
      89: iconst_1
      90: iconst_0
      91: iconst_3
      92: iconst_0
      93: invokespecial #106                // Method java/awt/image/ComponentColorModel."<init>":(Ljava/awt/color/ColorSpace;[IZZII)V
      96: putfield      #109                // Field OO0000:Ljava/awt/image/ColorModel;
      99: aload_0
     100: new           #98                 // class java/awt/image/ComponentColorModel
     103: dup
     104: sipush        1000
     107: invokestatic  #100                // Method java/awt/color/ColorSpace.getInstance:(I)Ljava/awt/color/ColorSpace;
     110: iconst_4
     111: newarray       int
     113: dup
     114: iconst_0
     115: bipush        8
     117: iastore
     118: dup
     119: iconst_1
     120: bipush        8
     122: iastore
     123: dup
     124: iconst_2
     125: bipush        8
     127: iastore
     128: iconst_0
     129: iconst_0
     130: iconst_1
     131: iconst_0
     132: invokespecial #106                // Method java/awt/image/ComponentColorModel."<init>":(Ljava/awt/color/ColorSpace;[IZZII)V
     135: putfield      #111                // Field Ø00000:Ljava/awt/image/ColorModel;
     138: return

  public void super(java.lang.String, java.lang.String) throws java.io.IOException;
    Code:
       0: aload_0
       1: getfield      #96                 // Field class:Lorg/apache/log4j/Logger;
       4: new           #120                // class java/lang/StringBuilder
       7: dup
       8: ldc           #122                // String Loading [
      10: invokespecial #124                // Method java/lang/StringBuilder."<init>":(Ljava/lang/String;)V
      13: aload_2
      14: invokevirtual #127                // Method java/lang/StringBuilder.append:(Ljava/lang/String;)Ljava/lang/StringBuilder;
      17: ldc           #131                // String ] as texture with id [
      19: invokevirtual #127                // Method java/lang/StringBuilder.append:(Ljava/lang/String;)Ljava/lang/StringBuilder;
      22: aload_1
      23: invokevirtual #127                // Method java/lang/StringBuilder.append:(Ljava/lang/String;)Ljava/lang/StringBuilder;
      26: ldc           #133                // String ]
      28: invokevirtual #127                // Method java/lang/StringBuilder.append:(Ljava/lang/String;)Ljava/lang/StringBuilder;
      31: invokevirtual #135                // Method java/lang/StringBuilder.toString:()Ljava/lang/String;
      34: invokevirtual #139                // Method org/apache/log4j/Logger.debug:(Ljava/lang/Object;)V
      37: aload_0
      38: aload_2
      39: invokevirtual #143                // Method super:(Ljava/lang/String;)Lcom/fs/graphics/Object;
      42: astore_3
      43: aload_3
      44: aload_1
      45: invokevirtual #147                // Method com/fs/graphics/Object.Ò00000:(Ljava/lang/String;)V
      48: aload_1
      49: aload_3
      50: invokestatic  #152                // Method com/fs/graphics/oOoO.o00000:(Ljava/lang/String;Lcom/fs/graphics/Object;)V
      53: return

  public void super(java.lang.String, java.awt.image.BufferedImage) throws java.io.IOException;
    Code:
       0: aload_0
       1: getfield      #96                 // Field class:Lorg/apache/log4j/Logger;
       4: new           #120                // class java/lang/StringBuilder
       7: dup
       8: ldc           #164                // String Loading image as [
      10: invokespecial #124                // Method java/lang/StringBuilder."<init>":(Ljava/lang/String;)V
      13: aload_1
      14: invokevirtual #127                // Method java/lang/StringBuilder.append:(Ljava/lang/String;)Ljava/lang/StringBuilder;
      17: ldc           #133                // String ]
      19: invokevirtual #127                // Method java/lang/StringBuilder.append:(Ljava/lang/String;)Ljava/lang/StringBuilder;
      22: invokevirtual #135                // Method java/lang/StringBuilder.toString:()Ljava/lang/String;
      25: invokevirtual #139                // Method org/apache/log4j/Logger.debug:(Ljava/lang/Object;)V
      28: aload_0
      29: aload_1
      30: aload_2
      31: invokevirtual #166                // Method Ò00000:(Ljava/lang/String;Ljava/awt/image/BufferedImage;)Lcom/fs/graphics/Object;
      34: astore_3
      35: aload_3
      36: aload_1
      37: invokevirtual #147                // Method com/fs/graphics/Object.Ò00000:(Ljava/lang/String;)V
      40: aload_1
      41: aload_3
      42: invokestatic  #152                // Method com/fs/graphics/oOoO.o00000:(Ljava/lang/String;Lcom/fs/graphics/Object;)V
      45: return

  private int Ò00000();
    Code:
       0: aload_0
       1: getfield      #79                 // Field Ô00000:Ljava/nio/IntBuffer;
       4: invokestatic  #173                // Method org/lwjgl/opengl/GL11.glGenTextures:(Ljava/nio/IntBuffer;)V
       7: aload_0
       8: getfield      #79                 // Field Ô00000:Ljava/nio/IntBuffer;
      11: iconst_0
      12: invokevirtual #179                // Method java/nio/IntBuffer.get:(I)I
      15: ireturn

  public com.fs.graphics.Object super(java.lang.String) throws java.io.IOException;
    Code:
       0: aload_0
       1: getfield      #71                 // Field ÔO0000:Ljava/util/HashMap;
       4: aload_1
       5: invokevirtual #185                // Method java/util/HashMap.get:(Ljava/lang/Object;)Ljava/lang/Object;
       8: checkcast     #148                // class com/fs/graphics/Object
      11: astore_2
      12: aload_2
      13: ifnull        18
      16: aload_2
      17: areturn
      18: invokestatic  #188                // Method com/fs/graphics/oOoO.class:()Z
      21: ifeq          54
      24: new           #148                // class com/fs/graphics/Object
      27: dup
      28: sipush        3553
      31: iconst_m1
      32: aload_1
      33: invokespecial #192                // Method com/fs/graphics/Object."<init>":(IILjava/lang/String;)V
      36: astore_2
      37: aload_2
      38: iconst_1
      39: invokevirtual #195                // Method com/fs/graphics/Object.o00000:(Z)V
      42: aload_0
      43: getfield      #71                 // Field ÔO0000:Ljava/util/HashMap;
      46: aload_1
      47: aload_2
      48: invokevirtual #199                // Method java/util/HashMap.put:(Ljava/lang/Object;Ljava/lang/Object;)Ljava/lang/Object;
      51: pop
      52: aload_2
      53: areturn
      54: aload_0
      55: aconst_null
      56: aload_1
      57: sipush        3553
      60: sipush        6408
      63: sipush        9729
      66: sipush        9729
      69: iconst_0
      70: invokevirtual #203                // Method super:(Lcom/fs/graphics/Object;Ljava/lang/String;IIIIZ)Lcom/fs/graphics/Object;
      73: astore_2
      74: aload_0
      75: getfield      #71                 // Field ÔO0000:Ljava/util/HashMap;
      78: aload_1
      79: aload_2
      80: invokevirtual #199                // Method java/util/HashMap.put:(Ljava/lang/Object;Ljava/lang/Object;)Ljava/lang/Object;
      83: pop
      84: aload_2
      85: areturn

  public com.fs.graphics.Object Ò00000(java.lang.String, java.awt.image.BufferedImage) throws java.io.IOException;
    Code:
       0: aload_0
       1: getfield      #71                 // Field ÔO0000:Ljava/util/HashMap;
       4: aload_1
       5: invokevirtual #185                // Method java/util/HashMap.get:(Ljava/lang/Object;)Ljava/lang/Object;
       8: checkcast     #148                // class com/fs/graphics/Object
      11: astore_3
      12: aload_3
      13: ifnull        18
      16: aload_3
      17: areturn
      18: invokestatic  #188                // Method com/fs/graphics/oOoO.class:()Z
      21: ifeq          54
      24: new           #148                // class com/fs/graphics/Object
      27: dup
      28: sipush        3553
      31: iconst_m1
      32: aload_1
      33: invokespecial #192                // Method com/fs/graphics/Object."<init>":(IILjava/lang/String;)V
      36: astore_3
      37: aload_3
      38: iconst_1
      39: invokevirtual #195                // Method com/fs/graphics/Object.o00000:(Z)V
      42: aload_0
      43: getfield      #71                 // Field ÔO0000:Ljava/util/HashMap;
      46: aload_1
      47: aload_3
      48: invokevirtual #199                // Method java/util/HashMap.put:(Ljava/lang/Object;Ljava/lang/Object;)Ljava/lang/Object;
      51: pop
      52: aload_3
      53: areturn
      54: aload_0
      55: aload_2
      56: sipush        3553
      59: sipush        6408
      62: sipush        9729
      65: sipush        9729
      68: invokevirtual #208                // Method super:(Ljava/awt/image/BufferedImage;IIII)Lcom/fs/graphics/Object;
      71: astore_3
      72: aload_0
      73: getfield      #71                 // Field ÔO0000:Ljava/util/HashMap;
      76: aload_1
      77: aload_3
      78: invokevirtual #199                // Method java/util/HashMap.put:(Ljava/lang/Object;Ljava/lang/Object;)Ljava/lang/Object;
      81: pop
      82: aload_3
      83: areturn

  public void super(com.fs.graphics.Object, java.lang.String) throws java.io.IOException;
    Code:
       0: invokestatic  #188                // Method com/fs/graphics/oOoO.class:()Z
       3: ifeq          17
       6: aload_1
       7: iconst_1
       8: invokevirtual #195                // Method com/fs/graphics/Object.o00000:(Z)V
      11: aload_1
      12: aload_2
      13: invokevirtual #213                // Method com/fs/graphics/Object.o00000:(Ljava/lang/String;)V
      16: return
      17: aload_0
      18: getfield      #96                 // Field class:Lorg/apache/log4j/Logger;
      21: ldc           #216                // String Loading image %s into existing tex id %d
      23: iconst_2
      24: anewarray     #3                  // class java/lang/Object
      27: dup
      28: iconst_0
      29: aload_2
      30: aastore
      31: dup
      32: iconst_1
      33: aload_1
      34: invokevirtual #218                // Method com/fs/graphics/Object.ö00000:()I
      37: invokestatic  #221                // Method java/lang/Integer.valueOf:(I)Ljava/lang/Integer;
      40: aastore
      41: invokestatic  #227                // Method java/lang/String.format:(Ljava/lang/String;[Ljava/lang/Object;)Ljava/lang/String;
      44: invokevirtual #139                // Method org/apache/log4j/Logger.debug:(Ljava/lang/Object;)V
      47: aload_0
      48: aload_1
      49: aload_2
      50: sipush        3553
      53: sipush        6408
      56: sipush        9729
      59: sipush        9729
      62: iconst_1
      63: invokevirtual #203                // Method super:(Lcom/fs/graphics/Object;Ljava/lang/String;IIIIZ)Lcom/fs/graphics/Object;
      66: pop
      67: aload_0
      68: getfield      #71                 // Field ÔO0000:Ljava/util/HashMap;
      71: aload_2
      72: aload_1
      73: invokevirtual #199                // Method java/util/HashMap.put:(Ljava/lang/Object;Ljava/lang/Object;)Ljava/lang/Object;
      76: pop
      77: return

  public void super(com.fs.graphics.Object) throws java.io.IOException;
    Code:
       0: invokestatic  #188                // Method com/fs/graphics/oOoO.class:()Z
       3: ifeq          12
       6: aload_1
       7: iconst_1
       8: invokevirtual #195                // Method com/fs/graphics/Object.o00000:(Z)V
      11: return
      12: aload_1
      13: invokevirtual #236                // Method com/fs/graphics/Object.Õ00000:()Ljava/lang/String;
      16: astore_2
      17: aload_2
      18: ifnonnull     31
      21: new           #239                // class java/lang/RuntimeException
      24: dup
      25: ldc           #241                // String Can\'t reload texture - was not loaded using a resourceName
      27: invokespecial #243                // Method java/lang/RuntimeException."<init>":(Ljava/lang/String;)V
      30: athrow
      31: aload_0
      32: aload_1
      33: aload_2
      34: invokevirtual #244                // Method super:(Lcom/fs/graphics/Object;Ljava/lang/String;)V
      37: return

  public com.fs.graphics.Object super(java.awt.image.BufferedImage, int, int, int, int) throws java.io.IOException;
    Code:
       0: iconst_0
       1: istore        6
       3: aload_0
       4: getfield      #246                // Field new:Lcom/fs/graphics/I;
       7: ifnull        21
      10: aload_0
      11: getfield      #246                // Field new:Lcom/fs/graphics/I;
      14: aload_1
      15: invokeinterface #248,  2          // InterfaceMethod com/fs/graphics/I.super:(Ljava/awt/image/BufferedImage;)Ljava/awt/image/BufferedImage;
      20: astore_1
      21: aload_0
      22: invokevirtual #253                // Method Ò00000:()I
      25: istore        7
      27: new           #148                // class com/fs/graphics/Object
      30: dup
      31: iload_2
      32: iload         7
      34: invokespecial #255                // Method com/fs/graphics/Object."<init>":(II)V
      37: astore        8
      39: iload_2
      40: iload         7
      42: invokestatic  #258                // Method com/fs/graphics/Object.o00000:(II)V
      45: aload         8
      47: aload_1
      48: invokevirtual #261                // Method java/awt/image/BufferedImage.getWidth:()I
      51: invokevirtual #266                // Method com/fs/graphics/Object.Ò00000:(I)V
      54: aload         8
      56: aload_1
      57: invokevirtual #270                // Method java/awt/image/BufferedImage.getHeight:()I
      60: invokevirtual #273                // Method com/fs/graphics/Object.o00000:(I)V
      63: aload_1
      64: invokevirtual #276                // Method java/awt/image/BufferedImage.getColorModel:()Ljava/awt/image/ColorModel;
      67: invokevirtual #280                // Method java/awt/image/ColorModel.hasAlpha:()Z
      70: ifeq          81
      73: sipush        6408
      76: istore        6
      78: goto          86
      81: sipush        6407
      84: istore        6
      86: aload_0
      87: aload_1
      88: aload         8
      90: invokevirtual #285                // Method super:(Ljava/awt/image/BufferedImage;Lcom/fs/graphics/Object;)Ljava/nio/ByteBuffer;
      93: astore        9
      95: aload         8
      97: aload_0
      98: getfield      #88                 // Field õ00000:Ljava/awt/Color;
     101: invokevirtual #289                // Method com/fs/graphics/Object.Object:(Ljava/awt/Color;)V
     104: aload         8
     106: aload_0
     107: getfield      #90                 // Field interface:Ljava/awt/Color;
     110: invokevirtual #293                // Method com/fs/graphics/Object.o00000:(Ljava/awt/Color;)V
     113: aload         8
     115: aload_0
     116: getfield      #86                 // Field Ó00000:Ljava/awt/Color;
     119: invokevirtual #296                // Method com/fs/graphics/Object.Ò00000:(Ljava/awt/Color;)V
     122: iload_2
     123: sipush        3553
     126: if_icmpne     147
     129: iload_2
     130: sipush        10241
     133: iload         4
     135: invokestatic  #299                // Method org/lwjgl/opengl/GL11.glTexParameteri:(III)V
     138: iload_2
     139: sipush        10240
     142: iload         5
     144: invokestatic  #299                // Method org/lwjgl/opengl/GL11.glTexParameteri:(III)V
     147: iload_2
     148: iconst_0
     149: iload_3
     150: aload_0
     151: aload_1
     152: invokevirtual #261                // Method java/awt/image/BufferedImage.getWidth:()I
     155: invokevirtual #303                // Method super:(I)I
     158: aload_0
     159: aload_1
     160: invokevirtual #270                // Method java/awt/image/BufferedImage.getHeight:()I
     163: invokevirtual #303                // Method super:(I)I
     166: iconst_0
     167: iload         6
     169: sipush        5121
     172: aload         9
     174: invokestatic  #306                // Method org/lwjgl/opengl/GL11.glTexImage2D:(IIIIIIIILjava/nio/ByteBuffer;)V
     177: getstatic     #47                 // Field ö00000:J
     180: aload         9
     182: invokevirtual #310                // Method java/nio/ByteBuffer.capacity:()I
     185: i2l
     186: ladd
     187: putstatic     #47                 // Field ö00000:J
     190: aload_0
     191: getfield      #96                 // Field class:Lorg/apache/log4j/Logger;
     194: ldc_w         #315                // String Loaded %.2f MB of texture data so far
     197: iconst_1
     198: anewarray     #3                  // class java/lang/Object
     201: dup
     202: iconst_0
     203: getstatic     #47                 // Field ö00000:J
     206: l2f
     207: ldc_w         #317                // float 1048576.0f
     210: fdiv
     211: invokestatic  #318                // Method java/lang/Float.valueOf:(F)Ljava/lang/Float;
     214: aastore
     215: invokestatic  #227                // Method java/lang/String.format:(Ljava/lang/String;[Ljava/lang/Object;)Ljava/lang/String;
     218: invokevirtual #139                // Method org/apache/log4j/Logger.debug:(Ljava/lang/Object;)V
     221: aload         9
     223: aload         8
     225: invokevirtual #323                // Method com/fs/graphics/Object.oO0000:()Ljava/lang/String;
     228: invokestatic  #326                // Method super:(Ljava/nio/ByteBuffer;Ljava/lang/String;)V
     231: aload         8
     233: areturn

  public com.fs.graphics.Object super(com.fs.graphics.Object, java.lang.String, int, int, int, int, boolean) throws java.io.IOException;
    Code:
       0: iconst_0
       1: istore        8
       3: aload_1
       4: ifnull        15
       7: aload_1
       8: invokevirtual #218                // Method com/fs/graphics/Object.ö00000:()I
      11: iconst_m1
      12: if_icmpne     33
      15: aload_0
      16: invokevirtual #253                // Method Ò00000:()I
      19: istore        9
      21: new           #148                // class com/fs/graphics/Object
      24: dup
      25: iload_3
      26: iload         9
      28: aload_2
      29: invokespecial #192                // Method com/fs/graphics/Object."<init>":(IILjava/lang/String;)V
      32: astore_1
      33: aload_1
      34: aload_2
      35: invokevirtual #213                // Method com/fs/graphics/Object.o00000:(Ljava/lang/String;)V
      38: aload_1
      39: invokevirtual #339                // Method com/fs/graphics/Object.Ø00000:()V
      42: aconst_null
      43: astore        9
      45: aload         9
      47: ifnonnull     170
      50: aload_0
      51: aload_2
      52: invokevirtual #341                // Method String:(Ljava/lang/String;)Ljava/awt/image/BufferedImage;
      55: astore        10
      57: aload_0
      58: aload         10
      60: invokevirtual #261                // Method java/awt/image/BufferedImage.getWidth:()I
      63: putfield      #345                // Field o00000:I
      66: aload_0
      67: aload         10
      69: invokevirtual #270                // Method java/awt/image/BufferedImage.getHeight:()I
      72: putfield      #347                // Field while:I
      75: aload_0
      76: getfield      #246                // Field new:Lcom/fs/graphics/I;
      79: ifnull        95
      82: aload_0
      83: getfield      #246                // Field new:Lcom/fs/graphics/I;
      86: aload         10
      88: invokeinterface #248,  2          // InterfaceMethod com/fs/graphics/I.super:(Ljava/awt/image/BufferedImage;)Ljava/awt/image/BufferedImage;
      93: astore        10
      95: aload_1
      96: aload         10
      98: invokevirtual #261                // Method java/awt/image/BufferedImage.getWidth:()I
     101: invokevirtual #266                // Method com/fs/graphics/Object.Ò00000:(I)V
     104: aload_1
     105: aload         10
     107: invokevirtual #270                // Method java/awt/image/BufferedImage.getHeight:()I
     110: invokevirtual #273                // Method com/fs/graphics/Object.o00000:(I)V
     113: aload         10
     115: invokevirtual #276                // Method java/awt/image/BufferedImage.getColorModel:()Ljava/awt/image/ColorModel;
     118: invokevirtual #280                // Method java/awt/image/ColorModel.hasAlpha:()Z
     121: ifeq          132
     124: sipush        6408
     127: istore        8
     129: goto          137
     132: sipush        6407
     135: istore        8
     137: aload_0
     138: aload         10
     140: aload_1
     141: invokevirtual #285                // Method super:(Ljava/awt/image/BufferedImage;Lcom/fs/graphics/Object;)Ljava/nio/ByteBuffer;
     144: astore        9
     146: aload_1
     147: aload_0
     148: getfield      #88                 // Field õ00000:Ljava/awt/Color;
     151: invokevirtual #289                // Method com/fs/graphics/Object.Object:(Ljava/awt/Color;)V
     154: aload_1
     155: aload_0
     156: getfield      #90                 // Field interface:Ljava/awt/Color;
     159: invokevirtual #293                // Method com/fs/graphics/Object.o00000:(Ljava/awt/Color;)V
     162: aload_1
     163: aload_0
     164: getfield      #86                 // Field Ó00000:Ljava/awt/Color;
     167: invokevirtual #296                // Method com/fs/graphics/Object.Ò00000:(Ljava/awt/Color;)V
     170: aload_0
     171: getfield      #345                // Field o00000:I
     174: sipush        1024
     177: if_icmpgt     194
     180: aload_0
     181: getfield      #347                // Field while:I
     184: sipush        1024
     187: if_icmpgt     194
     190: iconst_1
     191: goto          195
     194: iconst_0
     195: istore        10
     197: getstatic     #54                 // Field null:Ljava/util/Set;
     200: aload_2
     201: invokeinterface #349,  2          // InterfaceMethod java/util/Set.contains:(Ljava/lang/Object;)Z
     206: ifeq          212
     209: iconst_1
     210: istore        10
     212: iload         10
     214: ifeq          252
     217: iconst_0
     218: istore        7
     220: iload_3
     221: sipush        10241
     224: sipush        9987
     227: invokestatic  #299                // Method org/lwjgl/opengl/GL11.glTexParameteri:(III)V
     230: iload_3
     231: sipush        10240
     234: iload         6
     236: invokestatic  #299                // Method org/lwjgl/opengl/GL11.glTexParameteri:(III)V
     239: sipush        3553
     242: ldc_w         #355                // int 33169
     245: iconst_1
     246: invokestatic  #299                // Method org/lwjgl/opengl/GL11.glTexParameteri:(III)V
     249: goto          278
     252: iload_3
     253: sipush        10241
     256: iload         5
     258: invokestatic  #299                // Method org/lwjgl/opengl/GL11.glTexParameteri:(III)V
     261: iload_3
     262: sipush        10240
     265: iload         6
     267: invokestatic  #299                // Method org/lwjgl/opengl/GL11.glTexParameteri:(III)V
     270: iload_3
     271: ldc_w         #355                // int 33169
     274: iconst_0
     275: invokestatic  #299                // Method org/lwjgl/opengl/GL11.glTexParameteri:(III)V
     278: iload         7
     280: ifeq          316
     283: iload_3
     284: iconst_0
     285: iconst_0
     286: iconst_0
     287: aload_0
     288: aload_0
     289: getfield      #345                // Field o00000:I
     292: invokevirtual #303                // Method super:(I)I
     295: aload_0
     296: aload_0
     297: getfield      #347                // Field while:I
     300: invokevirtual #303                // Method super:(I)I
     303: iload         8
     305: sipush        5121
     308: aload         9
     310: invokestatic  #356                // Method org/lwjgl/opengl/GL11.glTexSubImage2D:(IIIIIIIILjava/nio/ByteBuffer;)V
     313: goto          347
     316: iload_3
     317: iconst_0
     318: iload         4
     320: aload_0
     321: aload_0
     322: getfield      #345                // Field o00000:I
     325: invokevirtual #303                // Method super:(I)I
     328: aload_0
     329: aload_0
     330: getfield      #347                // Field while:I
     333: invokevirtual #303                // Method super:(I)I
     336: iconst_0
     337: iload         8
     339: sipush        5121
     342: aload         9
     344: invokestatic  #306                // Method org/lwjgl/opengl/GL11.glTexImage2D:(IIIIIIIILjava/nio/ByteBuffer;)V
     347: getstatic     #47                 // Field ö00000:J
     350: aload         9
     352: invokevirtual #310                // Method java/nio/ByteBuffer.capacity:()I
     355: i2l
     356: ladd
     357: putstatic     #47                 // Field ö00000:J
     360: iload         10
     362: ifeq          383
     365: getstatic     #47                 // Field ö00000:J
     368: aload         9
     370: invokevirtual #310                // Method java/nio/ByteBuffer.capacity:()I
     373: i2f
     374: ldc_w         #359                // float 0.33f
     377: fmul
     378: f2l
     379: ladd
     380: putstatic     #47                 // Field ö00000:J
     383: aload_0
     384: getfield      #96                 // Field class:Lorg/apache/log4j/Logger;
     387: ldc_w         #315                // String Loaded %.2f MB of texture data so far
     390: iconst_1
     391: anewarray     #3                  // class java/lang/Object
     394: dup
     395: iconst_0
     396: getstatic     #47                 // Field ö00000:J
     399: l2f
     400: ldc_w         #317                // float 1048576.0f
     403: fdiv
     404: invokestatic  #318                // Method java/lang/Float.valueOf:(F)Ljava/lang/Float;
     407: aastore
     408: invokestatic  #227                // Method java/lang/String.format:(Ljava/lang/String;[Ljava/lang/Object;)Ljava/lang/String;
     411: invokevirtual #139                // Method org/apache/log4j/Logger.debug:(Ljava/lang/Object;)V
     414: aload         9
     416: aload_2
     417: invokestatic  #326                // Method super:(Ljava/nio/ByteBuffer;Ljava/lang/String;)V
     420: aload_1
     421: areturn

  public static void super(java.nio.ByteBuffer, java.lang.String);
    Code:
       0: aload_0
       1: getstatic     #63                 // Field oO0000:Ljava/nio/ByteBuffer;
       4: if_acmpne     8
       7: return
       8: getstatic     #59                 // Field float:Ljava/util/Map;
      11: aload_0
      12: invokevirtual #92                 // Method java/lang/Object.getClass:()Ljava/lang/Class;
      15: invokeinterface #363,  2          // InterfaceMethod java/util/Map.get:(Ljava/lang/Object;)Ljava/lang/Object;
      20: checkcast     #366                // class java/lang/reflect/Method
      23: astore_2
      24: aload_2
      25: ifnonnull     66
      28: aload_0
      29: invokevirtual #92                 // Method java/lang/Object.getClass:()Ljava/lang/Class;
      32: ldc_w         #368                // String cleaner
      35: iconst_0
      36: anewarray     #370                // class java/lang/Class
      39: invokevirtual #372                // Method java/lang/Class.getMethod:(Ljava/lang/String;[Ljava/lang/Class;)Ljava/lang/reflect/Method;
      42: astore_2
      43: aload_2
      44: ifnull        66
      47: aload_2
      48: iconst_1
      49: invokevirtual #376                // Method java/lang/reflect/Method.setAccessible:(Z)V
      52: getstatic     #59                 // Field float:Ljava/util/Map;
      55: aload_0
      56: invokevirtual #92                 // Method java/lang/Object.getClass:()Ljava/lang/Class;
      59: aload_2
      60: invokeinterface #379,  3          // InterfaceMethod java/util/Map.put:(Ljava/lang/Object;Ljava/lang/Object;)Ljava/lang/Object;
      65: pop
      66: aload_2
      67: ifnull        233
      70: aload_2
      71: aload_0
      72: iconst_0
      73: anewarray     #3                  // class java/lang/Object
      76: invokevirtual #380                // Method java/lang/reflect/Method.invoke:(Ljava/lang/Object;[Ljava/lang/Object;)Ljava/lang/Object;
      79: astore_3
      80: aload_3
      81: ifnull        210
      84: getstatic     #61                 // Field Ö00000:Ljava/util/Map;
      87: aload_3
      88: invokevirtual #92                 // Method java/lang/Object.getClass:()Ljava/lang/Class;
      91: invokeinterface #363,  2          // InterfaceMethod java/util/Map.get:(Ljava/lang/Object;)Ljava/lang/Object;
      96: checkcast     #366                // class java/lang/reflect/Method
      99: astore        4
     101: aload         4
     103: ifnonnull     148
     106: aload_3
     107: invokevirtual #92                 // Method java/lang/Object.getClass:()Ljava/lang/Class;
     110: ldc_w         #384                // String clean
     113: iconst_0
     114: anewarray     #370                // class java/lang/Class
     117: invokevirtual #372                // Method java/lang/Class.getMethod:(Ljava/lang/String;[Ljava/lang/Class;)Ljava/lang/reflect/Method;
     120: astore        4
     122: aload         4
     124: ifnull        148
     127: aload         4
     129: iconst_1
     130: invokevirtual #376                // Method java/lang/reflect/Method.setAccessible:(Z)V
     133: getstatic     #61                 // Field Ö00000:Ljava/util/Map;
     136: aload_3
     137: invokevirtual #92                 // Method java/lang/Object.getClass:()Ljava/lang/Class;
     140: aload         4
     142: invokeinterface #379,  3          // InterfaceMethod java/util/Map.put:(Ljava/lang/Object;Ljava/lang/Object;)Ljava/lang/Object;
     147: pop
     148: aload         4
     150: ifnull        187
     153: aload         4
     155: aload_3
     156: iconst_0
     157: anewarray     #3                  // class java/lang/Object
     160: invokevirtual #380                // Method java/lang/reflect/Method.invoke:(Ljava/lang/Object;[Ljava/lang/Object;)Ljava/lang/Object;
     163: pop
     164: getstatic     #45                 // Field ÓO0000:Lorg/apache/log4j/Logger;
     167: ldc_w         #386                // String Cleaned buffer for texture %s (using reflection)
     170: iconst_1
     171: anewarray     #3                  // class java/lang/Object
     174: dup
     175: iconst_0
     176: aload_1
     177: aastore
     178: invokestatic  #227                // Method java/lang/String.format:(Ljava/lang/String;[Ljava/lang/Object;)Ljava/lang/String;
     181: invokevirtual #388                // Method org/apache/log4j/Logger.info:(Ljava/lang/Object;)V
     184: goto          268
     187: getstatic     #45                 // Field ÓO0000:Lorg/apache/log4j/Logger;
     190: ldc_w         #391                // String Buffer for texture %s can not be destroyed
     193: iconst_1
     194: anewarray     #3                  // class java/lang/Object
     197: dup
     198: iconst_0
     199: aload_1
     200: aastore
     201: invokestatic  #227                // Method java/lang/String.format:(Ljava/lang/String;[Ljava/lang/Object;)Ljava/lang/String;
     204: invokevirtual #393                // Method org/apache/log4j/Logger.warn:(Ljava/lang/Object;)V
     207: goto          268
     210: getstatic     #45                 // Field ÓO0000:Lorg/apache/log4j/Logger;
     213: ldc_w         #391                // String Buffer for texture %s can not be destroyed
     216: iconst_1
     217: anewarray     #3                  // class java/lang/Object
     220: dup
     221: iconst_0
     222: aload_1
     223: aastore
     224: invokestatic  #227                // Method java/lang/String.format:(Ljava/lang/String;[Ljava/lang/Object;)Ljava/lang/String;
     227: invokevirtual #393                // Method org/apache/log4j/Logger.warn:(Ljava/lang/Object;)V
     230: goto          268
     233: getstatic     #45                 // Field ÓO0000:Lorg/apache/log4j/Logger;
     236: ldc_w         #391                // String Buffer for texture %s can not be destroyed
     239: iconst_1
     240: anewarray     #3                  // class java/lang/Object
     243: dup
     244: iconst_0
     245: aload_1
     246: aastore
     247: invokestatic  #227                // Method java/lang/String.format:(Ljava/lang/String;[Ljava/lang/Object;)Ljava/lang/String;
     250: invokevirtual #393                // Method org/apache/log4j/Logger.warn:(Ljava/lang/Object;)V
     253: goto          268
     256: astore_2
     257: getstatic     #45                 // Field ÓO0000:Lorg/apache/log4j/Logger;
     260: aload_2
     261: invokevirtual #396                // Method java/lang/Exception.getMessage:()Ljava/lang/String;
     264: aload_2
     265: invokevirtual #401                // Method org/apache/log4j/Logger.warn:(Ljava/lang/Object;Ljava/lang/Throwable;)V
     268: return
    Exception table:
       from    to  target type
           8   253   256   Class java/lang/Exception

  private java.nio.ByteBuffer Ò00000(java.lang.String) throws java.io.IOException;
    Code:
       0: aconst_null
       1: astore_2
       2: ldc           #1                  // class com/fs/graphics/TextureLoader
       4: invokevirtual #414                // Method java/lang/Class.getClassLoader:()Ljava/lang/ClassLoader;
       7: aload_1
       8: invokevirtual #418                // Method java/lang/ClassLoader.getResource:(Ljava/lang/String;)Ljava/net/URL;
      11: astore_3
      12: getstatic     #424                // Field java/lang/System.out:Ljava/io/PrintStream;
      15: aload_1
      16: invokevirtual #430                // Method java/io/PrintStream.println:(Ljava/lang/String;)V
      19: new           #435                // class java/io/BufferedInputStream
      22: dup
      23: new           #437                // class java/io/FileInputStream
      26: dup
      27: aload_1
      28: invokespecial #439                // Method java/io/FileInputStream."<init>":(Ljava/lang/String;)V
      31: invokespecial #440                // Method java/io/BufferedInputStream."<init>":(Ljava/io/InputStream;)V
      34: astore_2
      35: goto          90
      38: astore        4
      40: aload_3
      41: ifnull        59
      44: aload_0
      45: invokevirtual #92                 // Method java/lang/Object.getClass:()Ljava/lang/Class;
      48: invokevirtual #414                // Method java/lang/Class.getClassLoader:()Ljava/lang/ClassLoader;
      51: aload_1
      52: invokevirtual #443                // Method java/lang/ClassLoader.getResourceAsStream:(Ljava/lang/String;)Ljava/io/InputStream;
      55: astore_2
      56: goto          90
      59: new           #239                // class java/lang/RuntimeException
      62: dup
      63: new           #120                // class java/lang/StringBuilder
      66: dup
      67: ldc_w         #447                // String Error loading [
      70: invokespecial #124                // Method java/lang/StringBuilder."<init>":(Ljava/lang/String;)V
      73: aload_1
      74: invokevirtual #127                // Method java/lang/StringBuilder.append:(Ljava/lang/String;)Ljava/lang/StringBuilder;
      77: ldc_w         #449                // String ] image, url is null
      80: invokevirtual #127                // Method java/lang/StringBuilder.append:(Ljava/lang/String;)Ljava/lang/StringBuilder;
      83: invokevirtual #135                // Method java/lang/StringBuilder.toString:()Ljava/lang/String;
      86: invokespecial #243                // Method java/lang/RuntimeException."<init>":(Ljava/lang/String;)V
      89: athrow
      90: new           #451                // class de/matthiasmann/twl/utils/PNGDecoder
      93: dup
      94: aload_2
      95: invokespecial #453                // Method de/matthiasmann/twl/utils/PNGDecoder."<init>":(Ljava/io/InputStream;)V
      98: astore        4
     100: aload_0
     101: aload         4
     103: invokevirtual #454                // Method de/matthiasmann/twl/utils/PNGDecoder.getWidth:()I
     106: putfield      #345                // Field o00000:I
     109: aload_0
     110: aload         4
     112: invokevirtual #455                // Method de/matthiasmann/twl/utils/PNGDecoder.getHeight:()I
     115: putfield      #347                // Field while:I
     118: aload_0
     119: getfield      #345                // Field o00000:I
     122: aload_0
     123: aload_0
     124: getfield      #345                // Field o00000:I
     127: invokevirtual #303                // Method super:(I)I
     130: if_icmpne     148
     133: aload_0
     134: getfield      #347                // Field while:I
     137: aload_0
     138: aload_0
     139: getfield      #347                // Field while:I
     142: invokevirtual #303                // Method super:(I)I
     145: if_icmpeq     158
     148: aload_2
     149: ifnull        156
     152: aload_2
     153: invokevirtual #456                // Method java/io/InputStream.close:()V
     156: aconst_null
     157: areturn
     158: iconst_4
     159: aload_0
     160: getfield      #345                // Field o00000:I
     163: imul
     164: aload_0
     165: getfield      #347                // Field while:I
     168: imul
     169: invokestatic  #461                // Method java/nio/ByteBuffer.allocateDirect:(I)Ljava/nio/ByteBuffer;
     172: astore        5
     174: aload         4
     176: aload         5
     178: aload_0
     179: getfield      #345                // Field o00000:I
     182: iconst_4
     183: imul
     184: getstatic     #465                // Field de/matthiasmann/twl/utils/PNGDecoder$Format.RGBA:Lde/matthiasmann/twl/utils/PNGDecoder$Format;
     187: invokevirtual #471                // Method de/matthiasmann/twl/utils/PNGDecoder.decode:(Ljava/nio/ByteBuffer;ILde/matthiasmann/twl/utils/PNGDecoder$Format;)V
     190: aload         5
     192: invokevirtual #475                // Method java/nio/ByteBuffer.flip:()Ljava/nio/ByteBuffer;
     195: pop
     196: aload         5
     198: astore        7
     200: aload_2
     201: ifnull        208
     204: aload_2
     205: invokevirtual #456                // Method java/io/InputStream.close:()V
     208: aload         7
     210: areturn
     211: astore        6
     213: aload_2
     214: ifnull        221
     217: aload_2
     218: invokevirtual #456                // Method java/io/InputStream.close:()V
     221: aload         6
     223: athrow
    Exception table:
       from    to  target type
          12    35    38   Class java/lang/Exception
           2   148   211   any
         158   200   211   any

  private int super(int);
    Code:
       0: iconst_2
       1: istore_2
       2: goto          9
       5: iload_2
       6: iconst_2
       7: imul
       8: istore_2
       9: iload_2
      10: iload_1
      11: if_icmplt     5
      14: iload_2
      15: ireturn

  private java.nio.ByteBuffer super(java.awt.image.BufferedImage, com.fs.graphics.Object);
    Code:
       0: aconst_null
       1: astore_3
       2: iconst_2
       3: istore        6
       5: iconst_2
       6: istore        7
       8: goto          17
      11: iload         6
      13: iconst_2
      14: imul
      15: istore        6
      17: iload         6
      19: aload_1
      20: invokevirtual #261                // Method java/awt/image/BufferedImage.getWidth:()I
      23: if_icmplt     11
      26: goto          35
      29: iload         7
      31: iconst_2
      32: imul
      33: istore        7
      35: iload         7
      37: aload_1
      38: invokevirtual #270                // Method java/awt/image/BufferedImage.getHeight:()I
      41: if_icmplt     29
      44: aload_2
      45: iload         7
      47: invokevirtual #493                // Method com/fs/graphics/Object.Ô00000:(I)V
      50: aload_2
      51: iload         6
      53: invokevirtual #496                // Method com/fs/graphics/Object.Object:(I)V
      56: aload_0
      57: getstatic     #81                 // Field java/awt/Color.white:Ljava/awt/Color;
      60: putfield      #90                 // Field interface:Ljava/awt/Color;
      63: aload_0
      64: getstatic     #81                 // Field java/awt/Color.white:Ljava/awt/Color;
      67: putfield      #88                 // Field õ00000:Ljava/awt/Color;
      70: aload_0
      71: getstatic     #81                 // Field java/awt/Color.white:Ljava/awt/Color;
      74: putfield      #86                 // Field Ó00000:Ljava/awt/Color;
      77: fconst_0
      78: fstore        8
      80: fconst_0
      81: fstore        9
      83: fconst_0
      84: fstore        10
      86: fconst_0
      87: fstore        11
      89: sipush        256
      92: newarray       float
      94: astore        12
      96: sipush        256
      99: newarray       float
     101: astore        13
     103: sipush        256
     106: newarray       float
     108: astore        14
     110: aload_1
     111: invokevirtual #261                // Method java/awt/image/BufferedImage.getWidth:()I
     114: istore        15
     116: aload_1
     117: invokevirtual #270                // Method java/awt/image/BufferedImage.getHeight:()I
     120: istore        16
     122: aload_1
     123: invokevirtual #499                // Method java/awt/image/BufferedImage.getData:()Ljava/awt/image/Raster;
     126: astore        17
     128: aload_1
     129: invokevirtual #276                // Method java/awt/image/BufferedImage.getColorModel:()Ljava/awt/image/ColorModel;
     132: invokevirtual #280                // Method java/awt/image/ColorModel.hasAlpha:()Z
     135: ifeq          368
     138: iload         6
     140: iload         7
     142: imul
     143: iconst_4
     144: imul
     145: invokestatic  #503                // Method org/lwjgl/BufferUtils.createByteBuffer:(I)Ljava/nio/ByteBuffer;
     148: astore_3
     149: aload_3
     150: iconst_0
     151: invokevirtual #506                // Method java/nio/ByteBuffer.position:(I)Ljava/nio/ByteBuffer;
     154: pop
     155: aload_3
     156: aload_3
     157: invokevirtual #310                // Method java/nio/ByteBuffer.capacity:()I
     160: invokevirtual #509                // Method java/nio/ByteBuffer.limit:(I)Ljava/nio/ByteBuffer;
     163: pop
     164: iconst_4
     165: newarray       int
     167: astore        18
     169: iconst_0
     170: istore        19
     172: goto          358
     175: iconst_0
     176: istore        20
     178: goto          348
     181: aload         17
     183: iload         20
     185: iload         16
     187: iload         19
     189: isub
     190: iconst_1
     191: isub
     192: aload         18
     194: invokevirtual #512                // Method java/awt/image/Raster.getPixel:(II[I)[I
     197: pop
     198: aload         18
     200: iconst_3
     201: iaload
     202: ifne          208
     205: goto          345
     208: iload         19
     210: iload         6
     212: imul
     213: iload         20
     215: iadd
     216: iconst_4
     217: imul
     218: istore        21
     220: aload_3
     221: iload         21
     223: iconst_0
     224: iadd
     225: aload         18
     227: iconst_0
     228: iaload
     229: i2b
     230: invokevirtual #518                // Method java/nio/ByteBuffer.put:(IB)Ljava/nio/ByteBuffer;
     233: pop
     234: aload_3
     235: iload         21
     237: iconst_1
     238: iadd
     239: aload         18
     241: iconst_1
     242: iaload
     243: i2b
     244: invokevirtual #518                // Method java/nio/ByteBuffer.put:(IB)Ljava/nio/ByteBuffer;
     247: pop
     248: aload_3
     249: iload         21
     251: iconst_2
     252: iadd
     253: aload         18
     255: iconst_2
     256: iaload
     257: i2b
     258: invokevirtual #518                // Method java/nio/ByteBuffer.put:(IB)Ljava/nio/ByteBuffer;
     261: pop
     262: aload_3
     263: iload         21
     265: iconst_3
     266: iadd
     267: aload         18
     269: iconst_3
     270: iaload
     271: i2b
     272: invokevirtual #518                // Method java/nio/ByteBuffer.put:(IB)Ljava/nio/ByteBuffer;
     275: pop
     276: fload         8
     278: aload         18
     280: iconst_0
     281: iaload
     282: i2f
     283: fadd
     284: fstore        8
     286: fload         9
     288: aload         18
     290: iconst_1
     291: iaload
     292: i2f
     293: fadd
     294: fstore        9
     296: fload         10
     298: aload         18
     300: iconst_2
     301: iaload
     302: i2f
     303: fadd
     304: fstore        10
     306: aload         12
     308: aload         18
     310: iconst_0
     311: iaload
     312: dup2
     313: faload
     314: fconst_1
     315: fadd
     316: fastore
     317: aload         13
     319: aload         18
     321: iconst_1
     322: iaload
     323: dup2
     324: faload
     325: fconst_1
     326: fadd
     327: fastore
     328: aload         14
     330: aload         18
     332: iconst_2
     333: iaload
     334: dup2
     335: faload
     336: fconst_1
     337: fadd
     338: fastore
     339: fload         11
     341: fconst_1
     342: fadd
     343: fstore        11
     345: iinc          20, 1
     348: iload         20
     350: iload         15
     352: if_icmplt     181
     355: iinc          19, 1
     358: iload         19
     360: iload         16
     362: if_icmplt     175
     365: goto          648
     368: iload         15
     370: sipush        2048
     373: if_icmpne     415
     376: iload         16
     378: sipush        2048
     381: if_icmpne     415
     384: getstatic     #63                 // Field oO0000:Ljava/nio/ByteBuffer;
     387: ifnonnull     408
     390: iload         6
     392: iload         7
     394: imul
     395: iconst_3
     396: imul
     397: invokestatic  #503                // Method org/lwjgl/BufferUtils.createByteBuffer:(I)Ljava/nio/ByteBuffer;
     400: astore_3
     401: aload_3
     402: putstatic     #63                 // Field oO0000:Ljava/nio/ByteBuffer;
     405: goto          426
     408: getstatic     #63                 // Field oO0000:Ljava/nio/ByteBuffer;
     411: astore_3
     412: goto          426
     415: iload         6
     417: iload         7
     419: imul
     420: iconst_3
     421: imul
     422: invokestatic  #503                // Method org/lwjgl/BufferUtils.createByteBuffer:(I)Ljava/nio/ByteBuffer;
     425: astore_3
     426: aload_3
     427: iconst_0
     428: invokevirtual #506                // Method java/nio/ByteBuffer.position:(I)Ljava/nio/ByteBuffer;
     431: pop
     432: aload_3
     433: aload_3
     434: invokevirtual #310                // Method java/nio/ByteBuffer.capacity:()I
     437: invokevirtual #509                // Method java/nio/ByteBuffer.limit:(I)Ljava/nio/ByteBuffer;
     440: pop
     441: iconst_3
     442: newarray       int
     444: astore        18
     446: iconst_0
     447: istore        19
     449: goto          641
     452: iconst_0
     453: istore        20
     455: goto          631
     458: aload         17
     460: iload         20
     462: iload         16
     464: iload         19
     466: isub
     467: iconst_1
     468: isub
     469: aload         18
     471: invokevirtual #512                // Method java/awt/image/Raster.getPixel:(II[I)[I
     474: pop
     475: iload         19
     477: iload         6
     479: imul
     480: iload         20
     482: iadd
     483: iconst_3
     484: imul
     485: istore        21
     487: aload_3
     488: iload         21
     490: iconst_0
     491: iadd
     492: aload         18
     494: iconst_0
     495: iaload
     496: i2b
     497: invokevirtual #518                // Method java/nio/ByteBuffer.put:(IB)Ljava/nio/ByteBuffer;
     500: pop
     501: aload_3
     502: iload         21
     504: iconst_1
     505: iadd
     506: aload         18
     508: iconst_1
     509: iaload
     510: i2b
     511: invokevirtual #518                // Method java/nio/ByteBuffer.put:(IB)Ljava/nio/ByteBuffer;
     514: pop
     515: aload_3
     516: iload         21
     518: iconst_2
     519: iadd
     520: aload         18
     522: iconst_2
     523: iaload
     524: i2b
     525: invokevirtual #518                // Method java/nio/ByteBuffer.put:(IB)Ljava/nio/ByteBuffer;
     528: pop
     529: fload         8
     531: aload         18
     533: iconst_0
     534: iaload
     535: i2f
     536: fadd
     537: fstore        8
     539: fload         9
     541: aload         18
     543: iconst_1
     544: iaload
     545: i2f
     546: fadd
     547: fstore        9
     549: fload         10
     551: aload         18
     553: iconst_2
     554: iaload
     555: i2f
     556: fadd
     557: fstore        10
     559: aload         18
     561: iconst_0
     562: iaload
     563: sipush        256
     566: if_icmpge     622
     569: aload         18
     571: iconst_1
     572: iaload
     573: sipush        256
     576: if_icmpge     622
     579: aload         18
     581: iconst_2
     582: iaload
     583: sipush        256
     586: if_icmpge     622
     589: aload         12
     591: aload         18
     593: iconst_0
     594: iaload
     595: dup2
     596: faload
     597: fconst_1
     598: fadd
     599: fastore
     600: aload         13
     602: aload         18
     604: iconst_1
     605: iaload
     606: dup2
     607: faload
     608: fconst_1
     609: fadd
     610: fastore
     611: aload         14
     613: aload         18
     615: iconst_2
     616: iaload
     617: dup2
     618: faload
     619: fconst_1
     620: fadd
     621: fastore
     622: fload         11
     624: fconst_1
     625: fadd
     626: fstore        11
     628: iinc          20, 1
     631: iload         20
     633: iload         15
     635: if_icmplt     458
     638: iinc          19, 1
     641: iload         19
     643: iload         16
     645: if_icmplt     452
     648: fload         11
     650: fconst_0
     651: fcmpl
     652: ifle          1008
     655: fload         8
     657: fload         11
     659: fdiv
     660: f2i
     661: istore        18
     663: fload         9
     665: fload         11
     667: fdiv
     668: f2i
     669: istore        19
     671: fload         10
     673: fload         11
     675: fdiv
     676: f2i
     677: istore        20
     679: iload         18
     681: sipush        255
     684: if_icmple     692
     687: sipush        255
     690: istore        18
     692: iload         19
     694: sipush        255
     697: if_icmple     705
     700: sipush        255
     703: istore        19
     705: iload         20
     707: sipush        255
     710: if_icmple     718
     713: sipush        255
     716: istore        20
     718: iload         18
     720: ifge          726
     723: iconst_0
     724: istore        18
     726: iload         19
     728: ifge          734
     731: iconst_0
     732: istore        19
     734: iload         20
     736: ifge          742
     739: iconst_0
     740: istore        20
     742: aload_0
     743: new           #82                 // class java/awt/Color
     746: dup
     747: iload         18
     749: iload         19
     751: iload         20
     753: sipush        255
     756: invokespecial #521                // Method java/awt/Color."<init>":(IIII)V
     759: putfield      #88                 // Field õ00000:Ljava/awt/Color;
     762: ldc_w         #524                // float 0.5f
     765: fstore        21
     767: aload_0
     768: aload         12
     770: fload         11
     772: fload         21
     774: fmul
     775: invokevirtual #525                // Method Ò00000:([FF)F
     778: f2i
     779: istore        18
     781: aload_0
     782: aload         13
     784: fload         11
     786: fload         21
     788: fmul
     789: invokevirtual #525                // Method Ò00000:([FF)F
     792: f2i
     793: istore        19
     795: aload_0
     796: aload         14
     798: fload         11
     800: fload         21
     802: fmul
     803: invokevirtual #525                // Method Ò00000:([FF)F
     806: f2i
     807: istore        20
     809: iload         18
     811: sipush        255
     814: if_icmple     822
     817: sipush        255
     820: istore        18
     822: iload         19
     824: sipush        255
     827: if_icmple     835
     830: sipush        255
     833: istore        19
     835: iload         20
     837: sipush        255
     840: if_icmple     848
     843: sipush        255
     846: istore        20
     848: iload         18
     850: ifge          856
     853: iconst_0
     854: istore        18
     856: iload         19
     858: ifge          864
     861: iconst_0
     862: istore        19
     864: iload         20
     866: ifge          872
     869: iconst_0
     870: istore        20
     872: aload_0
     873: new           #82                 // class java/awt/Color
     876: dup
     877: iload         18
     879: iload         19
     881: iload         20
     883: sipush        255
     886: invokespecial #521                // Method java/awt/Color."<init>":(IIII)V
     889: putfield      #90                 // Field interface:Ljava/awt/Color;
     892: aload_0
     893: aload         12
     895: fload         11
     897: invokevirtual #529                // Method super:([FF)F
     900: f2i
     901: istore        18
     903: aload_0
     904: aload         13
     906: fload         11
     908: invokevirtual #529                // Method super:([FF)F
     911: f2i
     912: istore        19
     914: aload_0
     915: aload         14
     917: fload         11
     919: invokevirtual #525                // Method Ò00000:([FF)F
     922: f2i
     923: istore        20
     925: iload         18
     927: sipush        255
     930: if_icmple     938
     933: sipush        255
     936: istore        18
     938: iload         19
     940: sipush        255
     943: if_icmple     951
     946: sipush        255
     949: istore        19
     951: iload         20
     953: sipush        255
     956: if_icmple     964
     959: sipush        255
     962: istore        20
     964: iload         18
     966: ifge          972
     969: iconst_0
     970: istore        18
     972: iload         19
     974: ifge          980
     977: iconst_0
     978: istore        19
     980: iload         20
     982: ifge          988
     985: iconst_0
     986: istore        20
     988: aload_0
     989: new           #82                 // class java/awt/Color
     992: dup
     993: iload         18
     995: iload         19
     997: iload         20
     999: sipush        255
    1002: invokespecial #521                // Method java/awt/Color."<init>":(IIII)V
    1005: putfield      #86                 // Field Ó00000:Ljava/awt/Color;
    1008: aload_3
    1009: areturn

  private float super(float[], float);
    Code:
       0: fconst_0
       1: fstore_3
       2: fload_2
       3: ldc_w         #524                // float 0.5f
       6: fmul
       7: fstore        4
       9: iconst_0
      10: istore        5
      12: goto          40
      15: aload_1
      16: iload         5
      18: faload
      19: fstore        6
      21: fload_3
      22: fload         6
      24: fadd
      25: fstore_3
      26: fload_3
      27: fload         4
      29: fcmpl
      30: iflt          37
      33: iload         5
      35: i2f
      36: freturn
      37: iinc          5, 1
      40: iload         5
      42: sipush        255
      45: if_icmple     15
      48: fconst_0
      49: freturn

  private float Ò00000(float[], float);
    Code:
       0: fconst_0
       1: fstore_3
       2: fconst_0
       3: fstore        4
       5: sipush        255
       8: istore        5
      10: goto          65
      13: aload_1
      14: iload         5
      16: faload
      17: fstore        6
      19: fload         6
      21: fstore        7
      23: fload_3
      24: fload         6
      26: fadd
      27: fload_2
      28: fcmpl
      29: iflt          37
      32: fload_2
      33: fload_3
      34: fsub
      35: fstore        7
      37: fload_3
      38: fload         7
      40: fadd
      41: fstore_3
      42: fload         4
      44: iload         5
      46: i2f
      47: fload         7
      49: fmul
      50: fadd
      51: fstore        4
      53: fload_3
      54: fload_2
      55: fcmpl
      56: iflt          62
      59: goto          70
      62: iinc          5, -1
      65: iload         5
      67: ifge          13
      70: fload_3
      71: fconst_0
      72: fcmpl
      73: ifle          81
      76: fload         4
      78: fload_3
      79: fdiv
      80: freturn
      81: fconst_0
      82: freturn

  private java.awt.image.BufferedImage String(java.lang.String) throws java.io.IOException;
    Code:
       0: aload_1
       1: invokestatic  #565                // Method com/fs/graphics/L.class:(Ljava/lang/String;)Ljava/awt/image/BufferedImage;
       4: astore_2
       5: aload_2
       6: ifnull        11
       9: aload_2
      10: areturn
      11: new           #435                // class java/io/BufferedInputStream
      14: dup
      15: invokestatic  #570                // Method com/fs/util/ooOOOOOOOOOOOOOOOOOOOOOOOOOOOOOOOOOOOOOOOOOOOOOOOOOOOOOOOOOOOOOOOOOOOOOOOOOOOOOOOOOOOOOOOOOOOOOOOOOOOOOOOOOOOOOOOOOOOOOOOOOOOOOOOOOOOOOOOOOOOOOOOOOOOOOOOOOOOOOOOOOOOOOOOOOOOOOOOOOOOOOOOOOOOOOOOOOOOOOOOOOOOOOOOOOOOOOOOOOOOOOOOOOOOOOOOOOOOOOOOOOOOOOOOOOOOOOO.Ó00000:()Lcom/fs/util/ooOOOOOOOOOOOOOOOOOOOOOOOOOOOOOOOOOOOOOOOOOOOOOOOOOOOOOOOOOOOOOOOOOOOOOOOOOOOOOOOOOOOOOOOOOOOOOOOOOOOOOOOOOOOOOOOOOOOOOOOOOOOOOOOOOOOOOOOOOOOOOOOOOOOOOOOOOOOOOOOOOOOOOOOOOOOOOOOOOOOOOOOOOOOOOOOOOOOOOOOOOOOOOOOOOOOOOOOOOOOOOOOOOOOOOOOOOOOOOOOOOOOOOOOOOOOOOO;
      18: aload_1
      19: invokevirtual #575                // Method com/fs/util/ooOOOOOOOOOOOOOOOOOOOOOOOOOOOOOOOOOOOOOOOOOOOOOOOOOOOOOOOOOOOOOOOOOOOOOOOOOOOOOOOOOOOOOOOOOOOOOOOOOOOOOOOOOOOOOOOOOOOOOOOOOOOOOOOOOOOOOOOOOOOOOOOOOOOOOOOOOOOOOOOOOOOOOOOOOOOOOOOOOOOOOOOOOOOOOOOOOOOOOOOOOOOOOOOOOOOOOOOOOOOOOOOOOOOOOOOOOOOOOOOOOOOOOOOOOOOOOO.String:(Ljava/lang/String;)Ljava/io/InputStream;
      22: invokespecial #440                // Method java/io/BufferedInputStream."<init>":(Ljava/io/InputStream;)V
      25: invokestatic  #578                // Method javax/imageio/ImageIO.read:(Ljava/io/InputStream;)Ljava/awt/image/BufferedImage;
      28: areturn

  public void super(com.fs.graphics.I);
    Code:
       0: aload_0
       1: aload_1
       2: putfield      #246                // Field new:Lcom/fs/graphics/I;
       5: return

  public void Ó00000(java.lang.String);
    Code:
       0: aload_0
       1: getfield      #71                 // Field ÔO0000:Ljava/util/HashMap;
       4: aload_1
       5: invokevirtual #588                // Method java/util/HashMap.remove:(Ljava/lang/Object;)Ljava/lang/Object;
       8: pop
       9: return

  public java.util.HashMap super();
    Code:
       0: aload_0
       1: getfield      #71                 // Field ÔO0000:Ljava/util/HashMap;
       4: areturn
}
